Workbook
Name Men_Group_A_Result_Table: Rankings!$B$3:$F$6
Name Men_Group_B_Result_Table: Rankings!$B$10:$F$13
Name Men_Group_B_Result_Table: #REF!
Name MenFieldPlayers: _xlfn.ANCHORARRAY('MVP Voting'!$V$2)
Name MenGoalkeepers: _xlfn.ANCHORARRAY('MVP Voting'!$X$2)
Name Women_Result_Table: Rankings!$B$17:$F$21
Name Women_Result_Table: #REF!
Name WomenFieldPlayers: _xlfn.ANCHORARRAY('MVP Voting'!$W$2)
Name WomenGoalkeepers: _xlfn.ANCHORARRAY('MVP Voting'!$Y$2)

Sheet ----- NAVIGATION -----
A1: 🧭 BAY CLASSIC 2027: WORKBOOK NAVIGATION
A2: Click any sheet name below to jump straight there. New to this workbook? Start with the Admin Manual.
A4: START HERE
B5: Control Panel | C5: Live dashboard: registration, finance, games, current leaders. Open this first every time.
B6: Admin Manual | C6: Full step-by-step guide for running the tournament in this workbook.
B7: Volunteer Guide | C7: Quick guide for volunteers (non-organizers).
B8: Model Notes | C8: Running log of cleanup/action items for the model itself (organizer use only).
A10: MASTER DATA
B11: Inputs | C11: All tournament settings: dates, times, fee, capacity, venue. Change things here first.
B12: Format Engine | C12: Internal engine that builds the schedule shape from your format choice. Don't edit.
B13: Standings Engine | C13: Internal ranking calculations. Don't edit: see Rankings for the readable output.
B14: Teams Master | C14: Master list of all teams, divisions, group codes, jerseys, contacts.
B15: Referees Master | C15: Referee roster and pairings.
B16: Medical Staff Master | C16: Medical staff (physio / athletic trainer) roster, hours and pay.
B17: Products Master | C17: Concession product list: cost, price, margin.
A19: REGISTRATION
B20: Registration 2027 | C20: Team invitations, deposits, payments, roster status & capacity settings
A22: GAME OPERATIONS
B23: Games Schedule | C23: The schedule engine: matchups, times, scores, referees, volunteers.
B24: Group Draw | C24: Randomized group draw tool; locks codes into Teams Master.
B25: Printable Schedule | C25: Clean printable version of the schedule.
B26: Rankings | C26: Group standings, calculated automatically from scores.
B27: Final Rankings | C27: Final tournament placings and awards.
A29: TEAM ROSTERS
B30: Rosters Master | C30: All team rosters in one place.
B31: Roster Template | C31: Blank template teams use to submit rosters.
A33: STATISTICS & MVP
B34: Stats & MVP | C34: Top scorers and MVP/MVG leaders, calculated automatically.
B35: Individuals Stats Men | C35: Enter men's goals per game per player.
B36: Individuals Stats Women | C36: Enter women's goals per game per player.
B37: Voters Master | C37: List of eligible MVP voters.
B38: Officials Contacts | C38: Contact info for team officials.
B39: MVP Voting | C39: Enter MVP / MVG votes.
A41: VOLUNTEERS
B42: Volunteer Master List | C42: Master volunteer list; hours auto-tally from the assignment sheets.
B43: Gym Prep | C43: Gym setup/teardown volunteer assignments.
B44: Referee Pickup Drop Off | C44: Referee transportation volunteer assignments.
A46: FINANCE
B47: Budget Dashboard | C47: Multi-year P&L: income, expenses, net profit, variance.
B48: Multi Year Financial Summary | C48: Detailed year-by-year actuals (source of truth for Budget Dashboard).
B49: Operations Costs | C49: Budget vs. actual detail for operational costs (referees, physio, etc.).
B50: Concession Projection Details | C50: Concession sales projections by item.
B51: Concession purchase list | C51: Concession shopping list: what to buy, how much.
B52: Price List Concession | C52: Printable concession menu with prices.
B53: Merch Pre-Order (COGS) | C53: Commemorative hoodie/hat/bundle: unit economics, pre-order revenue & COGS from the Pre-orders tab, forecast P&L.
B54: Pre-orders | C54: Merchandise pre-orders, entered manually (one row per order).
A55: TEMPLATES
B56: Game Sheet | C56: Printable one-page officials' sheet: pick a game #, everything else fills in.

Sheet Control Panel
B2: 🏆 BAY CLASSIC 2027: CONTROL PANEL | F2: TOURNAMENT FORMAT | G2: 8M+4W | H2: 📖 New here? Open the Admin Manual
B3: ="Tournament starts "&TEXT(Inputs!C22,"dddd, mmm d, yyyy")&" • "&Inputs!C23 | F3: Configuration | G3: =Inputs!C13&" teams ("&Inputs!C14&"M / "&Inputs!C15&"W)" | H3: 🧭 See full workbook map
B4: Everything on this page calculates automatically: nothing to type here. Change settings on Inputs; log scores on Games Schedule.
B5: REGISTRATION | F5: CURRENT LEADERS
B6: Teams Registered | C6: =COUNTIF('Registration 2027'!$J$2:$J$40,"Fully Registered")+COUNTIF('Registration 2027'!$J$2:$J$40,"Host Registered") | D6: ="of "&Inputs!C13&" max" | F6: Top Scorer (M) | G6: ='Stats & MVP'!B6&": "&'Stats & MVP'!D6&" goals"
B7: Fees Collected | C7: =SUM('Registration 2027'!$H$2:$H$40) | D7: ="of "&TEXT(Inputs!C18*(Inputs!C13-'Registration 2027'!$R$9),"$#,##0")&" expected" | F7: Top Scorer (W) | G7: ='Stats & MVP'!B15&": "&'Stats & MVP'!D15&" goals"
F8: MVP (M) | G8: ='Stats & MVP'!G8
B9: FINANCE (2027 Budget) | F9: MVP (W) | G9: ='Stats & MVP'!G9
B10: Total Income | C10: ='Budget Dashboard'!A5
B11: Total Expenses | C11: ='Budget Dashboard'!B5 | F11: GROUP LEADERS
B12: Net Profit | C12: ='Budget Dashboard'!C5 | F12: Group A | G12: =Rankings!B3
F13: Group B | G13: =Rankings!B10
B14: GAMES | F14: Women | G14: =Rankings!B17
B15: Total Games | C15: =COUNT('Games Schedule'!$C$5:$C$31)
B16: Games Played | C16: {=SUMPRODUCT((('Games Schedule'!$S$5:$S$31+'Games Schedule'!$T$5:$T$31)>0)*1)}
B17: Goals Scored | C17: =SUM('Games Schedule'!$S$5:$T$31)
B19: PAYMENT TRACKER
B20: Status | C20: Teams
B21: Fully Registered | C21: =COUNTIF('Registration 2027'!$J$2:$J$40,"Fully Registered")
B22: Host Registered | C22: =COUNTIF('Registration 2027'!$J$2:$J$40,"Host Registered")
B23: Deposit Paid only | C23: =COUNTIF('Registration 2027'!$J$2:$J$40,"Deposit Paid")
B24: Not Registered | C24: =COUNTIF('Registration 2027'!$A$2:$A$40,"?*")-C21-C22-C23

Sheet Model Notes
A1: Bay Classic 2027: Model Notes & Action Items
A2: Open items to revisit, clean up, automate, or link. Example rows show how to use the log; replace them with your own.
A4: # | B4: Item | C4: Category | D4: Location | E4: Suggested action / status
A5: 1 | B5: Assign referee pairs to playoff games | C5: Revisit | D5: Games Schedule P23:P28 | E5: OPEN: pick a pair from the box at P34 once group standings are final. Q40 should read 0 and the conflict check at P43 should stay clear.
A6: 2 | B6: Confirm medical staff hours | C6: Revisit | D6: Medical Staff Master / Games Schedule AA | E6: OPEN: make sure every game has a name in col AA. Hours and pay update automatically on Medical Staff Master.
A7: 3 | B7: Reconcile final payments | C7: Clean up | D7: Registration 2027 cols E:H | E7: IN PROGRESS: enter the Final Pay Date as each balance arrives. Status and Fees Collected update by themselves.
A8: 4 | B8: Collect missing rosters | C8: Revisit | D8: Registration 2027 col I / Rosters Master | E8: OPEN: chase any team without an "x" in Roster Submitted before the draw, then paste the roster into its block.
A9: 5 | B9: Lock the group draw | C9: Link | D9: Group Draw I6:I18 to Teams Master E | E9: DONE: codes pasted as values into Teams Master col E, so the schedule no longer changes on recalculation.
A10: 6 | B10: Update concession prices | C10: Clean up | D10: Products Master | E10: DONE: COGS and sale prices reviewed. Price List Concession picks them up automatically.
A11: 7 | B11: Book referee travel | C11: Revisit | D11: Referees Master / Referee Pickup Drop Off | E11: OPEN: type flight and hotel costs as they are booked, and add airport pickup times and drivers.
A12: 8 | B12: Review budget vs actuals after the event | C12: Revisit | D12: Budget Dashboard col I | E12: OPEN: type 2027 actuals as money comes in or goes out, then compare with the 2027 Budget column.
A17: Completed this review (for reference)
A18: ✓ Group codes locked into Teams Master after the public draw.
A19: ✓ Referee pair labels checked against Referees Master col T.
A20: ✓ Volunteer and medical staff names match the dropdown lists on Games Schedule.
A21: ✓ Inputs reviewed: start date, fee, deposit %, venue and daily start times.

Sheet Admin Manual
A1: BAY CLASSIC 2027: ORGANIZER ADMIN MANUAL
A2: Master operating guide for the tournament workbook. Read the Executive Summary first, then jump to the function you need.
A4: 1. EXECUTIVE SUMMARY
A5: What this workbook does | B5: Runs the entire tournament from one file: registration & payments, the group draw, the game schedule, scores & rankings, player stats & MVP voting, volunteer assignments, concessions, and the full multi-year budget.
A6: The big idea | B6: It is DRIVER-BASED. You type a small number of inputs in a few designated places; everything else is formulas that recalculate automatically. You almost never edit calculated cells.
A7: The 3 places you actually type | B7: 1) INPUTS sheet: all tournament settings (dates, times, fee, capacity, venue). 2) The MASTER DATA tables: Teams, Referees, Rosters, Products, Medical Staff. 3) A few clearly marked entry cells: game scores, player goals, MVP votes, volunteer names.
A8: Where to look at a glance | B8: CONTROL PANEL: live dashboard of registration, finance, games and current leaders. Open this first every time to see tournament status at a glance.
A9: Golden rule | B9: If a cell already contains a formula (it calculates a result), DO NOT overwrite it. Only edit input cells. The font color tells you which is which; see Section 5.
A11: 2. HOW THE MODEL WORKS (data flow)
A12: Read this top-to-bottom: each layer feeds the next. Change something upstream and everything downstream follows.
A13: Layer | B13: Sheets | C13: Feeds into →
A14: 1. INPUTS (settings) | B14: Inputs | C14: Games Schedule (dates/times), Registration & Budget (fee/capacity), Game Sheet (venue), Control Panel.
A15: 2. MASTER DATA | B15: Teams Master, Referees Master, Rosters Master, Products Master, Medical Staff Master | C15: Group Draw & Games Schedule (team names), Game Sheet (rosters/refs), Concession (products), Budget (medical staff).
A16: 3. REGISTRATION | B16: Registration 2027 | C16: Control Panel (teams registered, fees collected), Budget Dashboard (paying-team count drives 2027 income).
A17: 4. DRAW | B17: Group Draw | C17: Writes Group Codes into Teams Master → which feed Games Schedule team matchups.
A18: 5. GAME OPERATIONS | B18: Games Schedule (engine), Printable Schedule, Game Sheet | C18: Rankings (from scores), Stats, Control Panel. Game Sheet pulls from Schedule + Rosters.
A19: 6. RESULTS | B19: Rankings, Final Rankings, Stats & MVP, Individuals Stats, MVP Voting | C19: Control Panel leaders, Final Rankings awards, jersey-color logic in Games Schedule.
A20: 7. VOLUNTEERS | B20: Volunteer Master List, Gym Prep, Referee Pickup Drop Off (Merch Booth assignment is a column on Games Schedule, not a separate sheet) | C20: Hours auto-tally on the Volunteer Master List from the assignment sheets.
A21: 8. FINANCE | B21: Budget Dashboard, Multi Year Financial Summary, Operations Costs, Concession sheets, Price List | C21: Control Panel finance KPIs. Concession detail rolls up into the Budget Dashboard.
A23: 3. WHERE TO START (setup order for a new year)
A24: Do these in order. Each step assumes the one above is done.
A25: Step | B25: Do this | C25: On this sheet
A26: 1 | B26: Set tournament settings: start date, venue, fee, capacity, daily start times, game durations. | C26: Inputs (blue cells C6:C29)
A27: 2 | B27: Confirm / update the team list, referees, and medical staff (physio / athletic trainer) for the year. Give every team a Short Name & jersey colors in the Team Styles table (Teams Master, cols O:R). | C27: Teams Master, Referees Master, Medical Staff Master
A28: 3 | B28: Track invitations, deposits and final payments as teams confirm. | C28: Registration 2027
A29: 4 | B29: Run the group draw and lock the Group Codes into Teams Master. | C29: Group Draw → Teams Master
A30: 5 | B30: Verify the auto-built schedule (matchups, times, referee pairs) reads correctly. | C30: Games Schedule
A31: 6 | B31: Load rosters, assign volunteers, set up concession products & pricing. | C31: Rosters Master, volunteer sheets, Products/Price List
A32: 7 | B32: During the event: enter scores, goals, votes, and mark volunteer presence. | C32: Games Schedule, Individuals Stats, MVP Voting
A33: 8 | B33: After: confirm final rankings & awards, reconcile actuals in the budget. | C33: Final Rankings, Budget Dashboard
A35: 4. FUNCTION RECIPES
A36: Each block: a one-line summary, where the drivers are, then click-by-click steps.
A38: ▶ 4.1 SET TOURNAMENT SETTINGS
A39: Summary | B39: All global settings live on the Inputs sheet. Change them here and dates, times, fees and capacity update everywhere automatically.
A40: Drivers | B40: Inputs sheet, blue cells: game minutes C6:C9 · capacity C13:C14 · fee C18 · deposit % C19 · start date C22 · venue C23 · daily start times C26:C29.
A41: Steps | B41: 1. Open Inputs. 2. Edit only the yellow/blue cells in column C. 3. Set Tournament Start Date (C22): Day 1; all game dates flow from this. 4. Set the first court time for each day (C26:C29). 5. Done: Games Schedule, Control Panel and Budget recalculate automatically.
A43: ▶ 4.2 BUILD / VERIFY THE SCHEDULE
A44: Summary | B44: The Games Schedule is the engine. Game numbers, dates and all the clock times (court, game, halftime, second half, end) are calculated. Matchups come from Group Codes; team names, jersey colors and referee pairs auto-resolve.
A45: Drivers | B45: Times ← Inputs. Matchups ← 'Code Team A' col L & 'Code Team B' col M (you set these codes). Names ← Teams Master. Jerseys ← Rankings. Referees typed in col P.
A46: Steps | B46: 1. Set times via Inputs (recipe 4.1): do NOT type clock times directly here. 2. In cols L & M, enter each game's Group Codes (e.g. A1 vs A2). Team names in N & O fill automatically. 3. Assign a referee pair per game in col P (pairs are listed in the box at P34:P38). 4. Check the 'TBD' cells: they mean a code has no matching team yet. 5. Never insert or delete rows; formulas depend on row positions.
A47: ⚠ Heads-up | B47: Cols D to H (the times) and N, O, Q, R, U, V, W are all formulas: leave them alone. Only L, M, P and the score columns (S, T) are for typing.
A49: ▶ 4.3 RUN THE GROUP DRAW
A50: Summary | B50: A random draw assigns registered teams to groups, then writes Group Codes that feed the schedule. Constraint: two teams from the same club cannot be drawn into the same group (the formula flags the host club's men's teams, short names HAR and HAR2).
A51: Drivers | B51: Group Draw sheet. Team list pulls from Teams Master. The draw is random (RAND).
A52: Steps | B52: 1. Open Group Draw. Press F9 to re-roll until you get a fair result (do it once, publicly). 2. Check the validation box (each group = 4, shows OK). 3. Select the 'Drawn Code' column (I6:I18) and Copy. 4. Paste-Special > VALUES into Teams Master column E (Group Code), matched to each team. 5. Once pasted as values the codes are LOCKED and stop changing. The schedule then resolves names from them.
A54: ▶ 4.4 USE THE GAME SHEET (printable officials' sheet)
A55: Summary | B55: A one-page, formula-driven sheet for referees/officials. Pick a game number and team names, rosters, referees, date/time and venue all populate.
A56: Drivers | B56: Game Sheet template. Selector cell (game # dropdown). Pulls from Games Schedule, Rosters Master and Inputs (venue).
A57: Steps | B57: 1. Open the Game Sheet template. 2. Select the Game # from the dropdown selector. 3. Teams, rosters, referees and timing fill automatically. 4. Print for officials. Do NOT type team or roster names manually: just change the game number.
A59: ▶ 4.5 ENTER SCORES & UPDATE RANKINGS
A60: Summary | B60: Enter each game's two scores; points, rankings and the Control Panel update automatically.
A61: Drivers | B61: Games Schedule: Score Team A = col S, Score Team B = col T. Points (cols U/V) auto: Win=2, Draw=1, Loss=0.
A62: Steps | B62: 1. Find the game row by Game # (col C). 2. Enter Team A's score in col S, Team B's in col T. 3. Points and standings recalculate automatically: do not edit the Rankings sorted tables. 4. Verify on the Rankings sheet that groups updated.
A64: ▶ 4.6 RECORD PLAYER STATS, MVP & TOP SCORERS
A65: Summary | B65: Enter goals per player per game; top scorers and award leaders calculate automatically. MVP/MVG come from the voting sheet.
A66: Drivers | B66: Goals: 'Individuals Stats Men' and 'Individuals Stats Women' (players auto-fill from Rosters Master; enter goals per game). Votes: 'MVP Voting'. Results roll up to 'Stats & MVP' and the Control Panel.
A67: Steps | B67: 1. On the Individuals Stats sheet, enter each player's goals per game in the goal columns. 2. Total goals and the Top-5 scorers on 'Stats & MVP' update automatically. 3. Enter MVP/MVG votes on the 'MVP Voting' sheet. 4. Award leaders appear on 'Stats & MVP' and the Control Panel.
A69: ▶ 4.7 REGISTRATION & PAYMENTS
A70: Summary | B70: Track invitations, deposits, final payments and roster submission per team. Status drives the Control Panel counters and the 2027 budget income.
A71: Drivers | B71: Registration 2027 table. Fee & deposit % come from Inputs. Status (col J) is AUTOMATIC: 'Host Registered' (Host Team = Yes), 'Fully Registered' (paid in full), 'Deposit Paid' (deposit only).
A72: Steps | B72: 1. As each team confirms, fill its row: invitation "x", Deposit Date, Final Pay Date; the $ amounts auto-fill from the per-team amounts on Budget Dashboard. 2. Mark Roster Submitted (col I) when the team sends its roster. 3. Status (col J) sets itself: never type over it. Control Panel team counts and 'Fees Collected' update automatically. 4. Paying-team count feeds 2027 budgeted registration income. 5. Give each newly confirmed team a Short Name & jerseys in the Team Styles table on Teams Master.
A74: ▶ 4.8 MANAGE VOLUNTEERS
A75: Summary | B75: Assign people to roles (timekeeper, scorekeeper, booth, gym prep, referee driving); hours tally automatically on the Volunteer Master List.
A76: Drivers | B76: Games Schedule: Time Keeper col X, Score Keeper col Y, Merch Booth col Z, Medical Staff col AA. Setup on 'Gym Prep'. Driving on 'Referee Pickup Drop Off'.
A77: Steps | B77: 1. Assign names in the relevant sheet's volunteer columns. 2. Always verify a volunteer is NOT playing in that same game. 3. Mark 'Presence Verified' when they arrive. 4. Hours auto-tally on the Volunteer Master List.
A79: ▶ 4.9 UPDATE THE CONCESSION PRODUCT LIST & PRICING
A80: Summary | B80: Maintain what's sold at the booth: items, cost (COGS), sale price and margin. This feeds concession revenue projections and the budget.
A81: Drivers | B81: Products Master table (ProductID, Description, Category, COGS, Sale Price; Gross Profit & Margin are formulas). 'Price List Concession' is the printable menu. 'Concession purchase list' is the shopping list.
A82: Steps | B82: 1. Add or edit items in Products Master: set Description, Category, COGS and Sale Price (blue inputs). Gross Profit & Margin calculate automatically. 2. To add a row, type on the first empty row of the table: it expands automatically. 3. Update the printable 'Price List Concession' menu to match. 4. List anything to buy on 'Concession purchase list'.
A83: ✓ Note | B83: RESOLVED: Price List Concession now pulls prices live from the Products Master table (no more external file link). Add new items to Products Master first; the price list picks them up automatically.
A85: ▶ 4.10 UPDATE THE BUDGET
A86: Summary | B86: The Budget Dashboard is a multi-year P&L (2024 to 2027) with income, expenses, net profit and variance vs budget / prior year. 2027 budgeted income is driven by the registration fee × paying teams.
A87: Drivers | B87: Budget Dashboard. Registration drivers in the box at M9:N15 (fee & deposit pull from Inputs; paying-teams count from Registration 2027). Detailed actuals live on 'Multi Year Financial Summary' and 'Operations Costs'.
A88: Steps | B88: 1. Enter 2027 budget figures in the '2027 Budget' column (income rows 11 to 14, expense rows 18 to 24). 2. Enter actuals in the '2027 Actuals' column as money comes in or goes out. 3. Totals, net profit and variance columns calculate automatically. 4. To change the fee that drives registration income, edit it on Inputs (not here).
A89: ⚠ Heads-up | B89: The detailed P&L on 'Multi Year Financial Summary' carries the authoritative actuals; the Dashboard category lines link to it. Edit detail there, not by overwriting the linked Dashboard cells (green = links to other sheets).
A91: 5. CELL COLOR CONVENTIONS (what's safe to edit)
A92: Font color | B92: Meaning | C92: Edit it?
A93: BLUE text | B93: Hardcoded input you type (a setting, a score, a price). Often on a yellow background. | C93: YES: these are the cells you change.
A94: BLACK text | B94: A formula that calculates from cells on the same sheet. | C94: NO: leave it; it recalculates itself.
A95: GREEN text | B95: A formula that links to another sheet in this workbook. | C95: NO: fix the source sheet instead.
A96: RED text | B96: A link to an external file (e.g. last year's workbook). | C96: Re-point or replace: external links often break.
A98: 6. IMPORTANT WARNINGS
A99: ❌ Do NOT insert or delete rows in Games Schedule: formulas depend on fixed row positions.
A100: ❌ Do NOT overwrite formula cells (black/green text) or the sorted Rankings tables.
A101: ❌ Do NOT type team names, times or scores' points by hand: set the driver and let it calculate.
A102: ✓ Always confirm a volunteer is not playing in the game they're assigned to.
A103: ✓ Change global settings only on the Inputs sheet: it is the single source of truth.
A104: ✓ Re-lock Group Codes (paste as values into Teams Master) after the draw so they stop re-rolling.
A106: 7. KEY CONTACTS
A107: Role | B107: Name | C107: Phone / Email
A108: Tournament Director | B108: [Add name] | C108: [Add phone / email]
A109: Referee Coordinator | B109: [Add name] | C109: Referee details on 'Referees Master'
A110: Volunteer Coordinator | B110: [Add name] | C110: Volunteer roster on 'Volunteer Master List'
A111: Concession / Finance Lead | B111: [Add name] | C111: [Add phone / email]
A112: Note: Team-official contacts are on 'Officials Contacts'. Team primary contacts are in 'Teams Master' and 'Registration 2027'.
A114: 8. QUICK NAVIGATION
A115: Status at a glance → Control Panel • All settings → Inputs • The engine → Games Schedule
A116: Money → Budget Dashboard • Awards → Stats & MVP / Final Rankings • People → the Master Data tables
A117: Volunteers' own quick guide is on the 'Volunteer Guide' sheet.

Sheet Volunteer Guide
A1: VOLUNTEER QUICK REFERENCE GUIDE
A3: ⚠️ IMPORTANT: Make sure you are NOT playing when you volunteer!
A5: YOUR VOLUNTEER ROLES
A7: 🕐 TIME KEEPER
A8: Location: Scorer's table
A9: Duties:
A10: • Start/stop game clock
A11: ="• Sound horn at halftime ("&Inputs!C7/2&" min) and end of game ("&Inputs!C7&" min)"
A12: • Track timeouts (1 per team per half, 1 minute each)
A13: • Signal 2-minute suspensions
A14: Arrive: 10 minutes before Court Time
A16: 📋 SCORE KEEPER
A17: Location: Scorer's table
A18: Duties:
A19: • Record all goals on score sheet
A20: • Track player suspensions (2 min, red cards)
A21: • Track timeouts used
A22: • Verify final score with referees
A23: Arrive: 10 minutes before Court Time
A25: 🏪 MERCHANDISE BOOTH
... A47: GAME TIMING
A49: Time | B49: Event
A50: Court Time | B50: ="Teams begin warm-up ("&Inputs!C6&" min)"
A51: Game Time | B51: ="First half starts ("&Inputs!C7/2&" min)"
A52: Halftime | B52: ="Break ("&Inputs!C8&" min)"
A53: Second Half | B53: ="Resumes ("&Inputs!C7/2&" min)"
A54: End of Game | B54: ="Maximum ~"&Inputs!C10&" min after Court Time"
A56: CHECK-IN PROCESS
A57: 1. Arrive 10 minutes before your assigned time
A58: 2. Find tournament coordinator or check-in desk
A59: 3. Your attendance will be marked in "Presence Verified" column
A60: 4. Get brief instructions from coordinator if needed
A62: QUESTIONS?
A63: Find any board member (marked in Participants list)
A64: They can help with any issues during your shift
A66: THANK YOU FOR VOLUNTEERING! 🙌

Sheet ----- MASTER DATA -----
A1: MASTER DATA

Sheet Inputs
B2: TOURNAMENT INPUTS & ASSUMPTIONS | C2: TOURNAMENT INPUTS & ASSUMPTIONS
B3: Central source for all tournament settings. Edit here: the rest of the model reads from these cells.
B5: GAME PARAMETERS (minutes)
B6: Warm up | C6: 5
B7: Actual play | C7: 50
B8: Halftime | C8: 5
B9: Incidents/buffer | C9: 5
B10: Total slot | C10: =SUM(C6:C9)
B12: TOURNAMENT CAPACITY
B13: Max Total Teams | C13: ='Format Engine'!H8
B14: Max Men's Teams | C14: ='Format Engine'!H9
B15: Max Women's Teams | C15: ='Format Engine'!H10
B17: REGISTRATION FEE
B18: Per-Team Fee | C18: 600
B19: Deposit % of Fee | C19: 0.35
B21: EVENT DETAILS
B22: Tournament Start Date | C22: 46430
B23: Venue Name / Location | C23: Northside Community Gym, Springfield, CA
B25: DAILY START TIMES (first court time each day)
B26: Day 1 Start (Game 1) | C26: 0.60416667
B27: Day 2 Start (Game 2) | C27: 0.33333333
B28: Day 3 Start (Game 8) | C28: 0.35416667
B29: Day 4 Start (Game 21) | C29: 0.35416667

Sheet Format Engine
B1: FORMAT ENGINE: Tournament Format Toggle
B2: Single switch that re-shapes the whole tournament. Change the Active Format on the Control Panel; every tab follows.
B3: The grid below (rows 22-91) is the static master game plan for each format: only edit it to redesign a format. The ACTIVE block (H7:H22) and active schedule update automatically from the toggle.
B4: ACTIVE FORMAT → | C4: ='Control Panel'!$G$2 | D4: (driven by Control Panel toggle G2)
B6: PARAMETERS BY FORMAT | C6: Format 1 | D6: Format 2 | E6: Format 3 | G6: ACTIVE | H6: ↓ read by all tabs
B7: Format name | C7: 8M+5W | D7: 8M+4W | E7: 6M+6W | G7: Active format | H7: =$C$4
B8: Total teams | C8: 13 | D8: 12 | E8: 12 | G8: Total teams | H8: =INDEX($C$8:$E$8,MATCH($C$4,$C$7:$E$7,0))
B9: Men teams | C9: 8 | D9: 8 | E9: 6 | G9: Men teams | H9: =INDEX($C$9:$E$9,MATCH($C$4,$C$7:$E$7,0))
B10: Women teams | C10: 5 | D10: 4 | E10: 6 | G10: Women teams | H10: =INDEX($C$10:$E$10,MATCH($C$4,$C$7:$E$7,0))
B11: Men groups | C11: 2 | D11: 2 | E11: 2 | G11: Men groups | H11: =INDEX($C$11:$E$11,MATCH($C$4,$C$7:$E$7,0))
B12: Women groups | C12: 1 | D12: 1 | E12: 2 | G12: Women groups | H12: =INDEX($C$12:$E$12,MATCH($C$4,$C$7:$E$7,0))
B13: Total games | C13: =COUNTIF($A$23:$A$200,C$7) | D13: =COUNTIF($A$23:$A$200,D$7) | E13: =COUNTIF($A$23:$A$200,E$7) | G13: Total games | H13: =INDEX($C$13:$E$13,MATCH($C$4,$C$7:$E$7,0))
B14: Day 1 games | C14: 1 | D14: 7 | E14: 6 | G14: Day 1 games | H14: =INDEX($C$14:$E$14,MATCH($C$4,$C$7:$E$7,0))
B15: Day 2 games | C15: 6 | D15: 11 | E15: 8 | G15: Day 2 games | H15: =INDEX($C$15:$E$15,MATCH($C$4,$C$7:$E$7,0))
B16: Day 3 games | C16: 13 | D16: 6 | E16: 4 | G16: Day 3 games | H16: =INDEX($C$16:$E$16,MATCH($C$4,$C$7:$E$7,0))
B17: Day 4 games | C17: 7 | D17: 0 | E17: 0 | G17: Day 4 games | H17: =INDEX($C$17:$E$17,MATCH($C$4,$C$7:$E$7,0))
F18: Day-1 last game # | H18: =H14
F19: Day-2 last game # | H19: =H14+H15
F20: Day-3 last game # | H20: =H14+H15+H16
F21: Day-4 last game # | H21: =H13 | J21: ACTIVE SCHEDULE (auto-filters to selected format)
A22: FormatKey | B22: Game | C22: Div | D22: Gr | E22: CodeA | F22: Active tournament days | G22: K | H22: =COUNTIF(H14:H17,">0") | J22: Game | K22: Div | L22: Gr | M22: CodeA | N22: CodeB | O22: K
A23: 8M+5W | B23: 1 | C23: W | D23: W | E23: W1 | F23: W2 | J23: {=_xlfn._xlws.FILTER(B23:G91,A23:A91=$C$4)}
A24: 8M+5W | B24: 2 | C24: M | D24: A | E24: A1 | F24: A2
A25: 8M+5W | B25: 3 | C25: M | D25: B | E25: B1 | F25: B2
A26: 8M+5W | B26: 4 | C26: W | D26: W | E26: W3 | F26: W4
A27: 8M+5W | B27: 5 | C27: M | D27: A | E27: A3 | F27: A4
A28: 8M+5W | B28: 6 | C28: M | D28: B | E28: B3 | F28: B4
A29: 8M+5W | B29: 7 | C29: W | D29: W | E29: W1 | F29: W5
A30: 8M+5W | B30: 8 | C30: M | D30: A | E30: A1 | F30: A3
A31: 8M+5W | B31: 9 | C31: W | D31: W | E31: W2 | F31: W5
A32: 8M+5W | B32: 10 | C32: M | D32: B | E32: B1 | F32: B3
A33: 8M+5W | B33: 11 | C33: W | D33: W | E33: W1 | F33: W4
A34: 8M+5W | B34: 12 | C34: M | D34: A | E34: A2 | F34: A4
A35: 8M+5W | B35: 13 | C35: W | D35: W | E35: W3 | F35: W5
... A44: 8M+5W | B44: 22 | C44: W | D44: W | E44: W4 | F44: W5
A45: 8M+5W | B45: 23 | C45: M | D45: P | E45: A4 | F45: B4 | G45: 7
A46: 8M+5W | B46: 24 | C46: M | D46: P | E46: A3 | F46: B3 | G46: 5
A47: 8M+5W | B47: 25 | C47: M | D47: P | E47: A2 | F47: B2 | G47: 3
A48: 8M+5W | B48: 26 | C48: W | D48: P | E48: W1 | F48: W2 | G48: 1
A49: 8M+5W | B49: 27 | C49: M | D49: P | E49: A1 | F49: B1 | G49: 1
A50: 8M+4W | B50: 1 | C50: W | D50: W | E50: W1 | F50: W2
A51: 8M+4W | B51: 2 | C51: M | D51: A | E51: A1 | F51: A2
A52: 8M+4W | B52: 3 | C52: M | D52: B | E52: B1 | F52: B2
A53: 8M+4W | B53: 4 | C53: W | D53: W | E53: W3 | F53: W4
A54: 8M+4W | B54: 5 | C54: M | D54: A | E54: A3 | F54: A4
A55: 8M+4W | B55: 6 | C55: M | D55: B | E55: B3 | F55: B4
A56: 8M+4W | B56: 7 | C56: W | D56: W | E56: W1 | F56: W3
A57: 8M+4W | B57: 8 | C57: M | D57: A | E57: A1 | F57: A3
A58: 8M+4W | B58: 9 | C58: W | D58: W | E58: W2 | F58: W4
A59: 8M+4W | B59: 10 | C59: M | D59: B | E59: B1 | F59: B3
A60: 8M+4W | B60: 11 | C60: W | D60: W | E60: W1 | F60: W4
A61: 8M+4W | B61: 12 | C61: M | D61: A | E61: A2 | F61: A4
... A67: 8M+4W | B67: 18 | C67: M | D67: B | E67: B2 | F67: B3
A68: 8M+4W | B68: 19 | C68: M | D68: P | E68: A4 | F68: B4 | G68: 7
A69: 8M+4W | B69: 20 | C69: M | D69: P | E69: A3 | F69: B3 | G69: 5
A70: 8M+4W | B70: 21 | C70: W | D70: P | E70: W3 | F70: W4 | G70: 3
A71: 8M+4W | B71: 22 | C71: M | D71: P | E71: A2 | F71: B2 | G71: 3
A72: 8M+4W | B72: 23 | C72: W | D72: P | E72: W1 | F72: W2 | G72: 1
A73: 8M+4W | B73: 24 | C73: M | D73: P | E73: A1 | F73: B1 | G73: 1
A74: 6M+6W | B74: 1 | C74: M | D74: A | E74: A1 | F74: A2
A75: 6M+6W | B75: 2 | C75: W | D75: WA | E75: WA1 | F75: WA2
A76: 6M+6W | B76: 3 | C76: M | D76: B | E76: B1 | F76: B2
A77: 6M+6W | B77: 4 | C77: W | D77: WB | E77: WB1 | F77: WB2
A78: 6M+6W | B78: 5 | C78: M | D78: A | E78: A1 | F78: A3
A79: 6M+6W | B79: 6 | C79: W | D79: WA | E79: WA1 | F79: WA3
A80: 6M+6W | B80: 7 | C80: M | D80: B | E80: B1 | F80: B3
A81: 6M+6W | B81: 8 | C81: W | D81: WB | E81: WB1 | F81: WB3
A82: 6M+6W | B82: 9 | C82: M | D82: A | E82: A2 | F82: A3
A83: 6M+6W | B83: 10 | C83: W | D83: WA | E83: WA2 | F83: WA3
A84: 6M+6W | B84: 11 | C84: M | D84: B | E84: B2 | F84: B3
A85: 6M+6W | B85: 12 | C85: W | D85: WB | E85: WB2 | F85: WB3
A86: 6M+6W | B86: 13 | C86: M | D86: P | E86: A3 | F86: B3 | G86: 5
A87: 6M+6W | B87: 14 | C87: W | D87: P | E87: WA3 | F87: WB3 | G87: 5
A88: 6M+6W | B88: 15 | C88: M | D88: P | E88: A2 | F88: B2 | G88: 3
A89: 6M+6W | B89: 16 | C89: W | D89: P | E89: WA2 | F89: WB2 | G89: 3
A90: 6M+6W | B90: 17 | C90: M | D90: P | E90: A1 | F90: B1 | G90: 1
A91: 6M+6W | B91: 18 | C91: W | D91: P | E91: WA1 | F91: WB1 | G91: 1

Sheet Standings Engine
B1: STANDINGS ENGINE: code-driven group standings (all formats)
B2: Group = code prefix, seed = digit. Points from non-playoff games only. Playoff matchups resolve their codes (e.g. A1 = Group A winner) against the RankedCode column.
A3: Team | B3: Code | C3: Group | D3: Pts | E3: GF | F3: GA | G3: GD | H3: RankScore | I3: RankInGrp | J3: RankedCode | K3: Active?
A4: ='Teams Master'!C2 | B4: ='Teams Master'!E2 | C4: =IF(B4="","",LEFT(B4,LEN(B4)-1)) | D4: =SUMIFS('Games Schedule'!$U$5:$U$31,'Games Schedule'!$L$5:$L$31,$B4,'Games Schedule'!$J$5:$J$31,"<>P")+SUMIFS('Games Schedule'!$V$5:$V$31,'Games Schedule'!$M$5:$M$31,$B4,'Games Schedule'!$J$5:$J$31,"<>P") | E4: =SUMIFS('Games Schedule'!$S$5:$S$31,'Games Schedule'!$L$5:$L$31,$B4,'Games Schedule'!$J$5:$J$31,"<>P")+SUMIFS('Games Schedule'!$T$5:$T$31,'Games Schedule'!$M$5:$M$31,$B4,'Games Schedule'!$J$5:$J$31,"<>P") | F4: =SUMIFS('Games Schedule'!$T$5:$T$31,'Games Schedule'!$L$5:$L$31,$B4,'Games Schedule'!$J$5:$J$31,"<>P")+SUMIFS('Games Schedule'!$S$5:$S$31,'Games Schedule'!$M$5:$M$31,$B4,'Games Schedule'!$J$5:$J$31,"<>P") | G4: =E4-F4 | H4: =D4*1000+G4 | I4: {=IF($C4="","",IF($K4=0,"",SUMPRODUCT(($C$4:$C$16=$C4)*($K$4:$K$16=1)*($H$4:$H$16>$H4))+SUMPRODUCT(($C$4:$C$16=$C4)*($K$4:$K$16=1)*($H$4:$H$16=$H4)*(ROW($H$4:$H$16)<ROW($H4)))+1))} | J4: =IF($C4="","",IF($K4=0,"",$C4&I4)) | K4: =IF($B4="","",IF((COUNTIFS('Format Engine'!$A$23:$A$91,'Format Engine'!$C$4,'Format Engine'!$E$23:$E$91,$B4,'Format Engine'!$D$23:$D$91,"<>P")+COUNTIFS('Format Engine'!$A$23:$A$91,'Format Engine'!$C$4,'Format Engine'!$F$23:$F$91,$B4,'Format Engine'!$D$23:$D$91,"<>P"))>0,1,0))
A5: ='Teams Master'!C3 | B5: ='Teams Master'!E3 | C5: =IF(B5="","",LEFT(B5,LEN(B5)-1)) | D5: =SUMIFS('Games Schedule'!$U$5:$U$31,'Games Schedule'!$L$5:$L$31,$B5,'Games Schedule'!$J$5:$J$31,"<>P")+SUMIFS('Games Schedule'!$V$5:$V$31,'Games Schedule'!$M$5:$M$31,$B5,'Games Schedule'!$J$5:$J$31,"<>P") | E5: =SUMIFS('Games Schedule'!$S$5:$S$31,'Games Schedule'!$L$5:$L$31,$B5,'Games Schedule'!$J$5:$J$31,"<>P")+SUMIFS('Games Schedule'!$T$5:$T$31,'Games Schedule'!$M$5:$M$31,$B5,'Games Schedule'!$J$5:$J$31,"<>P") | F5: =SUMIFS('Games Schedule'!$T$5:$T$31,'Games Schedule'!$L$5:$L$31,$B5,'Games Schedule'!$J$5:$J$31,"<>P")+SUMIFS('Games Schedule'!$S$5:$S$31,'Games Schedule'!$M$5:$M$31,$B5,'Games Schedule'!$J$5:$J$31,"<>P") | G5: =E5-F5 | H5: =D5*1000+G5 | I5: {=IF($C5="","",IF($K5=0,"",SUMPRODUCT(($C$4:$C$16=$C5)*($K$4:$K$16=1)*($H$4:$H$16>$H5))+SUMPRODUCT(($C$4:$C$16=$C5)*($K$4:$K$16=1)*($H$4:$H$16=$H5)*(ROW($H$4:$H$16)<ROW($H5)))+1))} | J5: =IF($C5="","",IF($K5=0,"",$C5&I5)) | K5: =IF($B5="","",IF((COUNTIFS('Format Engine'!$A$23:$A$91,'Format Engine'!$C$4,'Format Engine'!$E$23:$E$91,$B5,'Format Engine'!$D$23:$D$91,"<>P")+COUNTIFS('Format Engine'!$A$23:$A$91,'Format Engine'!$C$4,'Format Engine'!$F$23:$F$91,$B5,'Format Engine'!$D$23:$D$91,"<>P"))>0,1,0))
A6: ='Teams Master'!C4 | B6: ='Teams Master'!E4 | C6: =IF(B6="","",LEFT(B6,LEN(B6)-1)) | D6: =SUMIFS('Games Schedule'!$U$5:$U$31,'Games Schedule'!$L$5:$L$31,$B6,'Games Schedule'!$J$5:$J$31,"<>P")+SUMIFS('Games Schedule'!$V$5:$V$31,'Games Schedule'!$M$5:$M$31,$B6,'Games Schedule'!$J$5:$J$31,"<>P") | E6: =SUMIFS('Games Schedule'!$S$5:$S$31,'Games Schedule'!$L$5:$L$31,$B6,'Games Schedule'!$J$5:$J$31,"<>P")+SUMIFS('Games Schedule'!$T$5:$T$31,'Games Schedule'!$M$5:$M$31,$B6,'Games Schedule'!$J$5:$J$31,"<>P") | F6: =SUMIFS('Games Schedule'!$T$5:$T$31,'Games Schedule'!$L$5:$L$31,$B6,'Games Schedule'!$J$5:$J$31,"<>P")+SUMIFS('Games Schedule'!$S$5:$S$31,'Games Schedule'!$M$5:$M$31,$B6,'Games Schedule'!$J$5:$J$31,"<>P") | G6: =E6-F6 | H6: =D6*1000+G6 | I6: {=IF($C6="","",IF($K6=0,"",SUMPRODUCT(($C$4:$C$16=$C6)*($K$4:$K$16=1)*($H$4:$H$16>$H6))+SUMPRODUCT(($C$4:$C$16=$C6)*($K$4:$K$16=1)*($H$4:$H$16=$H6)*(ROW($H$4:$H$16)<ROW($H6)))+1))} | J6: =IF($C6="","",IF($K6=0,"",$C6&I6)) | K6: =IF($B6="","",IF((COUNTIFS('Format Engine'!$A$23:$A$91,'Format Engine'!$C$4,'Format Engine'!$E$23:$E$91,$B6,'Format Engine'!$D$23:$D$91,"<>P")+COUNTIFS('Format Engine'!$A$23:$A$91,'Format Engine'!$C$4,'Format Engine'!$F$23:$F$91,$B6,'Format Engine'!$D$23:$D$91,"<>P"))>0,1,0))
A7: ='Teams Master'!C5 | B7: ='Teams Master'!E5 | C7: =IF(B7="","",LEFT(B7,LEN(B7)-1)) | D7: =SUMIFS('Games Schedule'!$U$5:$U$31,'Games Schedule'!$L$5:$L$31,$B7,'Games Schedule'!$J$5:$J$31,"<>P")+SUMIFS('Games Schedule'!$V$5:$V$31,'Games Schedule'!$M$5:$M$31,$B7,'Games Schedule'!$J$5:$J$31,"<>P") | E7: =SUMIFS('Games Schedule'!$S$5:$S$31,'Games Schedule'!$L$5:$L$31,$B7,'Games Schedule'!$J$5:$J$31,"<>P")+SUMIFS('Games Schedule'!$T$5:$T$31,'Games Schedule'!$M$5:$M$31,$B7,'Games Schedule'!$J$5:$J$31,"<>P") | F7: =SUMIFS('Games Schedule'!$T$5:$T$31,'Games Schedule'!$L$5:$L$31,$B7,'Games Schedule'!$J$5:$J$31,"<>P")+SUMIFS('Games Schedule'!$S$5:$S$31,'Games Schedule'!$M$5:$M$31,$B7,'Games Schedule'!$J$5:$J$31,"<>P") | G7: =E7-F7 | H7: =D7*1000+G7 | I7: {=IF($C7="","",IF($K7=0,"",SUMPRODUCT(($C$4:$C$16=$C7)*($K$4:$K$16=1)*($H$4:$H$16>$H7))+SUMPRODUCT(($C$4:$C$16=$C7)*($K$4:$K$16=1)*($H$4:$H$16=$H7)*(ROW($H$4:$H$16)<ROW($H7)))+1))} | J7: =IF($C7="","",IF($K7=0,"",$C7&I7)) | K7: =IF($B7="","",IF((COUNTIFS('Format Engine'!$A$23:$A$91,'Format Engine'!$C$4,'Format Engine'!$E$23:$E$91,$B7,'Format Engine'!$D$23:$D$91,"<>P")+COUNTIFS('Format Engine'!$A$23:$A$91,'Format Engine'!$C$4,'Format Engine'!$F$23:$F$91,$B7,'Format Engine'!$D$23:$D$91,"<>P"))>0,1,0))
A8: ='Teams Master'!C6 | B8: ='Teams Master'!E6 | C8: =IF(B8="","",LEFT(B8,LEN(B8)-1)) | D8: =SUMIFS('Games Schedule'!$U$5:$U$31,'Games Schedule'!$L$5:$L$31,$B8,'Games Schedule'!$J$5:$J$31,"<>P")+SUMIFS('Games Schedule'!$V$5:$V$31,'Games Schedule'!$M$5:$M$31,$B8,'Games Schedule'!$J$5:$J$31,"<>P") | E8: =SUMIFS('Games Schedule'!$S$5:$S$31,'Games Schedule'!$L$5:$L$31,$B8,'Games Schedule'!$J$5:$J$31,"<>P")+SUMIFS('Games Schedule'!$T$5:$T$31,'Games Schedule'!$M$5:$M$31,$B8,'Games Schedule'!$J$5:$J$31,"<>P") | F8: =SUMIFS('Games Schedule'!$T$5:$T$31,'Games Schedule'!$L$5:$L$31,$B8,'Games Schedule'!$J$5:$J$31,"<>P")+SUMIFS('Games Schedule'!$S$5:$S$31,'Games Schedule'!$M$5:$M$31,$B8,'Games Schedule'!$J$5:$J$31,"<>P") | G8: =E8-F8 | H8: =D8*1000+G8 | I8: {=IF($C8="","",IF($K8=0,"",SUMPRODUCT(($C$4:$C$16=$C8)*($K$4:$K$16=1)*($H$4:$H$16>$H8))+SUMPRODUCT(($C$4:$C$16=$C8)*($K$4:$K$16=1)*($H$4:$H$16=$H8)*(ROW($H$4:$H$16)<ROW($H8)))+1))} | J8: =IF($C8="","",IF($K8=0,"",$C8&I8)) | K8: =IF($B8="","",IF((COUNTIFS('Format Engine'!$A$23:$A$91,'Format Engine'!$C$4,'Format Engine'!$E$23:$E$91,$B8,'Format Engine'!$D$23:$D$91,"<>P")+COUNTIFS('Format Engine'!$A$23:$A$91,'Format Engine'!$C$4,'Format Engine'!$F$23:$F$91,$B8,'Format Engine'!$D$23:$D$91,"<>P"))>0,1,0))
A9: ='Teams Master'!C7 | B9: ='Teams Master'!E7 | C9: =IF(B9="","",LEFT(B9,LEN(B9)-1)) | D9: =SUMIFS('Games Schedule'!$U$5:$U$31,'Games Schedule'!$L$5:$L$31,$B9,'Games Schedule'!$J$5:$J$31,"<>P")+SUMIFS('Games Schedule'!$V$5:$V$31,'Games Schedule'!$M$5:$M$31,$B9,'Games Schedule'!$J$5:$J$31,"<>P") | E9: =SUMIFS('Games Schedule'!$S$5:$S$31,'Games Schedule'!$L$5:$L$31,$B9,'Games Schedule'!$J$5:$J$31,"<>P")+SUMIFS('Games Schedule'!$T$5:$T$31,'Games Schedule'!$M$5:$M$31,$B9,'Games Schedule'!$J$5:$J$31,"<>P") | F9: =SUMIFS('Games Schedule'!$T$5:$T$31,'Games Schedule'!$L$5:$L$31,$B9,'Games Schedule'!$J$5:$J$31,"<>P")+SUMIFS('Games Schedule'!$S$5:$S$31,'Games Schedule'!$M$5:$M$31,$B9,'Games Schedule'!$J$5:$J$31,"<>P") | G9: =E9-F9 | H9: =D9*1000+G9 | I9: {=IF($C9="","",IF($K9=0,"",SUMPRODUCT(($C$4:$C$16=$C9)*($K$4:$K$16=1)*($H$4:$H$16>$H9))+SUMPRODUCT(($C$4:$C$16=$C9)*($K$4:$K$16=1)*($H$4:$H$16=$H9)*(ROW($H$4:$H$16)<ROW($H9)))+1))} | J9: =IF($C9="","",IF($K9=0,"",$C9&I9)) | K9: =IF($B9="","",IF((COUNTIFS('Format Engine'!$A$23:$A$91,'Format Engine'!$C$4,'Format Engine'!$E$23:$E$91,$B9,'Format Engine'!$D$23:$D$91,"<>P")+COUNTIFS('Format Engine'!$A$23:$A$91,'Format Engine'!$C$4,'Format Engine'!$F$23:$F$91,$B9,'Format Engine'!$D$23:$D$91,"<>P"))>0,1,0))
A10: ='Teams Master'!C8 | B10: ='Teams Master'!E8 | C10: =IF(B10="","",LEFT(B10,LEN(B10)-1)) | D10: =SUMIFS('Games Schedule'!$U$5:$U$31,'Games Schedule'!$L$5:$L$31,$B10,'Games Schedule'!$J$5:$J$31,"<>P")+SUMIFS('Games Schedule'!$V$5:$V$31,'Games Schedule'!$M$5:$M$31,$B10,'Games Schedule'!$J$5:$J$31,"<>P") | E10: =SUMIFS('Games Schedule'!$S$5:$S$31,'Games Schedule'!$L$5:$L$31,$B10,'Games Schedule'!$J$5:$J$31,"<>P")+SUMIFS('Games Schedule'!$T$5:$T$31,'Games Schedule'!$M$5:$M$31,$B10,'Games Schedule'!$J$5:$J$31,"<>P") | F10: =SUMIFS('Games Schedule'!$T$5:$T$31,'Games Schedule'!$L$5:$L$31,$B10,'Games Schedule'!$J$5:$J$31,"<>P")+SUMIFS('Games Schedule'!$S$5:$S$31,'Games Schedule'!$M$5:$M$31,$B10,'Games Schedule'!$J$5:$J$31,"<>P") | G10: =E10-F10 | H10: =D10*1000+G10 | I10: {=IF($C10="","",IF($K10=0,"",SUMPRODUCT(($C$4:$C$16=$C10)*($K$4:$K$16=1)*($H$4:$H$16>$H10))+SUMPRODUCT(($C$4:$C$16=$C10)*($K$4:$K$16=1)*($H$4:$H$16=$H10)*(ROW($H$4:$H$16)<ROW($H10)))+1))} | J10: =IF($C10="","",IF($K10=0,"",$C10&I10)) | K10: =IF($B10="","",IF((COUNTIFS('Format Engine'!$A$23:$A$91,'Format Engine'!$C$4,'Format Engine'!$E$23:$E$91,$B10,'Format Engine'!$D$23:$D$91,"<>P")+COUNTIFS('Format Engine'!$A$23:$A$91,'Format Engine'!$C$4,'Format Engine'!$F$23:$F$91,$B10,'Format Engine'!$D$23:$D$91,"<>P"))>0,1,0))
A11: ='Teams Master'!C9 | B11: ='Teams Master'!E9 | C11: =IF(B11="","",LEFT(B11,LEN(B11)-1)) | D11: =SUMIFS('Games Schedule'!$U$5:$U$31,'Games Schedule'!$L$5:$L$31,$B11,'Games Schedule'!$J$5:$J$31,"<>P")+SUMIFS('Games Schedule'!$V$5:$V$31,'Games Schedule'!$M$5:$M$31,$B11,'Games Schedule'!$J$5:$J$31,"<>P") | E11: =SUMIFS('Games Schedule'!$S$5:$S$31,'Games Schedule'!$L$5:$L$31,$B11,'Games Schedule'!$J$5:$J$31,"<>P")+SUMIFS('Games Schedule'!$T$5:$T$31,'Games Schedule'!$M$5:$M$31,$B11,'Games Schedule'!$J$5:$J$31,"<>P") | F11: =SUMIFS('Games Schedule'!$T$5:$T$31,'Games Schedule'!$L$5:$L$31,$B11,'Games Schedule'!$J$5:$J$31,"<>P")+SUMIFS('Games Schedule'!$S$5:$S$31,'Games Schedule'!$M$5:$M$31,$B11,'Games Schedule'!$J$5:$J$31,"<>P") | G11: =E11-F11 | H11: =D11*1000+G11 | I11: {=IF($C11="","",IF($K11=0,"",SUMPRODUCT(($C$4:$C$16=$C11)*($K$4:$K$16=1)*($H$4:$H$16>$H11))+SUMPRODUCT(($C$4:$C$16=$C11)*($K$4:$K$16=1)*($H$4:$H$16=$H11)*(ROW($H$4:$H$16)<ROW($H11)))+1))} | J11: =IF($C11="","",IF($K11=0,"",$C11&I11)) | K11: =IF($B11="","",IF((COUNTIFS('Format Engine'!$A$23:$A$91,'Format Engine'!$C$4,'Format Engine'!$E$23:$E$91,$B11,'Format Engine'!$D$23:$D$91,"<>P")+COUNTIFS('Format Engine'!$A$23:$A$91,'Format Engine'!$C$4,'Format Engine'!$F$23:$F$91,$B11,'Format Engine'!$D$23:$D$91,"<>P"))>0,1,0))
A12: ='Teams Master'!C10 | B12: ='Teams Master'!E10 | C12: =IF(B12="","",LEFT(B12,LEN(B12)-1)) | D12: =SUMIFS('Games Schedule'!$U$5:$U$31,'Games Schedule'!$L$5:$L$31,$B12,'Games Schedule'!$J$5:$J$31,"<>P")+SUMIFS('Games Schedule'!$V$5:$V$31,'Games Schedule'!$M$5:$M$31,$B12,'Games Schedule'!$J$5:$J$31,"<>P") | E12: =SUMIFS('Games Schedule'!$S$5:$S$31,'Games Schedule'!$L$5:$L$31,$B12,'Games Schedule'!$J$5:$J$31,"<>P")+SUMIFS('Games Schedule'!$T$5:$T$31,'Games Schedule'!$M$5:$M$31,$B12,'Games Schedule'!$J$5:$J$31,"<>P") | F12: =SUMIFS('Games Schedule'!$T$5:$T$31,'Games Schedule'!$L$5:$L$31,$B12,'Games Schedule'!$J$5:$J$31,"<>P")+SUMIFS('Games Schedule'!$S$5:$S$31,'Games Schedule'!$M$5:$M$31,$B12,'Games Schedule'!$J$5:$J$31,"<>P") | G12: =E12-F12 | H12: =D12*1000+G12 | I12: {=IF($C12="","",IF($K12=0,"",SUMPRODUCT(($C$4:$C$16=$C12)*($K$4:$K$16=1)*($H$4:$H$16>$H12))+SUMPRODUCT(($C$4:$C$16=$C12)*($K$4:$K$16=1)*($H$4:$H$16=$H12)*(ROW($H$4:$H$16)<ROW($H12)))+1))} | J12: =IF($C12="","",IF($K12=0,"",$C12&I12)) | K12: =IF($B12="","",IF((COUNTIFS('Format Engine'!$A$23:$A$91,'Format Engine'!$C$4,'Format Engine'!$E$23:$E$91,$B12,'Format Engine'!$D$23:$D$91,"<>P")+COUNTIFS('Format Engine'!$A$23:$A$91,'Format Engine'!$C$4,'Format Engine'!$F$23:$F$91,$B12,'Format Engine'!$D$23:$D$91,"<>P"))>0,1,0))
A13: ='Teams Master'!C11 | B13: ='Teams Master'!E11 | C13: =IF(B13="","",LEFT(B13,LEN(B13)-1)) | D13: =SUMIFS('Games Schedule'!$U$5:$U$31,'Games Schedule'!$L$5:$L$31,$B13,'Games Schedule'!$J$5:$J$31,"<>P")+SUMIFS('Games Schedule'!$V$5:$V$31,'Games Schedule'!$M$5:$M$31,$B13,'Games Schedule'!$J$5:$J$31,"<>P") | E13: =SUMIFS('Games Schedule'!$S$5:$S$31,'Games Schedule'!$L$5:$L$31,$B13,'Games Schedule'!$J$5:$J$31,"<>P")+SUMIFS('Games Schedule'!$T$5:$T$31,'Games Schedule'!$M$5:$M$31,$B13,'Games Schedule'!$J$5:$J$31,"<>P") | F13: =SUMIFS('Games Schedule'!$T$5:$T$31,'Games Schedule'!$L$5:$L$31,$B13,'Games Schedule'!$J$5:$J$31,"<>P")+SUMIFS('Games Schedule'!$S$5:$S$31,'Games Schedule'!$M$5:$M$31,$B13,'Games Schedule'!$J$5:$J$31,"<>P") | G13: =E13-F13 | H13: =D13*1000+G13 | I13: {=IF($C13="","",IF($K13=0,"",SUMPRODUCT(($C$4:$C$16=$C13)*($K$4:$K$16=1)*($H$4:$H$16>$H13))+SUMPRODUCT(($C$4:$C$16=$C13)*($K$4:$K$16=1)*($H$4:$H$16=$H13)*(ROW($H$4:$H$16)<ROW($H13)))+1))} | J13: =IF($C13="","",IF($K13=0,"",$C13&I13)) | K13: =IF($B13="","",IF((COUNTIFS('Format Engine'!$A$23:$A$91,'Format Engine'!$C$4,'Format Engine'!$E$23:$E$91,$B13,'Format Engine'!$D$23:$D$91,"<>P")+COUNTIFS('Format Engine'!$A$23:$A$91,'Format Engine'!$C$4,'Format Engine'!$F$23:$F$91,$B13,'Format Engine'!$D$23:$D$91,"<>P"))>0,1,0))
A14: ='Teams Master'!C12 | B14: ='Teams Master'!E12 | C14: =IF(B14="","",LEFT(B14,LEN(B14)-1)) | D14: =SUMIFS('Games Schedule'!$U$5:$U$31,'Games Schedule'!$L$5:$L$31,$B14,'Games Schedule'!$J$5:$J$31,"<>P")+SUMIFS('Games Schedule'!$V$5:$V$31,'Games Schedule'!$M$5:$M$31,$B14,'Games Schedule'!$J$5:$J$31,"<>P") | E14: =SUMIFS('Games Schedule'!$S$5:$S$31,'Games Schedule'!$L$5:$L$31,$B14,'Games Schedule'!$J$5:$J$31,"<>P")+SUMIFS('Games Schedule'!$T$5:$T$31,'Games Schedule'!$M$5:$M$31,$B14,'Games Schedule'!$J$5:$J$31,"<>P") | F14: =SUMIFS('Games Schedule'!$T$5:$T$31,'Games Schedule'!$L$5:$L$31,$B14,'Games Schedule'!$J$5:$J$31,"<>P")+SUMIFS('Games Schedule'!$S$5:$S$31,'Games Schedule'!$M$5:$M$31,$B14,'Games Schedule'!$J$5:$J$31,"<>P") | G14: =E14-F14 | H14: =D14*1000+G14 | I14: {=IF($C14="","",IF($K14=0,"",SUMPRODUCT(($C$4:$C$16=$C14)*($K$4:$K$16=1)*($H$4:$H$16>$H14))+SUMPRODUCT(($C$4:$C$16=$C14)*($K$4:$K$16=1)*($H$4:$H$16=$H14)*(ROW($H$4:$H$16)<ROW($H14)))+1))} | J14: =IF($C14="","",IF($K14=0,"",$C14&I14)) | K14: =IF($B14="","",IF((COUNTIFS('Format Engine'!$A$23:$A$91,'Format Engine'!$C$4,'Format Engine'!$E$23:$E$91,$B14,'Format Engine'!$D$23:$D$91,"<>P")+COUNTIFS('Format Engine'!$A$23:$A$91,'Format Engine'!$C$4,'Format Engine'!$F$23:$F$91,$B14,'Format Engine'!$D$23:$D$91,"<>P"))>0,1,0))
A15: ='Teams Master'!C13 | B15: ='Teams Master'!E13 | C15: =IF(B15="","",LEFT(B15,LEN(B15)-1)) | D15: =SUMIFS('Games Schedule'!$U$5:$U$31,'Games Schedule'!$L$5:$L$31,$B15,'Games Schedule'!$J$5:$J$31,"<>P")+SUMIFS('Games Schedule'!$V$5:$V$31,'Games Schedule'!$M$5:$M$31,$B15,'Games Schedule'!$J$5:$J$31,"<>P") | E15: =SUMIFS('Games Schedule'!$S$5:$S$31,'Games Schedule'!$L$5:$L$31,$B15,'Games Schedule'!$J$5:$J$31,"<>P")+SUMIFS('Games Schedule'!$T$5:$T$31,'Games Schedule'!$M$5:$M$31,$B15,'Games Schedule'!$J$5:$J$31,"<>P") | F15: =SUMIFS('Games Schedule'!$T$5:$T$31,'Games Schedule'!$L$5:$L$31,$B15,'Games Schedule'!$J$5:$J$31,"<>P")+SUMIFS('Games Schedule'!$S$5:$S$31,'Games Schedule'!$M$5:$M$31,$B15,'Games Schedule'!$J$5:$J$31,"<>P") | G15: =E15-F15 | H15: =D15*1000+G15 | I15: {=IF($C15="","",IF($K15=0,"",SUMPRODUCT(($C$4:$C$16=$C15)*($K$4:$K$16=1)*($H$4:$H$16>$H15))+SUMPRODUCT(($C$4:$C$16=$C15)*($K$4:$K$16=1)*($H$4:$H$16=$H15)*(ROW($H$4:$H$16)<ROW($H15)))+1))} | J15: =IF($C15="","",IF($K15=0,"",$C15&I15)) | K15: =IF($B15="","",IF((COUNTIFS('Format Engine'!$A$23:$A$91,'Format Engine'!$C$4,'Format Engine'!$E$23:$E$91,$B15,'Format Engine'!$D$23:$D$91,"<>P")+COUNTIFS('Format Engine'!$A$23:$A$91,'Format Engine'!$C$4,'Format Engine'!$F$23:$F$91,$B15,'Format Engine'!$D$23:$D$91,"<>P"))>0,1,0))
A16: ='Teams Master'!C14 | B16: ='Teams Master'!E14 | C16: =IF(B16="","",LEFT(B16,LEN(B16)-1)) | D16: =SUMIFS('Games Schedule'!$U$5:$U$31,'Games Schedule'!$L$5:$L$31,$B16,'Games Schedule'!$J$5:$J$31,"<>P")+SUMIFS('Games Schedule'!$V$5:$V$31,'Games Schedule'!$M$5:$M$31,$B16,'Games Schedule'!$J$5:$J$31,"<>P") | E16: =SUMIFS('Games Schedule'!$S$5:$S$31,'Games Schedule'!$L$5:$L$31,$B16,'Games Schedule'!$J$5:$J$31,"<>P")+SUMIFS('Games Schedule'!$T$5:$T$31,'Games Schedule'!$M$5:$M$31,$B16,'Games Schedule'!$J$5:$J$31,"<>P") | F16: =SUMIFS('Games Schedule'!$T$5:$T$31,'Games Schedule'!$L$5:$L$31,$B16,'Games Schedule'!$J$5:$J$31,"<>P")+SUMIFS('Games Schedule'!$S$5:$S$31,'Games Schedule'!$M$5:$M$31,$B16,'Games Schedule'!$J$5:$J$31,"<>P") | G16: =E16-F16 | H16: =D16*1000+G16 | I16: {=IF($C16="","",IF($K16=0,"",SUMPRODUCT(($C$4:$C$16=$C16)*($K$4:$K$16=1)*($H$4:$H$16>$H16))+SUMPRODUCT(($C$4:$C$16=$C16)*($K$4:$K$16=1)*($H$4:$H$16=$H16)*(ROW($H$4:$H$16)<ROW($H16)))+1))} | J16: =IF($C16="","",IF($K16=0,"",$C16&I16)) | K16: =IF($B16="","",IF((COUNTIFS('Format Engine'!$A$23:$A$91,'Format Engine'!$C$4,'Format Engine'!$E$23:$E$91,$B16,'Format Engine'!$D$23:$D$91,"<>P")+COUNTIFS('Format Engine'!$A$23:$A$91,'Format Engine'!$C$4,'Format Engine'!$F$23:$F$91,$B16,'Format Engine'!$D$23:$D$91,"<>P"))>0,1,0))

Sheet Teams Master
A1: TeamID | B1: Team Name | C1: Short Name | D1: Division | E1: Group Code | F1: Jersey Color Home | G1: Jersey Color Away | H1: Contact Name | I1: Contact Email | J1: Contact Phone | K1: Reg Status | L1: ⚠️ Rows fill automatically from Registration 2027 (Status = Fully Registered or Host Registered). Give each team a Short Name + Jerseys in the Team Styles table (O:R) → | M1: Code Check | O1: Team Name | P1: Short Name | Q1: Jersey Home | R1: Jersey Away
A2: =IF($C2="","",IF($D2="Men","M"&COUNTIF($D$2:$D2,"Men"),"W"&COUNTIF($D$2:$D2,"Women"))) | B2: =IFERROR(INDEX('Registration 2027'!$A$2:$A$45,MATCH(ROW()-1,'Registration 2027'!$U$2:$U$53,0)),"") | C2: =IF($B2="","",IFERROR(_xlfn.XLOOKUP($B2,TeamStyles[Team Name],TeamStyles[Short Name]),"⚠ add to Team Styles")) | D2: =IFERROR(INDEX('Registration 2027'!$B$2:$B$45,MATCH(ROW()-1,'Registration 2027'!$U$2:$U$53,0)),"") | E2: A1 | F2: =IF($B2="","",IFERROR(_xlfn.XLOOKUP($B2,TeamStyles[Team Name],TeamStyles[Jersey Home]),"⚠ add to Team Styles")) | G2: =IF($B2="","",IFERROR(_xlfn.XLOOKUP($B2,TeamStyles[Team Name],TeamStyles[Jersey Away]),"⚠ add to Team Styles")) | H2: =IFERROR(_xlfn.LET(_xlpm.v,INDEX('Registration 2027'!$K$2:$K$45,MATCH(ROW()-1,'Registration 2027'!$U$2:$U$53,0)),IF(OR(_xlpm.v=0,_xlpm.v=""),"",_xlpm.v)),"") | I2: =IFERROR(_xlfn.LET(_xlpm.v,INDEX('Registration 2027'!$L$2:$L$45,MATCH(ROW()-1,'Registration 2027'!$U$2:$U$53,0)),IF(OR(_xlpm.v=0,_xlpm.v=""),"",_xlpm.v)),"") | J2: =IFERROR(_xlfn.LET(_xlpm.v,INDEX('Registration 2027'!$N$2:$N$45,MATCH(ROW()-1,'Registration 2027'!$U$2:$U$53,0)),IF(OR(_xlpm.v=0,_xlpm.v=""),"",_xlpm.v)),"") | K2: =IFERROR(INDEX('Registration 2027'!$J$2:$J$45,MATCH(ROW()-1,'Registration 2027'!$U$2:$U$53,0)),"") | M2: =IF(E2="","",IF(COUNTIF($E$2:$E$14,E2)>1,"DUPLICATE","OK")) | O2: Harbor HC | P2: HAR | Q2: Navy | R2: White
A3: =IF($C3="","",IF($D3="Men","M"&COUNTIF($D$2:$D3,"Men"),"W"&COUNTIF($D$2:$D3,"Women"))) | B3: =IFERROR(INDEX('Registration 2027'!$A$2:$A$45,MATCH(ROW()-1,'Registration 2027'!$U$2:$U$53,0)),"") | C3: =IF($B3="","",IFERROR(_xlfn.XLOOKUP($B3,TeamStyles[Team Name],TeamStyles[Short Name]),"⚠ add to Team Styles")) | D3: =IFERROR(INDEX('Registration 2027'!$B$2:$B$45,MATCH(ROW()-1,'Registration 2027'!$U$2:$U$53,0)),"") | E3: A3 | F3: =IF($B3="","",IFERROR(_xlfn.XLOOKUP($B3,TeamStyles[Team Name],TeamStyles[Jersey Home]),"⚠ add to Team Styles")) | G3: =IF($B3="","",IFERROR(_xlfn.XLOOKUP($B3,TeamStyles[Team Name],TeamStyles[Jersey Away]),"⚠ add to Team Styles")) | H3: =IFERROR(_xlfn.LET(_xlpm.v,INDEX('Registration 2027'!$K$2:$K$45,MATCH(ROW()-1,'Registration 2027'!$U$2:$U$53,0)),IF(OR(_xlpm.v=0,_xlpm.v=""),"",_xlpm.v)),"") | I3: =IFERROR(_xlfn.LET(_xlpm.v,INDEX('Registration 2027'!$L$2:$L$45,MATCH(ROW()-1,'Registration 2027'!$U$2:$U$53,0)),IF(OR(_xlpm.v=0,_xlpm.v=""),"",_xlpm.v)),"") | J3: =IFERROR(_xlfn.LET(_xlpm.v,INDEX('Registration 2027'!$N$2:$N$45,MATCH(ROW()-1,'Registration 2027'!$U$2:$U$53,0)),IF(OR(_xlpm.v=0,_xlpm.v=""),"",_xlpm.v)),"") | K3: =IFERROR(INDEX('Registration 2027'!$J$2:$J$45,MATCH(ROW()-1,'Registration 2027'!$U$2:$U$53,0)),"") | M3: =IF(E3="","",IF(COUNTIF($E$2:$E$14,E3)>1,"DUPLICATE","OK")) | O3: Mesa Valley | P3: MES | Q3: Red | R3: White
A4: =IF($C4="","",IF($D4="Men","M"&COUNTIF($D$2:$D4,"Men"),"W"&COUNTIF($D$2:$D4,"Women"))) | B4: =IFERROR(INDEX('Registration 2027'!$A$2:$A$45,MATCH(ROW()-1,'Registration 2027'!$U$2:$U$53,0)),"") | C4: =IF($B4="","",IFERROR(_xlfn.XLOOKUP($B4,TeamStyles[Team Name],TeamStyles[Short Name]),"⚠ add to Team Styles")) | D4: =IFERROR(INDEX('Registration 2027'!$B$2:$B$45,MATCH(ROW()-1,'Registration 2027'!$U$2:$U$53,0)),"") | E4: B1 | F4: =IF($B4="","",IFERROR(_xlfn.XLOOKUP($B4,TeamStyles[Team Name],TeamStyles[Jersey Home]),"⚠ add to Team Styles")) | G4: =IF($B4="","",IFERROR(_xlfn.XLOOKUP($B4,TeamStyles[Team Name],TeamStyles[Jersey Away]),"⚠ add to Team Styles")) | H4: =IFERROR(_xlfn.LET(_xlpm.v,INDEX('Registration 2027'!$K$2:$K$45,MATCH(ROW()-1,'Registration 2027'!$U$2:$U$53,0)),IF(OR(_xlpm.v=0,_xlpm.v=""),"",_xlpm.v)),"") | I4: =IFERROR(_xlfn.LET(_xlpm.v,INDEX('Registration 2027'!$L$2:$L$45,MATCH(ROW()-1,'Registration 2027'!$U$2:$U$53,0)),IF(OR(_xlpm.v=0,_xlpm.v=""),"",_xlpm.v)),"") | J4: =IFERROR(_xlfn.LET(_xlpm.v,INDEX('Registration 2027'!$N$2:$N$45,MATCH(ROW()-1,'Registration 2027'!$U$2:$U$53,0)),IF(OR(_xlpm.v=0,_xlpm.v=""),"",_xlpm.v)),"") | K4: =IFERROR(INDEX('Registration 2027'!$J$2:$J$45,MATCH(ROW()-1,'Registration 2027'!$U$2:$U$53,0)),"") | M4: =IF(E4="","",IF(COUNTIF($E$2:$E$14,E4)>1,"DUPLICATE","OK")) | O4: Redwood United | P4: RED | Q4: Green | R4: White
A5: =IF($C5="","",IF($D5="Men","M"&COUNTIF($D$2:$D5,"Men"),"W"&COUNTIF($D$2:$D5,"Women"))) | B5: =IFERROR(INDEX('Registration 2027'!$A$2:$A$45,MATCH(ROW()-1,'Registration 2027'!$U$2:$U$53,0)),"") | C5: =IF($B5="","",IFERROR(_xlfn.XLOOKUP($B5,TeamStyles[Team Name],TeamStyles[Short Name]),"⚠ add to Team Styles")) | D5: =IFERROR(INDEX('Registration 2027'!$B$2:$B$45,MATCH(ROW()-1,'Registration 2027'!$U$2:$U$53,0)),"") | E5: B3 | F5: =IF($B5="","",IFERROR(_xlfn.XLOOKUP($B5,TeamStyles[Team Name],TeamStyles[Jersey Home]),"⚠ add to Team Styles")) | G5: =IF($B5="","",IFERROR(_xlfn.XLOOKUP($B5,TeamStyles[Team Name],TeamStyles[Jersey Away]),"⚠ add to Team Styles")) | H5: =IFERROR(_xlfn.LET(_xlpm.v,INDEX('Registration 2027'!$K$2:$K$45,MATCH(ROW()-1,'Registration 2027'!$U$2:$U$53,0)),IF(OR(_xlpm.v=0,_xlpm.v=""),"",_xlpm.v)),"") | I5: =IFERROR(_xlfn.LET(_xlpm.v,INDEX('Registration 2027'!$L$2:$L$45,MATCH(ROW()-1,'Registration 2027'!$U$2:$U$53,0)),IF(OR(_xlpm.v=0,_xlpm.v=""),"",_xlpm.v)),"") | J5: =IFERROR(_xlfn.LET(_xlpm.v,INDEX('Registration 2027'!$N$2:$N$45,MATCH(ROW()-1,'Registration 2027'!$U$2:$U$53,0)),IF(OR(_xlpm.v=0,_xlpm.v=""),"",_xlpm.v)),"") | K5: =IFERROR(INDEX('Registration 2027'!$J$2:$J$45,MATCH(ROW()-1,'Registration 2027'!$U$2:$U$53,0)),"") | M5: =IF(E5="","",IF(COUNTIF($E$2:$E$14,E5)>1,"DUPLICATE","OK")) | O5: Pacific Coast | P5: PAC | Q5: Blue | R5: Yellow
A6: =IF($C6="","",IF($D6="Men","M"&COUNTIF($D$2:$D6,"Men"),"W"&COUNTIF($D$2:$D6,"Women"))) | B6: =IFERROR(INDEX('Registration 2027'!$A$2:$A$45,MATCH(ROW()-1,'Registration 2027'!$U$2:$U$53,0)),"") | C6: =IF($B6="","",IFERROR(_xlfn.XLOOKUP($B6,TeamStyles[Team Name],TeamStyles[Short Name]),"⚠ add to Team Styles")) | D6: =IFERROR(INDEX('Registration 2027'!$B$2:$B$45,MATCH(ROW()-1,'Registration 2027'!$U$2:$U$53,0)),"") | E6: B4 | F6: =IF($B6="","",IFERROR(_xlfn.XLOOKUP($B6,TeamStyles[Team Name],TeamStyles[Jersey Home]),"⚠ add to Team Styles")) | G6: =IF($B6="","",IFERROR(_xlfn.XLOOKUP($B6,TeamStyles[Team Name],TeamStyles[Jersey Away]),"⚠ add to Team Styles")) | H6: =IFERROR(_xlfn.LET(_xlpm.v,INDEX('Registration 2027'!$K$2:$K$45,MATCH(ROW()-1,'Registration 2027'!$U$2:$U$53,0)),IF(OR(_xlpm.v=0,_xlpm.v=""),"",_xlpm.v)),"") | I6: =IFERROR(_xlfn.LET(_xlpm.v,INDEX('Registration 2027'!$L$2:$L$45,MATCH(ROW()-1,'Registration 2027'!$U$2:$U$53,0)),IF(OR(_xlpm.v=0,_xlpm.v=""),"",_xlpm.v)),"") | J6: =IFERROR(_xlfn.LET(_xlpm.v,INDEX('Registration 2027'!$N$2:$N$45,MATCH(ROW()-1,'Registration 2027'!$U$2:$U$53,0)),IF(OR(_xlpm.v=0,_xlpm.v=""),"",_xlpm.v)),"") | K6: =IFERROR(INDEX('Registration 2027'!$J$2:$J$45,MATCH(ROW()-1,'Registration 2027'!$U$2:$U$53,0)),"") | M6: =IF(E6="","",IF(COUNTIF($E$2:$E$14,E6)>1,"DUPLICATE","OK")) | O6: Summit City | P6: SUM | Q6: Black | R6: Orange
A7: =IF($C7="","",IF($D7="Men","M"&COUNTIF($D$2:$D7,"Men"),"W"&COUNTIF($D$2:$D7,"Women"))) | B7: =IFERROR(INDEX('Registration 2027'!$A$2:$A$45,MATCH(ROW()-1,'Registration 2027'!$U$2:$U$53,0)),"") | C7: =IF($B7="","",IFERROR(_xlfn.XLOOKUP($B7,TeamStyles[Team Name],TeamStyles[Short Name]),"⚠ add to Team Styles")) | D7: =IFERROR(INDEX('Registration 2027'!$B$2:$B$45,MATCH(ROW()-1,'Registration 2027'!$U$2:$U$53,0)),"") | E7: A2 | F7: =IF($B7="","",IFERROR(_xlfn.XLOOKUP($B7,TeamStyles[Team Name],TeamStyles[Jersey Home]),"⚠ add to Team Styles")) | G7: =IF($B7="","",IFERROR(_xlfn.XLOOKUP($B7,TeamStyles[Team Name],TeamStyles[Jersey Away]),"⚠ add to Team Styles")) | H7: =IFERROR(_xlfn.LET(_xlpm.v,INDEX('Registration 2027'!$K$2:$K$45,MATCH(ROW()-1,'Registration 2027'!$U$2:$U$53,0)),IF(OR(_xlpm.v=0,_xlpm.v=""),"",_xlpm.v)),"") | I7: =IFERROR(_xlfn.LET(_xlpm.v,INDEX('Registration 2027'!$L$2:$L$45,MATCH(ROW()-1,'Registration 2027'!$U$2:$U$53,0)),IF(OR(_xlpm.v=0,_xlpm.v=""),"",_xlpm.v)),"") | J7: =IFERROR(_xlfn.LET(_xlpm.v,INDEX('Registration 2027'!$N$2:$N$45,MATCH(ROW()-1,'Registration 2027'!$U$2:$U$53,0)),IF(OR(_xlpm.v=0,_xlpm.v=""),"",_xlpm.v)),"") | K7: =IFERROR(INDEX('Registration 2027'!$J$2:$J$45,MATCH(ROW()-1,'Registration 2027'!$U$2:$U$53,0)),"") | M7: =IF(E7="","",IF(COUNTIF($E$2:$E$14,E7)>1,"DUPLICATE","OK")) | O7: Lakeside HB | P7: LAK | Q7: Sky Blue | R7: White
A8: =IF($C8="","",IF($D8="Men","M"&COUNTIF($D$2:$D8,"Men"),"W"&COUNTIF($D$2:$D8,"Women"))) | B8: =IFERROR(INDEX('Registration 2027'!$A$2:$A$45,MATCH(ROW()-1,'Registration 2027'!$U$2:$U$53,0)),"") | C8: =IF($B8="","",IFERROR(_xlfn.XLOOKUP($B8,TeamStyles[Team Name],TeamStyles[Short Name]),"⚠ add to Team Styles")) | D8: =IFERROR(INDEX('Registration 2027'!$B$2:$B$45,MATCH(ROW()-1,'Registration 2027'!$U$2:$U$53,0)),"") | E8: B2 | F8: =IF($B8="","",IFERROR(_xlfn.XLOOKUP($B8,TeamStyles[Team Name],TeamStyles[Jersey Home]),"⚠ add to Team Styles")) | G8: =IF($B8="","",IFERROR(_xlfn.XLOOKUP($B8,TeamStyles[Team Name],TeamStyles[Jersey Away]),"⚠ add to Team Styles")) | H8: =IFERROR(_xlfn.LET(_xlpm.v,INDEX('Registration 2027'!$K$2:$K$45,MATCH(ROW()-1,'Registration 2027'!$U$2:$U$53,0)),IF(OR(_xlpm.v=0,_xlpm.v=""),"",_xlpm.v)),"") | I8: =IFERROR(_xlfn.LET(_xlpm.v,INDEX('Registration 2027'!$L$2:$L$45,MATCH(ROW()-1,'Registration 2027'!$U$2:$U$53,0)),IF(OR(_xlpm.v=0,_xlpm.v=""),"",_xlpm.v)),"") | J8: =IFERROR(_xlfn.LET(_xlpm.v,INDEX('Registration 2027'!$N$2:$N$45,MATCH(ROW()-1,'Registration 2027'!$U$2:$U$53,0)),IF(OR(_xlpm.v=0,_xlpm.v=""),"",_xlpm.v)),"") | K8: =IFERROR(INDEX('Registration 2027'!$J$2:$J$45,MATCH(ROW()-1,'Registration 2027'!$U$2:$U$53,0)),"") | M8: =IF(E8="","",IF(COUNTIF($E$2:$E$14,E8)>1,"DUPLICATE","OK")) | O8: Canyon Ridge HC | P8: CAN | Q8: Maroon | R8: Gold
A9: =IF($C9="","",IF($D9="Men","M"&COUNTIF($D$2:$D9,"Men"),"W"&COUNTIF($D$2:$D9,"Women"))) | B9: =IFERROR(INDEX('Registration 2027'!$A$2:$A$45,MATCH(ROW()-1,'Registration 2027'!$U$2:$U$53,0)),"") | C9: =IF($B9="","",IFERROR(_xlfn.XLOOKUP($B9,TeamStyles[Team Name],TeamStyles[Short Name]),"⚠ add to Team Styles")) | D9: =IFERROR(INDEX('Registration 2027'!$B$2:$B$45,MATCH(ROW()-1,'Registration 2027'!$U$2:$U$53,0)),"") | E9: A4 | F9: =IF($B9="","",IFERROR(_xlfn.XLOOKUP($B9,TeamStyles[Team Name],TeamStyles[Jersey Home]),"⚠ add to Team Styles")) | G9: =IF($B9="","",IFERROR(_xlfn.XLOOKUP($B9,TeamStyles[Team Name],TeamStyles[Jersey Away]),"⚠ add to Team Styles")) | H9: =IFERROR(_xlfn.LET(_xlpm.v,INDEX('Registration 2027'!$K$2:$K$45,MATCH(ROW()-1,'Registration 2027'!$U$2:$U$53,0)),IF(OR(_xlpm.v=0,_xlpm.v=""),"",_xlpm.v)),"") | I9: =IFERROR(_xlfn.LET(_xlpm.v,INDEX('Registration 2027'!$L$2:$L$45,MATCH(ROW()-1,'Registration 2027'!$U$2:$U$53,0)),IF(OR(_xlpm.v=0,_xlpm.v=""),"",_xlpm.v)),"") | J9: =IFERROR(_xlfn.LET(_xlpm.v,INDEX('Registration 2027'!$N$2:$N$45,MATCH(ROW()-1,'Registration 2027'!$U$2:$U$53,0)),IF(OR(_xlpm.v=0,_xlpm.v=""),"",_xlpm.v)),"") | K9: =IFERROR(INDEX('Registration 2027'!$J$2:$J$45,MATCH(ROW()-1,'Registration 2027'!$U$2:$U$53,0)),"") | M9: =IF(E9="","",IF(COUNTIF($E$2:$E$14,E9)>1,"DUPLICATE","OK")) | O9: Northwind HC | P9: NOR | Q9: Gray | R9: Black
A10: =IF($C10="","",IF($D10="Men","M"&COUNTIF($D$2:$D10,"Men"),"W"&COUNTIF($D$2:$D10,"Women"))) | B10: =IFERROR(INDEX('Registration 2027'!$A$2:$A$45,MATCH(ROW()-1,'Registration 2027'!$U$2:$U$53,0)),"") | C10: =IF($B10="","",IFERROR(_xlfn.XLOOKUP($B10,TeamStyles[Team Name],TeamStyles[Short Name]),"⚠ add to Team Styles")) | D10: =IFERROR(INDEX('Registration 2027'!$B$2:$B$45,MATCH(ROW()-1,'Registration 2027'!$U$2:$U$53,0)),"") | E10: W1 | F10: =IF($B10="","",IFERROR(_xlfn.XLOOKUP($B10,TeamStyles[Team Name],TeamStyles[Jersey Home]),"⚠ add to Team Styles")) | G10: =IF($B10="","",IFERROR(_xlfn.XLOOKUP($B10,TeamStyles[Team Name],TeamStyles[Jersey Away]),"⚠ add to Team Styles")) | H10: =IFERROR(_xlfn.LET(_xlpm.v,INDEX('Registration 2027'!$K$2:$K$45,MATCH(ROW()-1,'Registration 2027'!$U$2:$U$53,0)),IF(OR(_xlpm.v=0,_xlpm.v=""),"",_xlpm.v)),"") | I10: =IFERROR(_xlfn.LET(_xlpm.v,INDEX('Registration 2027'!$L$2:$L$45,MATCH(ROW()-1,'Registration 2027'!$U$2:$U$53,0)),IF(OR(_xlpm.v=0,_xlpm.v=""),"",_xlpm.v)),"") | J10: =IFERROR(_xlfn.LET(_xlpm.v,INDEX('Registration 2027'!$N$2:$N$45,MATCH(ROW()-1,'Registration 2027'!$U$2:$U$53,0)),IF(OR(_xlpm.v=0,_xlpm.v=""),"",_xlpm.v)),"") | K10: =IFERROR(INDEX('Registration 2027'!$J$2:$J$45,MATCH(ROW()-1,'Registration 2027'!$U$2:$U$53,0)),"") | M10: =IF(E10="","",IF(COUNTIF($E$2:$E$14,E10)>1,"DUPLICATE","OK")) | O10: Harbor HC W | P10: HARW | Q10: Navy | R10: White
A11: =IF($C11="","",IF($D11="Men","M"&COUNTIF($D$2:$D11,"Men"),"W"&COUNTIF($D$2:$D11,"Women"))) | B11: =IFERROR(INDEX('Registration 2027'!$A$2:$A$45,MATCH(ROW()-1,'Registration 2027'!$U$2:$U$53,0)),"") | C11: =IF($B11="","",IFERROR(_xlfn.XLOOKUP($B11,TeamStyles[Team Name],TeamStyles[Short Name]),"⚠ add to Team Styles")) | D11: =IFERROR(INDEX('Registration 2027'!$B$2:$B$45,MATCH(ROW()-1,'Registration 2027'!$U$2:$U$53,0)),"") | E11: W3 | F11: =IF($B11="","",IFERROR(_xlfn.XLOOKUP($B11,TeamStyles[Team Name],TeamStyles[Jersey Home]),"⚠ add to Team Styles")) | G11: =IF($B11="","",IFERROR(_xlfn.XLOOKUP($B11,TeamStyles[Team Name],TeamStyles[Jersey Away]),"⚠ add to Team Styles")) | H11: =IFERROR(_xlfn.LET(_xlpm.v,INDEX('Registration 2027'!$K$2:$K$45,MATCH(ROW()-1,'Registration 2027'!$U$2:$U$53,0)),IF(OR(_xlpm.v=0,_xlpm.v=""),"",_xlpm.v)),"") | I11: =IFERROR(_xlfn.LET(_xlpm.v,INDEX('Registration 2027'!$L$2:$L$45,MATCH(ROW()-1,'Registration 2027'!$U$2:$U$53,0)),IF(OR(_xlpm.v=0,_xlpm.v=""),"",_xlpm.v)),"") | J11: =IFERROR(_xlfn.LET(_xlpm.v,INDEX('Registration 2027'!$N$2:$N$45,MATCH(ROW()-1,'Registration 2027'!$U$2:$U$53,0)),IF(OR(_xlpm.v=0,_xlpm.v=""),"",_xlpm.v)),"") | K11: =IFERROR(INDEX('Registration 2027'!$J$2:$J$45,MATCH(ROW()-1,'Registration 2027'!$U$2:$U$53,0)),"") | M11: =IF(E11="","",IF(COUNTIF($E$2:$E$14,E11)>1,"DUPLICATE","OK")) | O11: Redwood United W | P11: REDW | Q11: Green | R11: White
A12: =IF($C12="","",IF($D12="Men","M"&COUNTIF($D$2:$D12,"Men"),"W"&COUNTIF($D$2:$D12,"Women"))) | B12: =IFERROR(INDEX('Registration 2027'!$A$2:$A$45,MATCH(ROW()-1,'Registration 2027'!$U$2:$U$53,0)),"") | C12: =IF($B12="","",IFERROR(_xlfn.XLOOKUP($B12,TeamStyles[Team Name],TeamStyles[Short Name]),"⚠ add to Team Styles")) | D12: =IFERROR(INDEX('Registration 2027'!$B$2:$B$45,MATCH(ROW()-1,'Registration 2027'!$U$2:$U$53,0)),"") | E12: W2 | F12: =IF($B12="","",IFERROR(_xlfn.XLOOKUP($B12,TeamStyles[Team Name],TeamStyles[Jersey Home]),"⚠ add to Team Styles")) | G12: =IF($B12="","",IFERROR(_xlfn.XLOOKUP($B12,TeamStyles[Team Name],TeamStyles[Jersey Away]),"⚠ add to Team Styles")) | H12: =IFERROR(_xlfn.LET(_xlpm.v,INDEX('Registration 2027'!$K$2:$K$45,MATCH(ROW()-1,'Registration 2027'!$U$2:$U$53,0)),IF(OR(_xlpm.v=0,_xlpm.v=""),"",_xlpm.v)),"") | I12: =IFERROR(_xlfn.LET(_xlpm.v,INDEX('Registration 2027'!$L$2:$L$45,MATCH(ROW()-1,'Registration 2027'!$U$2:$U$53,0)),IF(OR(_xlpm.v=0,_xlpm.v=""),"",_xlpm.v)),"") | J12: =IFERROR(_xlfn.LET(_xlpm.v,INDEX('Registration 2027'!$N$2:$N$45,MATCH(ROW()-1,'Registration 2027'!$U$2:$U$53,0)),IF(OR(_xlpm.v=0,_xlpm.v=""),"",_xlpm.v)),"") | K12: =IFERROR(INDEX('Registration 2027'!$J$2:$J$45,MATCH(ROW()-1,'Registration 2027'!$U$2:$U$53,0)),"") | M12: =IF(E12="","",IF(COUNTIF($E$2:$E$14,E12)>1,"DUPLICATE","OK")) | O12: Desert Storm | P12: DES | Q12: Orange | R12: Black
A13: =IF($C13="","",IF($D13="Men","M"&COUNTIF($D$2:$D13,"Men"),"W"&COUNTIF($D$2:$D13,"Women"))) | B13: =IFERROR(INDEX('Registration 2027'!$A$2:$A$45,MATCH(ROW()-1,'Registration 2027'!$U$2:$U$53,0)),"") | C13: =IF($B13="","",IFERROR(_xlfn.XLOOKUP($B13,TeamStyles[Team Name],TeamStyles[Short Name]),"⚠ add to Team Styles")) | D13: =IFERROR(INDEX('Registration 2027'!$B$2:$B$45,MATCH(ROW()-1,'Registration 2027'!$U$2:$U$53,0)),"") | E13: W4 | F13: =IF($B13="","",IFERROR(_xlfn.XLOOKUP($B13,TeamStyles[Team Name],TeamStyles[Jersey Home]),"⚠ add to Team Styles")) | G13: =IF($B13="","",IFERROR(_xlfn.XLOOKUP($B13,TeamStyles[Team Name],TeamStyles[Jersey Away]),"⚠ add to Team Styles")) | H13: =IFERROR(_xlfn.LET(_xlpm.v,INDEX('Registration 2027'!$K$2:$K$45,MATCH(ROW()-1,'Registration 2027'!$U$2:$U$53,0)),IF(OR(_xlpm.v=0,_xlpm.v=""),"",_xlpm.v)),"") | I13: =IFERROR(_xlfn.LET(_xlpm.v,INDEX('Registration 2027'!$L$2:$L$45,MATCH(ROW()-1,'Registration 2027'!$U$2:$U$53,0)),IF(OR(_xlpm.v=0,_xlpm.v=""),"",_xlpm.v)),"") | J13: =IFERROR(_xlfn.LET(_xlpm.v,INDEX('Registration 2027'!$N$2:$N$45,MATCH(ROW()-1,'Registration 2027'!$U$2:$U$53,0)),IF(OR(_xlpm.v=0,_xlpm.v=""),"",_xlpm.v)),"") | K13: =IFERROR(INDEX('Registration 2027'!$J$2:$J$45,MATCH(ROW()-1,'Registration 2027'!$U$2:$U$53,0)),"") | M13: =IF(E13="","",IF(COUNTIF($E$2:$E$14,E13)>1,"DUPLICATE","OK")) | O13: Bayview | P13: BAY | Q13: Purple | R13: White
A14: =IF($C14="","",IF($D14="Men","M"&COUNTIF($D$2:$D14,"Men"),"W"&COUNTIF($D$2:$D14,"Women"))) | B14: =IFERROR(INDEX('Registration 2027'!$A$2:$A$45,MATCH(ROW()-1,'Registration 2027'!$U$2:$U$53,0)),"") | C14: =IF($B14="","",IFERROR(_xlfn.XLOOKUP($B14,TeamStyles[Team Name],TeamStyles[Short Name]),"⚠ add to Team Styles")) | D14: =IFERROR(INDEX('Registration 2027'!$B$2:$B$45,MATCH(ROW()-1,'Registration 2027'!$U$2:$U$53,0)),"") | F14: =IF($B14="","",IFERROR(_xlfn.XLOOKUP($B14,TeamStyles[Team Name],TeamStyles[Jersey Home]),"⚠ add to Team Styles")) | G14: =IF($B14="","",IFERROR(_xlfn.XLOOKUP($B14,TeamStyles[Team Name],TeamStyles[Jersey Away]),"⚠ add to Team Styles")) | H14: =IFERROR(_xlfn.LET(_xlpm.v,INDEX('Registration 2027'!$K$2:$K$45,MATCH(ROW()-1,'Registration 2027'!$U$2:$U$53,0)),IF(OR(_xlpm.v=0,_xlpm.v=""),"",_xlpm.v)),"") | I14: =IFERROR(_xlfn.LET(_xlpm.v,INDEX('Registration 2027'!$L$2:$L$45,MATCH(ROW()-1,'Registration 2027'!$U$2:$U$53,0)),IF(OR(_xlpm.v=0,_xlpm.v=""),"",_xlpm.v)),"") | J14: =IFERROR(_xlfn.LET(_xlpm.v,INDEX('Registration 2027'!$N$2:$N$45,MATCH(ROW()-1,'Registration 2027'!$U$2:$U$53,0)),IF(OR(_xlpm.v=0,_xlpm.v=""),"",_xlpm.v)),"") | K14: =IFERROR(INDEX('Registration 2027'!$J$2:$J$45,MATCH(ROW()-1,'Registration 2027'!$U$2:$U$53,0)),"") | M14: =IF(E14="","",IF(COUNTIF($E$2:$E$14,E14)>1,"DUPLICATE","OK")) | O14: Valley Storm HC | P14: VAL | Q14: Teal | R14: White

Sheet Referees Master
A1: REFEREE MASTER
A2: One row per referee: contacts and travel costs. Blue cells = type; Total Cost calculates. Assign referee pairs to games on Games Schedule; driving shifts on Referee Pickup Drop Off.
A3: RefID | B3: Name | C3: Location | D3: Email | E3: Phone | F3: Phone WhatsApp | G3: Type | H3: Flight Cost | I3: Hotel Cost | J3: Per Diem | K3: Car Rental | L3: Total Cost | M3: Payment Method | N3: Pair # | O3: Host-club affiliated? | R3: Referee 1 | S3: Referee 2 | T3: Pair Label (used in schedule) | U3: Host-club pair?
A4: R1 | B4: Selin Ekstrom | C4: Overseas | D4: selin.ekstrom@example.org | E4: 555-0139 | F4: 555-0146 | G4: International | L4: =SUM(H4:K4) | M4: Wire | N4: =ROUNDUP((ROW()-1)/2,0) | O4: No | R4: =B4 | S4: =B5 | T4: =R4&" / "&S4 | U4: =IF(COUNTIFS($N$4:$N$13,ROW()-2,$O$4:$O$13,"Yes")>0,"Yes","No")
A5: R2 | B5: Jasper Holm | C5: Overseas | D5: jasper.holm@example.org | E5: 555-0153 | F5: 555-0160 | G5: International | L5: =SUM(H5:K5) | M5: Wire | N5: =ROUNDUP((ROW()-1)/2,0) | O5: No | R5: =B6 | S5: =B7 | T5: =R5&" / "&S5 | U5: =IF(COUNTIFS($N$4:$N$13,ROW()-2,$O$4:$O$13,"Yes")>0,"Yes","No")
A6: R3 | B6: Camila Duarte | C6: USA | D6: camila.duarte@example.org | E6: 555-0167 | F6: 555-0174 | G6: Domestic | L6: =SUM(H6:K6) | M6: ACH | N6: =ROUNDUP((ROW()-1)/2,0) | O6: No | R6: =B8 | S6: =B9 | T6: =R6&" / "&S6 | U6: =IF(COUNTIFS($N$4:$N$13,ROW()-2,$O$4:$O$13,"Yes")>0,"Yes","No")
A7: R4 | B7: Nico Moretti | C7: USA | D7: nico.moretti@example.org | E7: 555-0181 | F7: 555-0188 | G7: Domestic | L7: =SUM(H7:K7) | M7: ACH | N7: =ROUNDUP((ROW()-1)/2,0) | O7: No | R7: =B10 | S7: =B11 | T7: =R7&" / "&S7 | U7: =IF(COUNTIFS($N$4:$N$13,ROW()-2,$O$4:$O$13,"Yes")>0,"Yes","No")
A8: R5 | B8: Leo Larsen | C8: USA | D8: leo.larsen@example.org | E8: 555-0195 | F8: 555-0102 | G8: Domestic | L8: =SUM(H8:K8) | M8: Check | N8: =ROUNDUP((ROW()-1)/2,0) | O8: No | R8: =B12 | S8: =B13 | T8: =R8&" / "&S8 | U8: =IF(COUNTIFS($N$4:$N$13,ROW()-2,$O$4:$O$13,"Yes")>0,"Yes","No")
A9: R6 | B9: Silas Kaplan | C9: USA | D9: silas.kaplan@example.org | E9: 555-0109 | F9: 555-0116 | G9: Domestic | L9: =SUM(H9:K9) | M9: Check | N9: =ROUNDUP((ROW()-1)/2,0) | O9: No
A10: R7 | B10: Liam Garza | C10: USA | D10: liam.garza@example.org | E10: 555-0123 | F10: 555-0130 | G10: Local | L10: =SUM(H10:K10) | N10: =ROUNDUP((ROW()-1)/2,0) | O10: Yes
A11: R8 | B11: Emeka Dahl | C11: USA | D11: emeka.dahl@example.org | E11: 555-0137 | F11: 555-0144 | G11: Local | L11: =SUM(H11:K11) | N11: =ROUNDUP((ROW()-1)/2,0) | O11: Yes
A12: R9 | B12: Kira Engel | C12: USA | D12: kira.engel@example.org | E12: 555-0151 | F12: 555-0158 | G12: Domestic | L12: =SUM(H12:K12) | N12: =ROUNDUP((ROW()-1)/2,0) | O12: No
A13: R10 | B13: Erik Patel | C13: USA | D13: erik.patel@example.org | E13: 555-0165 | F13: 555-0172 | G13: Domestic | L13: =SUM(H13:K13) | N13: =ROUNDUP((ROW()-1)/2,0) | O13: No
H14: =SUBTOTAL(109,RefereesMaster[Flight Cost]) | I14: =SUBTOTAL(109,RefereesMaster[Hotel Cost]) | J14: =SUBTOTAL(109,RefereesMaster[Per Diem]) | L14: =SUBTOTAL(109,RefereesMaster[Total Cost])

Sheet Medical Staff Master
A1: MEDICAL STAFF MASTER (PHYSIO / ATHLETIC TRAINER)
A2: Type medical staff names & payment handles (blue). Hours pull automatically from the Games Schedule medical staff column; pay = hours × the rate in B3.
A3: Rate ($/hr): | B3: 40
A5: StaffID | B5: Name | C5: Hours Worked | D5: Rate $/Hr | E5: Total Owed | F5: Payment Handle
A6: PT1 | B6: Tomas Toivonen | C6: {=SUMPRODUCT(('Games Schedule'!$AA$5:$AA$31=$B6)*IFERROR('Games Schedule'!$H$5:$H$31-'Games Schedule'!$D$5:$D$31,0))*24} | D6: =$B$3 | E6: =C6*D6 | F6: @tomas-toivonen
A7: PT2 | B7: Kofi Nordin | C7: {=SUMPRODUCT(('Games Schedule'!$AA$5:$AA$31=$B7)*IFERROR('Games Schedule'!$H$5:$H$31-'Games Schedule'!$D$5:$D$31,0))*24} | D7: =$B$3 | E7: =C7*D7 | F7: @kofi-nordin
A8: PT3 | B8: Kira Kim | C8: {=SUMPRODUCT(('Games Schedule'!$AA$5:$AA$31=$B8)*IFERROR('Games Schedule'!$H$5:$H$31-'Games Schedule'!$D$5:$D$31,0))*24} | D8: =$B$3 | E8: =C8*D8 | F8: @kira-kim
A9: PT4 | B9: Astrid Nyberg | C9: {=SUMPRODUCT(('Games Schedule'!$AA$5:$AA$31=$B9)*IFERROR('Games Schedule'!$H$5:$H$31-'Games Schedule'!$D$5:$D$31,0))*24} | D9: =$B$3 | E9: =C9*D9 | F9: @astrid-nyberg
A11: Total | E11: =SUM(E6:E9)

Sheet Products Master
A1: CONCESSION & MERCH PRODUCTS MASTER
A2: One row per item sold at the booth: set Description, Category, COGS & Sale Price (blue). Profit & margin calculate. Feeds Price List Concession and revenue projections. Add items on the first empty table row.
A3: ProductID | B3: Description | C3: Category | D3: COGS | E3: Sale Price | F3: Gross Profit | G3: Gross Margin
A4: F01 | B4: Black coffee, per pod | C4: Beverage | D4: 0.58 | E4: 2.25 | F4: =E4-D4 | G4: =IF(E4=0,0,F4/E4)
A5: F02 | B5: Hot chocolate, per pod | C5: Beverage | D5: 0.95 | E5: 2.25 | F5: =E5-D5 | G5: =IF(E5=0,0,F5/E5)
A6: F03 | B6: Tea, per pod | C6: Beverage | D6: 0.5 | E6: 1.75 | F6: =E6-D6 | G6: =IF(E6=0,0,F6/E6)
A7: F04 | B7: Sports drink 12 oz | C7: Beverage | D7: 0.9 | E7: 2.75 | F7: =E7-D7 | G7: =IF(E7=0,0,F7/E7)
A8: F05 | B8: Sports drink 12 oz, 2 for $4 | C8: Beverage | D8: 1.8 | E8: 4 | F8: =E8-D8 | G8: =IF(E8=0,0,F8/E8)
A9: F06 | B9: Grilled sandwich | C9: Food | D9: 2.2 | E9: 6 | F9: =E9-D9 | G9: =IF(E9=0,0,F9/E9)
A10: F07 | B10: Grilled sandwich, vegetarian | C10: Food | D10: 1.9 | E10: 5 | F10: =E10-D10 | G10: =IF(E10=0,0,F10/E10)
A11: F08 | B11: Grilled sandwich + sports drink combo | C11: Combo | D11: 3.1 | E11: 7.5 | F11: =E11-D11 | G11: =IF(E11=0,0,F11/E11)
A12: F09 | B12: Vegetarian sandwich + sports drink combo | C12: Combo | D12: 2.9 | E12: 6.5 | F12: =E12-D12 | G12: =IF(E12=0,0,F12/E12)
A13: F10 | B13: Rice cake | C13: Food | D13: 1.4 | E13: 3.5 | F13: =E13-D13 | G13: =IF(E13=0,0,F13/E13)
A14: F11 | B14: Crepes | C14: Food | D14: 1.6 | E14: 4.5 | F14: =E14-D14 | G14: =IF(E14=0,0,F14/E14)
A15: F12 | B15: Energy bar, single | C15: Food | D15: 0.8 | E15: 2.25 | F15: =E15-D15 | G15: =IF(E15=0,0,F15/E15)
... A30: M12 | B30: Cap and shirt bundle | C30: Merchandise | D30: 19 | E30: 40 | F30: =E30-D30 | G30: =IF(E30=0,0,F30/E30)

Sheet ----- REGISTRATION -----
A1: REGISTRATION

Sheet Registration 2027
A1: Team | B1: Division | C1: Invitation Sent | D1: Deposit | E1: Deposit Date | F1: Final Payment | G1: Final Pay Date | H1: Total Amount | I1: Roster Submitted | J1: Status | K1: Contact Name | L1: Contact Email | M1: WhatsApp 1 | N1: Phone 1 | O1: Host Team | P1: Entry Confirmed | Q1: TOURNAMENT CAPACITY SETTINGS | T1: Confirmed | U1: Roster Seq
A2: Harbor HC | B2: Men | C2: x | D2: =IF($E2<>"",'Budget Dashboard'!$N$14,"") | F2: =IF($G2<>"",'Budget Dashboard'!$N$15,"") | H2: =IF(OR($D2<>"",$F2<>""),N($D2)+N($F2),"") | I2: x | J2: =IF(O2="Yes","Host Registered",IF(AND(H2<>"",H2>=$R$3),"Fully Registered",IF(D2<>"","Deposit Paid",""))) | K2: Tomas Nieminen | L2: tomas.nieminen@example.org | M2: 555-0107 | N2: 555-0114 | O2: Yes | P2: x | Q2: 📝 INPUTS (Editable) | T2: =IF(OR($J2="Fully Registered",$J2="Host Registered"),1,0) | U2: =IF($T2=0,"",IF($B2="Men",SUMIFS($T$2:$T2,$B$2:$B2,"Men"),SUMIFS($T$2:$T$40,$B$2:$B$40,"Men")+SUMIFS($T$2:$T2,$B$2:$B2,"Women")))
A3: Mesa Valley | B3: Men | C3: x | D3: =IF($E3<>"",'Budget Dashboard'!$N$14,"") | E3: 46279 | F3: =IF($G3<>"",'Budget Dashboard'!$N$15,"") | G3: 46357 | H3: =IF(OR($D3<>"",$F3<>""),N($D3)+N($F3),"") | I3: x | J3: =IF(O3="Yes","Host Registered",IF(AND(H3<>"",H3>=$R$3),"Fully Registered",IF(D3<>"","Deposit Paid",""))) | K3: Isabel Moretti | L3: isabel.moretti@example.org | M3: 555-0121 | N3: 555-0128 | O3: No | P3: x | Q3: Registration Fee: | R3: =Inputs!C18 | T3: =IF(OR($J3="Fully Registered",$J3="Host Registered"),1,0) | U3: =IF($T3=0,"",IF($B3="Men",SUMIFS($T$2:$T3,$B$2:$B3,"Men"),SUMIFS($T$2:$T$40,$B$2:$B$40,"Men")+SUMIFS($T$2:$T3,$B$2:$B3,"Women")))
A4: Redwood United | B4: Men | C4: x | D4: =IF($E4<>"",'Budget Dashboard'!$N$14,"") | E4: 46286 | F4: =IF($G4<>"",'Budget Dashboard'!$N$15,"") | G4: 46360 | H4: =IF(OR($D4<>"",$F4<>""),N($D4)+N($F4),"") | I4: x | J4: =IF(O4="Yes","Host Registered",IF(AND(H4<>"",H4>=$R$3),"Fully Registered",IF(D4<>"","Deposit Paid",""))) | K4: Freya Torres | L4: freya.torres@example.org | M4: 555-0135 | N4: 555-0142 | O4: No | P4: x | Q4: Max Total Teams: | R4: =Inputs!C13 | T4: =IF(OR($J4="Fully Registered",$J4="Host Registered"),1,0) | U4: =IF($T4=0,"",IF($B4="Men",SUMIFS($T$2:$T4,$B$2:$B4,"Men"),SUMIFS($T$2:$T$40,$B$2:$B$40,"Men")+SUMIFS($T$2:$T4,$B$2:$B4,"Women")))
A5: Pacific Coast | B5: Men | C5: x | D5: =IF($E5<>"",'Budget Dashboard'!$N$14,"") | E5: 46295 | F5: =IF($G5<>"",'Budget Dashboard'!$N$15,"") | G5: 46365 | H5: =IF(OR($D5<>"",$F5<>""),N($D5)+N($F5),"") | I5: x | J5: =IF(O5="Yes","Host Registered",IF(AND(H5<>"",H5>=$R$3),"Fully Registered",IF(D5<>"","Deposit Paid",""))) | K5: Pia Larsen | L5: pia.larsen@example.org | M5: 555-0149 | N5: 555-0156 | O5: No | P5: x | Q5: Max Men's Teams: | R5: =Inputs!C14 | T5: =IF(OR($J5="Fully Registered",$J5="Host Registered"),1,0) | U5: =IF($T5=0,"",IF($B5="Men",SUMIFS($T$2:$T5,$B$2:$B5,"Men"),SUMIFS($T$2:$T$40,$B$2:$B$40,"Men")+SUMIFS($T$2:$T5,$B$2:$B5,"Women")))
A6: Summit City | B6: Men | C6: x | D6: =IF($E6<>"",'Budget Dashboard'!$N$14,"") | E6: 46297 | F6: =IF($G6<>"",'Budget Dashboard'!$N$15,"") | G6: 46371 | H6: =IF(OR($D6<>"",$F6<>""),N($D6)+N($F6),"") | I6: x | J6: =IF(O6="Yes","Host Registered",IF(AND(H6<>"",H6>=$R$3),"Fully Registered",IF(D6<>"","Deposit Paid",""))) | K6: Priya Kaplan | L6: priya.kaplan@example.org | M6: 555-0163 | N6: 555-0170 | O6: No | P6: x | Q6: Max Women's Teams: | R6: =R4-R5 | T6: =IF(OR($J6="Fully Registered",$J6="Host Registered"),1,0) | U6: =IF($T6=0,"",IF($B6="Men",SUMIFS($T$2:$T6,$B$2:$B6,"Men"),SUMIFS($T$2:$T$40,$B$2:$B$40,"Men")+SUMIFS($T$2:$T6,$B$2:$B6,"Women")))
A7: Lakeside HB | B7: Men | C7: x | D7: =IF($E7<>"",'Budget Dashboard'!$N$14,"") | E7: 46304 | F7: =IF($G7<>"",'Budget Dashboard'!$N$15,"") | G7: 46374 | H7: =IF(OR($D7<>"",$F7<>""),N($D7)+N($F7),"") | I7: x | J7: =IF(O7="Yes","Host Registered",IF(AND(H7<>"",H7>=$R$3),"Fully Registered",IF(D7<>"","Deposit Paid",""))) | K7: Jalen Ibrahim | L7: jalen.ibrahim@example.org | M7: 555-0177 | N7: 555-0184 | O7: No | P7: x | T7: =IF(OR($J7="Fully Registered",$J7="Host Registered"),1,0) | U7: =IF($T7=0,"",IF($B7="Men",SUMIFS($T$2:$T7,$B$2:$B7,"Men"),SUMIFS($T$2:$T$40,$B$2:$B$40,"Men")+SUMIFS($T$2:$T7,$B$2:$B7,"Women")))
A8: Canyon Ridge HC | B8: Men | C8: x | D8: =IF($E8<>"",'Budget Dashboard'!$N$14,"") | E8: 46310 | F8: =IF($G8<>"",'Budget Dashboard'!$N$15,"") | G8: 46393 | H8: =IF(OR($D8<>"",$F8<>""),N($D8)+N($F8),"") | I8: x | J8: =IF(O8="Yes","Host Registered",IF(AND(H8<>"",H8>=$R$3),"Fully Registered",IF(D8<>"","Deposit Paid",""))) | K8: Tove Wong | L8: tove.wong@example.org | M8: 555-0191 | N8: 555-0198 | O8: No | P8: x | Q8: 📊 REGISTRATION STATUS | T8: =IF(OR($J8="Fully Registered",$J8="Host Registered"),1,0) | U8: =IF($T8=0,"",IF($B8="Men",SUMIFS($T$2:$T8,$B$2:$B8,"Men"),SUMIFS($T$2:$T$40,$B$2:$B$40,"Men")+SUMIFS($T$2:$T8,$B$2:$B8,"Women")))
A9: Northwind HC | B9: Men | C9: x | D9: =IF($E9<>"",'Budget Dashboard'!$N$14,"") | E9: 46315 | F9: =IF($G9<>"",'Budget Dashboard'!$N$15,"") | G9: 46395 | H9: =IF(OR($D9<>"",$F9<>""),N($D9)+N($F9),"") | I9: x | J9: =IF(O9="Yes","Host Registered",IF(AND(H9<>"",H9>=$R$3),"Fully Registered",IF(D9<>"","Deposit Paid",""))) | K9: Fatima Cordova | L9: fatima.cordova@example.org | M9: 555-0105 | N9: 555-0112 | O9: No | P9: x | Q9: Host Teams: | R9: =COUNTIF($J$2:$J$45,"Host Registered") | T9: =IF(OR($J9="Fully Registered",$J9="Host Registered"),1,0) | U9: =IF($T9=0,"",IF($B9="Men",SUMIFS($T$2:$T9,$B$2:$B9,"Men"),SUMIFS($T$2:$T$40,$B$2:$B$40,"Men")+SUMIFS($T$2:$T9,$B$2:$B9,"Women")))
A10: Valley Storm HC | B10: Men | C10: x | D10: =IF($E10<>"",'Budget Dashboard'!$N$14,"") | F10: =IF($G10<>"",'Budget Dashboard'!$N$15,"") | H10: =IF(OR($D10<>"",$F10<>""),N($D10)+N($F10),"") | J10: =IF(O10="Yes","Host Registered",IF(AND(H10<>"",H10>=$R$3),"Fully Registered",IF(D10<>"","Deposit Paid",""))) | K10: Teodor Vasquez | L10: teodor.vasquez@example.org | M10: 555-0175 | N10: 555-0182 | O10: No | Q10: Fully Registered: | R10: =COUNTIF($J$2:$J$45,"Fully Registered") | T10: =IF(OR($J10="Fully Registered",$J10="Host Registered"),1,0) | U10: =IF($T10=0,"",IF($B10="Men",SUMIFS($T$2:$T10,$B$2:$B10,"Men"),SUMIFS($T$2:$T$40,$B$2:$B$40,"Men")+SUMIFS($T$2:$T10,$B$2:$B10,"Women")))
A11: Harbor HC W | B11: Women | C11: x | D11: =IF($E11<>"",'Budget Dashboard'!$N$14,"") | F11: =IF($G11<>"",'Budget Dashboard'!$N$15,"") | H11: =IF(OR($D11<>"",$F11<>""),N($D11)+N($F11),"") | I11: x | J11: =IF(O11="Yes","Host Registered",IF(AND(H11<>"",H11>=$R$3),"Fully Registered",IF(D11<>"","Deposit Paid",""))) | K11: Talia Adeyemi | L11: talia.adeyemi@example.org | M11: 555-0119 | N11: 555-0126 | O11: Yes | P11: x | Q11: Deposit Paid: | R11: =COUNTIF($J$2:$J$45,"Deposit Paid") | T11: =IF(OR($J11="Fully Registered",$J11="Host Registered"),1,0) | U11: =IF($T11=0,"",IF($B11="Men",SUMIFS($T$2:$T11,$B$2:$B11,"Men"),SUMIFS($T$2:$T$40,$B$2:$B$40,"Men")+SUMIFS($T$2:$T11,$B$2:$B11,"Women")))
A12: Redwood United W | B12: Women | C12: x | D12: =IF($E12<>"",'Budget Dashboard'!$N$14,"") | E12: 46322 | F12: =IF($G12<>"",'Budget Dashboard'!$N$15,"") | G12: 46399 | H12: =IF(OR($D12<>"",$F12<>""),N($D12)+N($F12),"") | I12: x | J12: =IF(O12="Yes","Host Registered",IF(AND(H12<>"",H12>=$R$3),"Fully Registered",IF(D12<>"","Deposit Paid",""))) | K12: Sofia Ostrowski | L12: sofia.ostrowski@example.org | M12: 555-0133 | N12: 555-0140 | O12: No | P12: x | Q12: Total Confirmed: | R12: =R9+R10 | T12: =IF(OR($J12="Fully Registered",$J12="Host Registered"),1,0) | U12: =IF($T12=0,"",IF($B12="Men",SUMIFS($T$2:$T12,$B$2:$B12,"Men"),SUMIFS($T$2:$T$40,$B$2:$B$40,"Men")+SUMIFS($T$2:$T12,$B$2:$B12,"Women")))
A13: Desert Storm | B13: Women | C13: x | D13: =IF($E13<>"",'Budget Dashboard'!$N$14,"") | E13: 46329 | F13: =IF($G13<>"",'Budget Dashboard'!$N$15,"") | G13: 46402 | H13: =IF(OR($D13<>"",$F13<>""),N($D13)+N($F13),"") | I13: x | J13: =IF(O13="Yes","Host Registered",IF(AND(H13<>"",H13>=$R$3),"Fully Registered",IF(D13<>"","Deposit Paid",""))) | K13: Camila Engel | L13: camila.engel@example.org | M13: 555-0147 | N13: 555-0154 | O13: No | P13: x | T13: =IF(OR($J13="Fully Registered",$J13="Host Registered"),1,0) | U13: =IF($T13=0,"",IF($B13="Men",SUMIFS($T$2:$T13,$B$2:$B13,"Men"),SUMIFS($T$2:$T$40,$B$2:$B$40,"Men")+SUMIFS($T$2:$T13,$B$2:$B13,"Women")))
A14: Bayview | B14: Women | C14: x | D14: =IF($E14<>"",'Budget Dashboard'!$N$14,"") | E14: 46336 | F14: =IF($G14<>"",'Budget Dashboard'!$N$15,"") | G14: 46406 | H14: =IF(OR($D14<>"",$F14<>""),N($D14)+N($F14),"") | I14: x | J14: =IF(O14="Yes","Host Registered",IF(AND(H14<>"",H14>=$R$3),"Fully Registered",IF(D14<>"","Deposit Paid",""))) | K14: Ingrid Ziegler | L14: ingrid.ziegler@example.org | M14: 555-0161 | N14: 555-0168 | O14: No | P14: x | Q14: 🎯 SPOTS AVAILABLE | T14: =IF(OR($J14="Fully Registered",$J14="Host Registered"),1,0) | U14: =IF($T14=0,"",IF($B14="Men",SUMIFS($T$2:$T14,$B$2:$B14,"Men"),SUMIFS($T$2:$T$40,$B$2:$B$40,"Men")+SUMIFS($T$2:$T14,$B$2:$B14,"Women")))
A15: Eastbay Women HC | B15: Women | C15: x | D15: =IF($E15<>"",'Budget Dashboard'!$N$14,"") | F15: =IF($G15<>"",'Budget Dashboard'!$N$15,"") | H15: =IF(OR($D15<>"",$F15<>""),N($D15)+N($F15),"") | J15: =IF(O15="Yes","Host Registered",IF(AND(H15<>"",H15>=$R$3),"Fully Registered",IF(D15<>"","Deposit Paid",""))) | K15: Vera Zielinski | L15: vera.zielinski@example.org | M15: 555-0189 | N15: 555-0196 | O15: No | Q15: Registered Men: | R15: =COUNTIFS($J$2:$J$45,"Fully Registered",$B$2:$B$45,"Men")+COUNTIFS($J$2:$J$45,"Host Registered",$B$2:$B$45,"Men")+COUNTIFS($J$2:$J$45,"Deposit Paid",$B$2:$B$45,"Men") | T15: =IF(OR($J15="Fully Registered",$J15="Host Registered"),1,0) | U15: =IF($T15=0,"",IF($B15="Men",SUMIFS($T$2:$T15,$B$2:$B15,"Men"),SUMIFS($T$2:$T$40,$B$2:$B$40,"Men")+SUMIFS($T$2:$T15,$B$2:$B15,"Women")))
D16: =IF($E16<>"",'Budget Dashboard'!$N$14,"") | F16: =IF($G16<>"",'Budget Dashboard'!$N$15,"") | H16: =IF(OR($D16<>"",$F16<>""),N($D16)+N($F16),"") | J16: =IF(O16="Yes","Host Registered",IF(AND(H16<>"",H16>=$R$3),"Fully Registered",IF(D16<>"","Deposit Paid",""))) | Q16: Registered Women: | R16: =COUNTIFS($J$2:$J$45,"Fully Registered",$B$2:$B$45,"Women")+COUNTIFS($J$2:$J$45,"Host Registered",$B$2:$B$45,"Women")+COUNTIFS($J$2:$J$45,"Deposit Paid",$B$2:$B$45,"Women") | T16: =IF(OR($J16="Fully Registered",$J16="Host Registered"),1,0) | U16: =IF($T16=0,"",IF($B16="Men",SUMIFS($T$2:$T16,$B$2:$B16,"Men"),SUMIFS($T$2:$T$40,$B$2:$B$40,"Men")+SUMIFS($T$2:$T16,$B$2:$B16,"Women")))
D17: =IF($E17<>"",'Budget Dashboard'!$N$14,"") | F17: =IF($G17<>"",'Budget Dashboard'!$N$15,"") | H17: =IF(OR($D17<>"",$F17<>""),N($D17)+N($F17),"") | J17: =IF(O17="Yes","Host Registered",IF(AND(H17<>"",H17>=$R$3),"Fully Registered",IF(D17<>"","Deposit Paid",""))) | Q17: Open Spots (Men): | R17: =MAX(0,R5-R15) | T17: =IF(OR($J17="Fully Registered",$J17="Host Registered"),1,0) | U17: =IF($T17=0,"",IF($B17="Men",SUMIFS($T$2:$T17,$B$2:$B17,"Men"),SUMIFS($T$2:$T$40,$B$2:$B$40,"Men")+SUMIFS($T$2:$T17,$B$2:$B17,"Women")))
D18: =IF($E18<>"",'Budget Dashboard'!$N$14,"") | F18: =IF($G18<>"",'Budget Dashboard'!$N$15,"") | H18: =IF(OR($D18<>"",$F18<>""),N($D18)+N($F18),"") | J18: =IF(O18="Yes","Host Registered",IF(AND(H18<>"",H18>=$R$3),"Fully Registered",IF(D18<>"","Deposit Paid",""))) | Q18: Open Spots (Women): | R18: =MAX(0,R6-R16) | T18: =IF(OR($J18="Fully Registered",$J18="Host Registered"),1,0) | U18: =IF($T18=0,"",IF($B18="Men",SUMIFS($T$2:$T18,$B$2:$B18,"Men"),SUMIFS($T$2:$T$40,$B$2:$B$40,"Men")+SUMIFS($T$2:$T18,$B$2:$B18,"Women")))
D19: =IF($E19<>"",'Budget Dashboard'!$N$14,"") | F19: =IF($G19<>"",'Budget Dashboard'!$N$15,"") | H19: =IF(OR($D19<>"",$F19<>""),N($D19)+N($F19),"") | J19: =IF(O19="Yes","Host Registered",IF(AND(H19<>"",H19>=$R$3),"Fully Registered",IF(D19<>"","Deposit Paid",""))) | T19: =IF(OR($J19="Fully Registered",$J19="Host Registered"),1,0) | U19: =IF($T19=0,"",IF($B19="Men",SUMIFS($T$2:$T19,$B$2:$B19,"Men"),SUMIFS($T$2:$T$40,$B$2:$B$40,"Men")+SUMIFS($T$2:$T19,$B$2:$B19,"Women")))
D20: =IF($E20<>"",'Budget Dashboard'!$N$14,"") | F20: =IF($G20<>"",'Budget Dashboard'!$N$15,"") | H20: =IF(OR($D20<>"",$F20<>""),N($D20)+N($F20),"") | J20: =IF(O20="Yes","Host Registered",IF(AND(H20<>"",H20>=$R$3),"Fully Registered",IF(D20<>"","Deposit Paid",""))) | Q20: FORMAT MATCH CHECK | T20: =IF(OR($J20="Fully Registered",$J20="Host Registered"),1,0) | U20: =IF($T20=0,"",IF($B20="Men",SUMIFS($T$2:$T20,$B$2:$B20,"Men"),SUMIFS($T$2:$T$40,$B$2:$B$40,"Men")+SUMIFS($T$2:$T20,$B$2:$B20,"Women")))
D21: =IF($E21<>"",'Budget Dashboard'!$N$14,"") | F21: =IF($G21<>"",'Budget Dashboard'!$N$15,"") | H21: =IF(OR($D21<>"",$F21<>""),N($D21)+N($F21),"") | J21: =IF(O21="Yes","Host Registered",IF(AND(H21<>"",H21>=$R$3),"Fully Registered",IF(D21<>"","Deposit Paid",""))) | Q21: Men confirmed vs slots | R21: =IF($R$15=$R$5,"OK ("&$R$15&"/"&$R$5&")","MISMATCH: "&$R$15&" confirmed vs "&$R$5&" slots") | T21: =IF(OR($J21="Fully Registered",$J21="Host Registered"),1,0) | U21: =IF($T21=0,"",IF($B21="Men",SUMIFS($T$2:$T21,$B$2:$B21,"Men"),SUMIFS($T$2:$T$40,$B$2:$B$40,"Men")+SUMIFS($T$2:$T21,$B$2:$B21,"Women")))
D22: =IF($E22<>"",'Budget Dashboard'!$N$14,"") | F22: =IF($G22<>"",'Budget Dashboard'!$N$15,"") | H22: =IF(OR($D22<>"",$F22<>""),N($D22)+N($F22),"") | J22: =IF(O22="Yes","Host Registered",IF(AND(H22<>"",H22>=$R$3),"Fully Registered",IF(D22<>"","Deposit Paid",""))) | Q22: Women confirmed vs slots | R22: =IF($R$16=$R$6,"OK ("&$R$16&"/"&$R$6&")","MISMATCH: "&$R$16&" confirmed vs "&$R$6&" slots") | T22: =IF(OR($J22="Fully Registered",$J22="Host Registered"),1,0) | U22: =IF($T22=0,"",IF($B22="Men",SUMIFS($T$2:$T22,$B$2:$B22,"Men"),SUMIFS($T$2:$T$40,$B$2:$B$40,"Men")+SUMIFS($T$2:$T22,$B$2:$B22,"Women")))
D23: =IF($E23<>"",'Budget Dashboard'!$N$14,"") | F23: =IF($G23<>"",'Budget Dashboard'!$N$15,"") | H23: =IF(OR($D23<>"",$F23<>""),N($D23)+N($F23),"") | J23: =IF(O23="Yes","Host Registered",IF(AND(H23<>"",H23>=$R$3),"Fully Registered",IF(D23<>"","Deposit Paid",""))) | Q23: Roster ready? | R23: =IF(AND($R$15=$R$5,$R$16=$R$6),"YES: matches active format","NO: adjust registrations") | T23: =IF(OR($J23="Fully Registered",$J23="Host Registered"),1,0) | U23: =IF($T23=0,"",IF($B23="Men",SUMIFS($T$2:$T23,$B$2:$B23,"Men"),SUMIFS($T$2:$T$40,$B$2:$B$40,"Men")+SUMIFS($T$2:$T23,$B$2:$B23,"Women")))
D24: =IF($E24<>"",'Budget Dashboard'!$N$14,"") | F24: =IF($G24<>"",'Budget Dashboard'!$N$15,"") | H24: =IF(OR($D24<>"",$F24<>""),N($D24)+N($F24),"") | J24: =IF(O24="Yes","Host Registered",IF(AND(H24<>"",H24>=$R$3),"Fully Registered",IF(D24<>"","Deposit Paid",""))) | Q24: Not Registered | T24: =IF(OR($J24="Fully Registered",$J24="Host Registered"),1,0) | U24: =IF($T24=0,"",IF($B24="Men",SUMIFS($T$2:$T24,$B$2:$B24,"Men"),SUMIFS($T$2:$T$40,$B$2:$B$40,"Men")+SUMIFS($T$2:$T24,$B$2:$B24,"Women")))
D25: =IF($E25<>"",'Budget Dashboard'!$N$14,"") | F25: =IF($G25<>"",'Budget Dashboard'!$N$15,"") | H25: =IF(OR($D25<>"",$F25<>""),N($D25)+N($F25),"") | J25: =IF(O25="Yes","Host Registered",IF(AND(H25<>"",H25>=$R$3),"Fully Registered",IF(D25<>"","Deposit Paid",""))) | T25: =IF(OR($J25="Fully Registered",$J25="Host Registered"),1,0) | U25: =IF($T25=0,"",IF($B25="Men",SUMIFS($T$2:$T25,$B$2:$B25,"Men"),SUMIFS($T$2:$T$40,$B$2:$B$40,"Men")+SUMIFS($T$2:$T25,$B$2:$B25,"Women")))
D26: =IF($E26<>"",'Budget Dashboard'!$N$14,"") | F26: =IF($G26<>"",'Budget Dashboard'!$N$15,"") | H26: =IF(OR($D26<>"",$F26<>""),N($D26)+N($F26),"") | J26: =IF(O26="Yes","Host Registered",IF(AND(H26<>"",H26>=$R$3),"Fully Registered",IF(D26<>"","Deposit Paid",""))) | T26: =IF(OR($J26="Fully Registered",$J26="Host Registered"),1,0) | U26: =IF($T26=0,"",IF($B26="Men",SUMIFS($T$2:$T26,$B$2:$B26,"Men"),SUMIFS($T$2:$T$40,$B$2:$B$40,"Men")+SUMIFS($T$2:$T26,$B$2:$B26,"Women")))
D27: =IF($E27<>"",'Budget Dashboard'!$N$14,"") | F27: =IF($G27<>"",'Budget Dashboard'!$N$15,"") | H27: =IF(OR($D27<>"",$F27<>""),N($D27)+N($F27),"") | J27: =IF(O27="Yes","Host Registered",IF(AND(H27<>"",H27>=$R$3),"Fully Registered",IF(D27<>"","Deposit Paid",""))) | T27: =IF(OR($J27="Fully Registered",$J27="Host Registered"),1,0) | U27: =IF($T27=0,"",IF($B27="Men",SUMIFS($T$2:$T27,$B$2:$B27,"Men"),SUMIFS($T$2:$T$40,$B$2:$B$40,"Men")+SUMIFS($T$2:$T27,$B$2:$B27,"Women")))
D28: =IF($E28<>"",'Budget Dashboard'!$N$14,"") | F28: =IF($G28<>"",'Budget Dashboard'!$N$15,"") | H28: =IF(OR($D28<>"",$F28<>""),N($D28)+N($F28),"") | J28: =IF(O28="Yes","Host Registered",IF(AND(H28<>"",H28>=$R$3),"Fully Registered",IF(D28<>"","Deposit Paid",""))) | T28: =IF(OR($J28="Fully Registered",$J28="Host Registered"),1,0) | U28: =IF($T28=0,"",IF($B28="Men",SUMIFS($T$2:$T28,$B$2:$B28,"Men"),SUMIFS($T$2:$T$40,$B$2:$B$40,"Men")+SUMIFS($T$2:$T28,$B$2:$B28,"Women")))
D29: =IF($E29<>"",'Budget Dashboard'!$N$14,"") | F29: =IF($G29<>"",'Budget Dashboard'!$N$15,"") | H29: =IF(OR($D29<>"",$F29<>""),N($D29)+N($F29),"") | J29: =IF(O29="Yes","Host Registered",IF(AND(H29<>"",H29>=$R$3),"Fully Registered",IF(D29<>"","Deposit Paid",""))) | T29: =IF(OR($J29="Fully Registered",$J29="Host Registered"),1,0) | U29: =IF($T29=0,"",IF($B29="Men",SUMIFS($T$2:$T29,$B$2:$B29,"Men"),SUMIFS($T$2:$T$40,$B$2:$B$40,"Men")+SUMIFS($T$2:$T29,$B$2:$B29,"Women")))
D30: =IF($E30<>"",'Budget Dashboard'!$N$14,"") | F30: =IF($G30<>"",'Budget Dashboard'!$N$15,"") | H30: =IF(OR($D30<>"",$F30<>""),N($D30)+N($F30),"") | J30: =IF(O30="Yes","Host Registered",IF(AND(H30<>"",H30>=$R$3),"Fully Registered",IF(D30<>"","Deposit Paid",""))) | T30: =IF(OR($J30="Fully Registered",$J30="Host Registered"),1,0) | U30: =IF($T30=0,"",IF($B30="Men",SUMIFS($T$2:$T30,$B$2:$B30,"Men"),SUMIFS($T$2:$T$40,$B$2:$B$40,"Men")+SUMIFS($T$2:$T30,$B$2:$B30,"Women")))
D31: =IF($E31<>"",'Budget Dashboard'!$N$14,"") | F31: =IF($G31<>"",'Budget Dashboard'!$N$15,"") | H31: =IF(OR($D31<>"",$F31<>""),N($D31)+N($F31),"") | J31: =IF(O31="Yes","Host Registered",IF(AND(H31<>"",H31>=$R$3),"Fully Registered",IF(D31<>"","Deposit Paid",""))) | T31: =IF(OR($J31="Fully Registered",$J31="Host Registered"),1,0) | U31: =IF($T31=0,"",IF($B31="Men",SUMIFS($T$2:$T31,$B$2:$B31,"Men"),SUMIFS($T$2:$T$40,$B$2:$B$40,"Men")+SUMIFS($T$2:$T31,$B$2:$B31,"Women")))
D32: =IF($E32<>"",'Budget Dashboard'!$N$14,"") | F32: =IF($G32<>"",'Budget Dashboard'!$N$15,"") | H32: =IF(OR($D32<>"",$F32<>""),N($D32)+N($F32),"") | J32: =IF(O32="Yes","Host Registered",IF(AND(H32<>"",H32>=$R$3),"Fully Registered",IF(D32<>"","Deposit Paid",""))) | T32: =IF(OR($J32="Fully Registered",$J32="Host Registered"),1,0) | U32: =IF($T32=0,"",IF($B32="Men",SUMIFS($T$2:$T32,$B$2:$B32,"Men"),SUMIFS($T$2:$T$40,$B$2:$B$40,"Men")+SUMIFS($T$2:$T32,$B$2:$B32,"Women")))
D33: =IF($E33<>"",'Budget Dashboard'!$N$14,"") | F33: =IF($G33<>"",'Budget Dashboard'!$N$15,"") | H33: =IF(OR($D33<>"",$F33<>""),N($D33)+N($F33),"") | J33: =IF(O33="Yes","Host Registered",IF(AND(H33<>"",H33>=$R$3),"Fully Registered",IF(D33<>"","Deposit Paid",""))) | T33: =IF(OR($J33="Fully Registered",$J33="Host Registered"),1,0) | U33: =IF($T33=0,"",IF($B33="Men",SUMIFS($T$2:$T33,$B$2:$B33,"Men"),SUMIFS($T$2:$T$40,$B$2:$B$40,"Men")+SUMIFS($T$2:$T33,$B$2:$B33,"Women")))
D34: =IF($E34<>"",'Budget Dashboard'!$N$14,"") | F34: =IF($G34<>"",'Budget Dashboard'!$N$15,"") | H34: =IF(OR($D34<>"",$F34<>""),N($D34)+N($F34),"") | J34: =IF(O34="Yes","Host Registered",IF(AND(H34<>"",H34>=$R$3),"Fully Registered",IF(D34<>"","Deposit Paid",""))) | T34: =IF(OR($J34="Fully Registered",$J34="Host Registered"),1,0) | U34: =IF($T34=0,"",IF($B34="Men",SUMIFS($T$2:$T34,$B$2:$B34,"Men"),SUMIFS($T$2:$T$40,$B$2:$B$40,"Men")+SUMIFS($T$2:$T34,$B$2:$B34,"Women")))
D35: =IF($E35<>"",'Budget Dashboard'!$N$14,"") | F35: =IF($G35<>"",'Budget Dashboard'!$N$15,"") | H35: =IF(OR($D35<>"",$F35<>""),N($D35)+N($F35),"") | J35: =IF(O35="Yes","Host Registered",IF(AND(H35<>"",H35>=$R$3),"Fully Registered",IF(D35<>"","Deposit Paid",""))) | T35: =IF(OR($J35="Fully Registered",$J35="Host Registered"),1,0) | U35: =IF($T35=0,"",IF($B35="Men",SUMIFS($T$2:$T35,$B$2:$B35,"Men"),SUMIFS($T$2:$T$40,$B$2:$B$40,"Men")+SUMIFS($T$2:$T35,$B$2:$B35,"Women")))
D36: =IF($E36<>"",'Budget Dashboard'!$N$14,"") | F36: =IF($G36<>"",'Budget Dashboard'!$N$15,"") | H36: =IF(OR($D36<>"",$F36<>""),N($D36)+N($F36),"") | J36: =IF(O36="Yes","Host Registered",IF(AND(H36<>"",H36>=$R$3),"Fully Registered",IF(D36<>"","Deposit Paid",""))) | T36: =IF(OR($J36="Fully Registered",$J36="Host Registered"),1,0) | U36: =IF($T36=0,"",IF($B36="Men",SUMIFS($T$2:$T36,$B$2:$B36,"Men"),SUMIFS($T$2:$T$40,$B$2:$B$40,"Men")+SUMIFS($T$2:$T36,$B$2:$B36,"Women")))
... D38: =IF($E38<>"",'Budget Dashboard'!$N$14,"") | F38: =IF($G38<>"",'Budget Dashboard'!$N$15,"") | H38: =IF(OR($D38<>"",$F38<>""),N($D38)+N($F38),"") | J38: =IF(O38="Yes","Host Registered",IF(AND(H38<>"",H38>=$R$3),"Fully Registered",IF(D38<>"","Deposit Paid",""))) | T38: =IF(OR($J38="Fully Registered",$J38="Host Registered"),1,0) | U38: =IF($T38=0,"",IF($B38="Men",SUMIFS($T$2:$T38,$B$2:$B38,"Men"),SUMIFS($T$2:$T$40,$B$2:$B$40,"Men")+SUMIFS($T$2:$T38,$B$2:$B38,"Women")))
J39: =IF(O39="Yes","Host Registered",IF(AND(H39<>"",H39>=$R$3),"Fully Registered",IF(D39<>"","Deposit Paid",""))) | T39: =IF(OR($J39="Fully Registered",$J39="Host Registered"),1,0) | U39: =IF($T39=0,"",IF($B39="Men",SUMIFS($T$2:$T39,$B$2:$B39,"Men"),SUMIFS($T$2:$T$40,$B$2:$B$40,"Men")+SUMIFS($T$2:$T39,$B$2:$B39,"Women")))
J40: =IF(O40="Yes","Host Registered",IF(AND(H40<>"",H40>=$R$3),"Fully Registered",IF(D40<>"","Deposit Paid",""))) | T40: =IF(OR($J40="Fully Registered",$J40="Host Registered"),1,0) | U40: =IF($T40=0,"",IF($B40="Men",SUMIFS($T$2:$T40,$B$2:$B40,"Men"),SUMIFS($T$2:$T$40,$B$2:$B$40,"Men")+SUMIFS($T$2:$T40,$B$2:$B40,"Women")))
A41: Women's Teams | B41: =COUNTIFS($B$2:$B$40,"Women",$J$2:$J$40,"Fully Registered")+COUNTIFS($B$2:$B$40,"Women",$J$2:$J$40,"Host Registered") | D41: =SUMIF($B$2:$B$40,"Women",D$2:D$40) | F41: =SUMIF($B$2:$B$40,"Women",F$2:F$40) | H41: =IF(OR(D41<>"",F41<>""),D41+F41,"") | O41: No
A42: Men's Teams | B42: =COUNTIFS($B$2:$B$40,"Men",$J$2:$J$40,"Fully Registered")+COUNTIFS($B$2:$B$40,"Men",$J$2:$J$40,"Host Registered") | D42: =SUMIF($B$2:$B$40,"Men",D$2:D$40) | F42: =SUMIF($B$2:$B$40,"Men",F$2:F$40) | H42: =IF(OR(D42<>"",F42<>""),D42+F42,"") | O42: No
A44: HOW THIS TAB WORKS
A45: • One row per team: Men first, then Women. Add new teams in the first empty row of the table (through row 40).
A46: • Invitation Sent (col C): type an "x" once the invite has gone out.
A47: • Deposit Date (col E): enter the date the deposit is received; Deposit (col D) fills in automatically from the per-team deposit on Budget Dashboard (N14).
A48: • Final Pay Date (col G): enter the date the balance is received; Final Payment (col F) fills in automatically (Budget Dashboard N15) and Total (col H) updates.
A49: • Status (col J) is automatic: "Host Registered" when Host Team = Yes; "Fully Registered" once Total reaches the registration fee; "Deposit Paid" when only a deposit is in.
A50: • Host Team (col O): "Yes" only for the host club's teams (here Harbor HC and Harbor HC W); no payment required.
A51: • Capacity panel (cols T:U): registration fee and max team counts are pulled from the Inputs tab; status counts and open spots update on their own.
A52: • Short Names & Jerseys: set once per team in the Team Styles table on Teams Master (cols O:R); Teams Master looks them up by exact team name and flags any team missing from that list.
A53: • Teams Master (and the sheets built on it) picks up a team automatically once its Status is "Fully Registered" or "Host Registered" (hidden helpers in cols W:X).
A54: • Naming: clubs with a team in both divisions add a W suffix to the women's team (e.g. Redwood United / Redwood United W) so every team name is unique.
A55: • Rows 41 to 42 summarize registered teams and payments by division.
A56: • Roster Submitted (col I): mark "x" when the team sends its player roster; chase before the draw.

Sheet ----- GAME OPERATIONS -----
A1: GAME OPERATIONS

Sheet Games Schedule
B1: GAMES SCHEDULE: THE ENGINE. Dates, times, matchups, names & jerseys all calculate from Inputs + Format Engine. Never insert/delete rows or type over black/green cells.
B2: You type only: referee pairs (col P; pairs listed in the box at P34), scores (cols S:T, blue) and volunteer names (cols X:AA). Q40 should read 0 when every game has a ref pair; conflict checks are in col AB and P42. | X2: MAKE SURE YOU DON’T VOLUNTEER WHEN YOU PLAY!!
C3: DO NOT TOUCH ANYTHING BELOW THIS MESSAGE | X3: Volunteer Here | Y3: Volunteer Here
B4: Date | C4: Game # | D4: Court Time | E4: Game time | F4: Half time | G4: Second Half start | H4: End of Game max | I4: Div. | J4: Gr. | L4: Code Team A | M4: Code Team B | N4: NameTeam A | O4: NameTeam B | P4: Referees | Q4: Jersey Color Team A | R4: Jersey Color Team B | S4: Score Team A | T4: Score Team B | U4: Points Team A | V4: Points Team B | W4: Total Pts (Check) | X4: Time Keeper | Y4: Score Keeper | Z4: Merch Booth | AA4: Medical Staff | AB4: Host Ref Check
B5: =IF($C5="","",(Inputs!$C$22-('Format Engine'!$H$22-3))+IF($C5<='Format Engine'!$H$18,0,IF($C5<='Format Engine'!$H$19,1,IF($C5<='Format Engine'!$H$20,2,3)))) | C5: =IF(ROW()-4<='Format Engine'!$H$13,ROW()-4,"") | D5: {=IF($C5="","",IF(OR($C5=1,$C5='Format Engine'!$H$18+1,$C5='Format Engine'!$H$19+1,$C5='Format Engine'!$H$20+1),INDEX(Inputs!$C$26:$C$29,IF($C5<='Format Engine'!$H$18,1,IF($C5<='Format Engine'!$H$19,2,IF($C5<='Format Engine'!$H$20,3,4)))),H4+TIME(0,$C$38,0)))} | E5: =IF($C5="","",D5+TIME(0,$C$35,0)) | F5: =IF($C5="","",E5+TIME(0,$C$36/2,0)) | G5: =IF($C5="","",F5+TIME(0,$C$37,0)) | H5: =IF($C5="","",G5+TIME(0,$C$36/2,0)+TIME(0,$C$38,0)) | I5: {=IF($C5="","",INDEX(_xlfn.ANCHORARRAY('Format Engine'!$J$23),$C5,2))} | J5: {=IF($C5="","",INDEX(_xlfn.ANCHORARRAY('Format Engine'!$J$23),$C5,3))} | K5: {=IF($C5="","",IF(INDEX(_xlfn.ANCHORARRAY('Format Engine'!$J$23),$C5,6)=0,"",INDEX(_xlfn.ANCHORARRAY('Format Engine'!$J$23),$C5,6)))} | L5: {=IF($C5="","",INDEX(_xlfn.ANCHORARRAY('Format Engine'!$J$23),$C5,4))} | M5: {=IF($C5="","",INDEX(_xlfn.ANCHORARRAY('Format Engine'!$J$23),$C5,5))} | N5: =IF($C5="","",IF($J5="P",IFERROR(INDEX('Standings Engine'!$A$4:$A$16,MATCH($L5,'Standings Engine'!$J$4:$J$16,0)),"TBD"),IFERROR(INDEX('Teams Master'!$C$2:$C$14,MATCH($L5,'Teams Master'!$E$2:$E$14,0)),"TBD"))) | O5: =IF($C5="","",IF($J5="P",IFERROR(INDEX('Standings Engine'!$A$4:$A$16,MATCH($M5,'Standings Engine'!$J$4:$J$16,0)),"TBD"),IFERROR(INDEX('Teams Master'!$C$2:$C$14,MATCH($M5,'Teams Master'!$E$2:$E$14,0)),"TBD"))) | P5: Selin Ekstrom / Jasper Holm | Q5: =IF($C5="","",IFERROR(INDEX(Rankings!$E$25:$E$37,MATCH(N5,Rankings!$B$25:$B$37,0)),"TBD")) | R5: =IF($C5="","",IFERROR(IF(INDEX(Rankings!$E$25:$E$37,MATCH(O5,Rankings!$B$25:$B$37,0))=Q5,INDEX(Rankings!$F$25:$F$37,MATCH(O5,Rankings!$B$25:$B$37,0)),INDEX(Rankings!$E$25:$E$37,MATCH(O5,Rankings!$B$25:$B$37,0))),"TBD")) | S5: 27 | T5: 24 | U5: =IF($C5="","",IF(S5=0,0,IF(S5>T5,2,IF(S5=T5,1,0)))) | V5: =IF($C5="","",IF(T5=0,0,IF(U5=2,0,IF(U5=1,1,2)))) | W5: =SUM(U5:V5) | X5: Nestor Flynn | Y5: Nadia Castillo | Z5: Tobias Bianchi | AA5: Tomas Toivonen | AB5: =IF($N5="","",_xlfn.LET(_xlpm.pairCal,IFERROR(INDEX('Referees Master'!$U$4:$U$8,MATCH($P5,'Referees Master'!$T$4:$T$8,0)),""),_xlpm.isCalGame,OR(ISNUMBER(SEARCH("HAR",$N5)),ISNUMBER(SEARCH("HAR",$O5))),IF(_xlpm.pairCal="","n/a",IF(AND(_xlpm.pairCal="Yes",_xlpm.isCalGame),"⚠ CONFLICT","OK"))))
B6: =IF($C6="","",(Inputs!$C$22-('Format Engine'!$H$22-3))+IF($C6<='Format Engine'!$H$18,0,IF($C6<='Format Engine'!$H$19,1,IF($C6<='Format Engine'!$H$20,2,3)))) | C6: =IF(ROW()-4<='Format Engine'!$H$13,ROW()-4,"") | D6: {=IF($C6="","",IF(OR($C6=1,$C6='Format Engine'!$H$18+1,$C6='Format Engine'!$H$19+1,$C6='Format Engine'!$H$20+1),INDEX(Inputs!$C$26:$C$29,IF($C6<='Format Engine'!$H$18,1,IF($C6<='Format Engine'!$H$19,2,IF($C6<='Format Engine'!$H$20,3,4)))),H5+TIME(0,$C$38,0)))} | E6: =IF($C6="","",D6+TIME(0,$C$35,0)) | F6: =IF($C6="","",E6+TIME(0,$C$36/2,0)) | G6: =IF($C6="","",F6+TIME(0,$C$37,0)) | H6: =IF($C6="","",G6+TIME(0,$C$36/2,0)+TIME(0,$C$38,0)) | I6: {=IF($C6="","",INDEX(_xlfn.ANCHORARRAY('Format Engine'!$J$23),$C6,2))} | J6: {=IF($C6="","",INDEX(_xlfn.ANCHORARRAY('Format Engine'!$J$23),$C6,3))} | K6: {=IF($C6="","",IF(INDEX(_xlfn.ANCHORARRAY('Format Engine'!$J$23),$C6,6)=0,"",INDEX(_xlfn.ANCHORARRAY('Format Engine'!$J$23),$C6,6)))} | L6: {=IF($C6="","",INDEX(_xlfn.ANCHORARRAY('Format Engine'!$J$23),$C6,4))} | M6: {=IF($C6="","",INDEX(_xlfn.ANCHORARRAY('Format Engine'!$J$23),$C6,5))} | N6: =IF($C6="","",IF($J6="P",IFERROR(INDEX('Standings Engine'!$A$4:$A$16,MATCH($L6,'Standings Engine'!$J$4:$J$16,0)),"TBD"),IFERROR(INDEX('Teams Master'!$C$2:$C$14,MATCH($L6,'Teams Master'!$E$2:$E$14,0)),"TBD"))) | O6: =IF($C6="","",IF($J6="P",IFERROR(INDEX('Standings Engine'!$A$4:$A$16,MATCH($M6,'Standings Engine'!$J$4:$J$16,0)),"TBD"),IFERROR(INDEX('Teams Master'!$C$2:$C$14,MATCH($M6,'Teams Master'!$E$2:$E$14,0)),"TBD"))) | P6: Camila Duarte / Nico Moretti | Q6: =IF($C6="","",IFERROR(INDEX(Rankings!$E$25:$E$37,MATCH(N6,Rankings!$B$25:$B$37,0)),"TBD")) | R6: =IF($C6="","",IFERROR(IF(INDEX(Rankings!$E$25:$E$37,MATCH(O6,Rankings!$B$25:$B$37,0))=Q6,INDEX(Rankings!$F$25:$F$37,MATCH(O6,Rankings!$B$25:$B$37,0)),INDEX(Rankings!$E$25:$E$37,MATCH(O6,Rankings!$B$25:$B$37,0))),"TBD")) | S6: 31 | T6: 28 | U6: =IF($C6="","",IF(S6=0,0,IF(S6>T6,2,IF(S6=T6,1,0)))) | V6: =IF($C6="","",IF(T6=0,0,IF(U6=2,0,IF(U6=1,1,2)))) | W6: =SUM(U6:V6) | X6: Jasper Singh | Y6: Amir Rautio | Z6: Hugo Lowe | AA6: Tomas Toivonen | AB6: =IF($N6="","",_xlfn.LET(_xlpm.pairCal,IFERROR(INDEX('Referees Master'!$U$4:$U$8,MATCH($P6,'Referees Master'!$T$4:$T$8,0)),""),_xlpm.isCalGame,OR(ISNUMBER(SEARCH("HAR",$N6)),ISNUMBER(SEARCH("HAR",$O6))),IF(_xlpm.pairCal="","n/a",IF(AND(_xlpm.pairCal="Yes",_xlpm.isCalGame),"⚠ CONFLICT","OK"))))
B7: =IF($C7="","",(Inputs!$C$22-('Format Engine'!$H$22-3))+IF($C7<='Format Engine'!$H$18,0,IF($C7<='Format Engine'!$H$19,1,IF($C7<='Format Engine'!$H$20,2,3)))) | C7: =IF(ROW()-4<='Format Engine'!$H$13,ROW()-4,"") | D7: {=IF($C7="","",IF(OR($C7=1,$C7='Format Engine'!$H$18+1,$C7='Format Engine'!$H$19+1,$C7='Format Engine'!$H$20+1),INDEX(Inputs!$C$26:$C$29,IF($C7<='Format Engine'!$H$18,1,IF($C7<='Format Engine'!$H$19,2,IF($C7<='Format Engine'!$H$20,3,4)))),H6+TIME(0,$C$38,0)))} | E7: =IF($C7="","",D7+TIME(0,$C$35,0)) | F7: =IF($C7="","",E7+TIME(0,$C$36/2,0)) | G7: =IF($C7="","",F7+TIME(0,$C$37,0)) | H7: =IF($C7="","",G7+TIME(0,$C$36/2,0)+TIME(0,$C$38,0)) | I7: {=IF($C7="","",INDEX(_xlfn.ANCHORARRAY('Format Engine'!$J$23),$C7,2))} | J7: {=IF($C7="","",INDEX(_xlfn.ANCHORARRAY('Format Engine'!$J$23),$C7,3))} | K7: {=IF($C7="","",IF(INDEX(_xlfn.ANCHORARRAY('Format Engine'!$J$23),$C7,6)=0,"",INDEX(_xlfn.ANCHORARRAY('Format Engine'!$J$23),$C7,6)))} | L7: {=IF($C7="","",INDEX(_xlfn.ANCHORARRAY('Format Engine'!$J$23),$C7,4))} | M7: {=IF($C7="","",INDEX(_xlfn.ANCHORARRAY('Format Engine'!$J$23),$C7,5))} | N7: =IF($C7="","",IF($J7="P",IFERROR(INDEX('Standings Engine'!$A$4:$A$16,MATCH($L7,'Standings Engine'!$J$4:$J$16,0)),"TBD"),IFERROR(INDEX('Teams Master'!$C$2:$C$14,MATCH($L7,'Teams Master'!$E$2:$E$14,0)),"TBD"))) | O7: =IF($C7="","",IF($J7="P",IFERROR(INDEX('Standings Engine'!$A$4:$A$16,MATCH($M7,'Standings Engine'!$J$4:$J$16,0)),"TBD"),IFERROR(INDEX('Teams Master'!$C$2:$C$14,MATCH($M7,'Teams Master'!$E$2:$E$14,0)),"TBD"))) | P7: Leo Larsen / Silas Kaplan | Q7: =IF($C7="","",IFERROR(INDEX(Rankings!$E$25:$E$37,MATCH(N7,Rankings!$B$25:$B$37,0)),"TBD")) | R7: =IF($C7="","",IFERROR(IF(INDEX(Rankings!$E$25:$E$37,MATCH(O7,Rankings!$B$25:$B$37,0))=Q7,INDEX(Rankings!$F$25:$F$37,MATCH(O7,Rankings!$B$25:$B$37,0)),INDEX(Rankings!$E$25:$E$37,MATCH(O7,Rankings!$B$25:$B$37,0))),"TBD")) | S7: 29 | T7: 26 | U7: =IF($C7="","",IF(S7=0,0,IF(S7>T7,2,IF(S7=T7,1,0)))) | V7: =IF($C7="","",IF(T7=0,0,IF(U7=2,0,IF(U7=1,1,2)))) | W7: =SUM(U7:V7) | X7: Tobias Calloway | Y7: Ivan Almeida | Z7: Kai Varga | AA7: Tomas Toivonen | AB7: =IF($N7="","",_xlfn.LET(_xlpm.pairCal,IFERROR(INDEX('Referees Master'!$U$4:$U$8,MATCH($P7,'Referees Master'!$T$4:$T$8,0)),""),_xlpm.isCalGame,OR(ISNUMBER(SEARCH("HAR",$N7)),ISNUMBER(SEARCH("HAR",$O7))),IF(_xlpm.pairCal="","n/a",IF(AND(_xlpm.pairCal="Yes",_xlpm.isCalGame),"⚠ CONFLICT","OK"))))
B8: =IF($C8="","",(Inputs!$C$22-('Format Engine'!$H$22-3))+IF($C8<='Format Engine'!$H$18,0,IF($C8<='Format Engine'!$H$19,1,IF($C8<='Format Engine'!$H$20,2,3)))) | C8: =IF(ROW()-4<='Format Engine'!$H$13,ROW()-4,"") | D8: {=IF($C8="","",IF(OR($C8=1,$C8='Format Engine'!$H$18+1,$C8='Format Engine'!$H$19+1,$C8='Format Engine'!$H$20+1),INDEX(Inputs!$C$26:$C$29,IF($C8<='Format Engine'!$H$18,1,IF($C8<='Format Engine'!$H$19,2,IF($C8<='Format Engine'!$H$20,3,4)))),H7+TIME(0,$C$38,0)))} | E8: =IF($C8="","",D8+TIME(0,$C$35,0)) | F8: =IF($C8="","",E8+TIME(0,$C$36/2,0)) | G8: =IF($C8="","",F8+TIME(0,$C$37,0)) | H8: =IF($C8="","",G8+TIME(0,$C$36/2,0)+TIME(0,$C$38,0)) | I8: {=IF($C8="","",INDEX(_xlfn.ANCHORARRAY('Format Engine'!$J$23),$C8,2))} | J8: {=IF($C8="","",INDEX(_xlfn.ANCHORARRAY('Format Engine'!$J$23),$C8,3))} | K8: {=IF($C8="","",IF(INDEX(_xlfn.ANCHORARRAY('Format Engine'!$J$23),$C8,6)=0,"",INDEX(_xlfn.ANCHORARRAY('Format Engine'!$J$23),$C8,6)))} | L8: {=IF($C8="","",INDEX(_xlfn.ANCHORARRAY('Format Engine'!$J$23),$C8,4))} | M8: {=IF($C8="","",INDEX(_xlfn.ANCHORARRAY('Format Engine'!$J$23),$C8,5))} | N8: =IF($C8="","",IF($J8="P",IFERROR(INDEX('Standings Engine'!$A$4:$A$16,MATCH($L8,'Standings Engine'!$J$4:$J$16,0)),"TBD"),IFERROR(INDEX('Teams Master'!$C$2:$C$14,MATCH($L8,'Teams Master'!$E$2:$E$14,0)),"TBD"))) | O8: =IF($C8="","",IF($J8="P",IFERROR(INDEX('Standings Engine'!$A$4:$A$16,MATCH($M8,'Standings Engine'!$J$4:$J$16,0)),"TBD"),IFERROR(INDEX('Teams Master'!$C$2:$C$14,MATCH($M8,'Teams Master'!$E$2:$E$14,0)),"TBD"))) | P8: Liam Garza / Emeka Dahl | Q8: =IF($C8="","",IFERROR(INDEX(Rankings!$E$25:$E$37,MATCH(N8,Rankings!$B$25:$B$37,0)),"TBD")) | R8: =IF($C8="","",IFERROR(IF(INDEX(Rankings!$E$25:$E$37,MATCH(O8,Rankings!$B$25:$B$37,0))=Q8,INDEX(Rankings!$F$25:$F$37,MATCH(O8,Rankings!$B$25:$B$37,0)),INDEX(Rankings!$E$25:$E$37,MATCH(O8,Rankings!$B$25:$B$37,0))),"TBD")) | S8: 23 | T8: 25 | U8: =IF($C8="","",IF(S8=0,0,IF(S8>T8,2,IF(S8=T8,1,0)))) | V8: =IF($C8="","",IF(T8=0,0,IF(U8=2,0,IF(U8=1,1,2)))) | W8: =SUM(U8:V8) | X8: Daria Coleman | Y8: Bastian Falk | Z8: Saskia Costa | AA8: Kofi Nordin | AB8: =IF($N8="","",_xlfn.LET(_xlpm.pairCal,IFERROR(INDEX('Referees Master'!$U$4:$U$8,MATCH($P8,'Referees Master'!$T$4:$T$8,0)),""),_xlpm.isCalGame,OR(ISNUMBER(SEARCH("HAR",$N8)),ISNUMBER(SEARCH("HAR",$O8))),IF(_xlpm.pairCal="","n/a",IF(AND(_xlpm.pairCal="Yes",_xlpm.isCalGame),"⚠ CONFLICT","OK"))))
B9: =IF($C9="","",(Inputs!$C$22-('Format Engine'!$H$22-3))+IF($C9<='Format Engine'!$H$18,0,IF($C9<='Format Engine'!$H$19,1,IF($C9<='Format Engine'!$H$20,2,3)))) | C9: =IF(ROW()-4<='Format Engine'!$H$13,ROW()-4,"") | D9: {=IF($C9="","",IF(OR($C9=1,$C9='Format Engine'!$H$18+1,$C9='Format Engine'!$H$19+1,$C9='Format Engine'!$H$20+1),INDEX(Inputs!$C$26:$C$29,IF($C9<='Format Engine'!$H$18,1,IF($C9<='Format Engine'!$H$19,2,IF($C9<='Format Engine'!$H$20,3,4)))),H8+TIME(0,$C$38,0)))} | E9: =IF($C9="","",D9+TIME(0,$C$35,0)) | F9: =IF($C9="","",E9+TIME(0,$C$36/2,0)) | G9: =IF($C9="","",F9+TIME(0,$C$37,0)) | H9: =IF($C9="","",G9+TIME(0,$C$36/2,0)+TIME(0,$C$38,0)) | I9: {=IF($C9="","",INDEX(_xlfn.ANCHORARRAY('Format Engine'!$J$23),$C9,2))} | J9: {=IF($C9="","",INDEX(_xlfn.ANCHORARRAY('Format Engine'!$J$23),$C9,3))} | K9: {=IF($C9="","",IF(INDEX(_xlfn.ANCHORARRAY('Format Engine'!$J$23),$C9,6)=0,"",INDEX(_xlfn.ANCHORARRAY('Format Engine'!$J$23),$C9,6)))} | L9: {=IF($C9="","",INDEX(_xlfn.ANCHORARRAY('Format Engine'!$J$23),$C9,4))} | M9: {=IF($C9="","",INDEX(_xlfn.ANCHORARRAY('Format Engine'!$J$23),$C9,5))} | N9: =IF($C9="","",IF($J9="P",IFERROR(INDEX('Standings Engine'!$A$4:$A$16,MATCH($L9,'Standings Engine'!$J$4:$J$16,0)),"TBD"),IFERROR(INDEX('Teams Master'!$C$2:$C$14,MATCH($L9,'Teams Master'!$E$2:$E$14,0)),"TBD"))) | O9: =IF($C9="","",IF($J9="P",IFERROR(INDEX('Standings Engine'!$A$4:$A$16,MATCH($M9,'Standings Engine'!$J$4:$J$16,0)),"TBD"),IFERROR(INDEX('Teams Master'!$C$2:$C$14,MATCH($M9,'Teams Master'!$E$2:$E$14,0)),"TBD"))) | P9: Kira Engel / Erik Patel | Q9: =IF($C9="","",IFERROR(INDEX(Rankings!$E$25:$E$37,MATCH(N9,Rankings!$B$25:$B$37,0)),"TBD")) | R9: =IF($C9="","",IFERROR(IF(INDEX(Rankings!$E$25:$E$37,MATCH(O9,Rankings!$B$25:$B$37,0))=Q9,INDEX(Rankings!$F$25:$F$37,MATCH(O9,Rankings!$B$25:$B$37,0)),INDEX(Rankings!$E$25:$E$37,MATCH(O9,Rankings!$B$25:$B$37,0))),"TBD")) | S9: 33 | T9: 27 | U9: =IF($C9="","",IF(S9=0,0,IF(S9>T9,2,IF(S9=T9,1,0)))) | V9: =IF($C9="","",IF(T9=0,0,IF(U9=2,0,IF(U9=1,1,2)))) | W9: =SUM(U9:V9) | X9: Nora Bakker | Y9: Emil Madsen | Z9: Adaeze Ueda | AA9: Kofi Nordin | AB9: =IF($N9="","",_xlfn.LET(_xlpm.pairCal,IFERROR(INDEX('Referees Master'!$U$4:$U$8,MATCH($P9,'Referees Master'!$T$4:$T$8,0)),""),_xlpm.isCalGame,OR(ISNUMBER(SEARCH("HAR",$N9)),ISNUMBER(SEARCH("HAR",$O9))),IF(_xlpm.pairCal="","n/a",IF(AND(_xlpm.pairCal="Yes",_xlpm.isCalGame),"⚠ CONFLICT","OK"))))
B10: =IF($C10="","",(Inputs!$C$22-('Format Engine'!$H$22-3))+IF($C10<='Format Engine'!$H$18,0,IF($C10<='Format Engine'!$H$19,1,IF($C10<='Format Engine'!$H$20,2,3)))) | C10: =IF(ROW()-4<='Format Engine'!$H$13,ROW()-4,"") | D10: {=IF($C10="","",IF(OR($C10=1,$C10='Format Engine'!$H$18+1,$C10='Format Engine'!$H$19+1,$C10='Format Engine'!$H$20+1),INDEX(Inputs!$C$26:$C$29,IF($C10<='Format Engine'!$H$18,1,IF($C10<='Format Engine'!$H$19,2,IF($C10<='Format Engine'!$H$20,3,4)))),H9+TIME(0,$C$38,0)))} | E10: =IF($C10="","",D10+TIME(0,$C$35,0)) | F10: =IF($C10="","",E10+TIME(0,$C$36/2,0)) | G10: =IF($C10="","",F10+TIME(0,$C$37,0)) | H10: =IF($C10="","",G10+TIME(0,$C$36/2,0)+TIME(0,$C$38,0)) | I10: {=IF($C10="","",INDEX(_xlfn.ANCHORARRAY('Format Engine'!$J$23),$C10,2))} | J10: {=IF($C10="","",INDEX(_xlfn.ANCHORARRAY('Format Engine'!$J$23),$C10,3))} | K10: {=IF($C10="","",IF(INDEX(_xlfn.ANCHORARRAY('Format Engine'!$J$23),$C10,6)=0,"",INDEX(_xlfn.ANCHORARRAY('Format Engine'!$J$23),$C10,6)))} | L10: {=IF($C10="","",INDEX(_xlfn.ANCHORARRAY('Format Engine'!$J$23),$C10,4))} | M10: {=IF($C10="","",INDEX(_xlfn.ANCHORARRAY('Format Engine'!$J$23),$C10,5))} | N10: =IF($C10="","",IF($J10="P",IFERROR(INDEX('Standings Engine'!$A$4:$A$16,MATCH($L10,'Standings Engine'!$J$4:$J$16,0)),"TBD"),IFERROR(INDEX('Teams Master'!$C$2:$C$14,MATCH($L10,'Teams Master'!$E$2:$E$14,0)),"TBD"))) | O10: =IF($C10="","",IF($J10="P",IFERROR(INDEX('Standings Engine'!$A$4:$A$16,MATCH($M10,'Standings Engine'!$J$4:$J$16,0)),"TBD"),IFERROR(INDEX('Teams Master'!$C$2:$C$14,MATCH($M10,'Teams Master'!$E$2:$E$14,0)),"TBD"))) | P10: Selin Ekstrom / Jasper Holm | Q10: =IF($C10="","",IFERROR(INDEX(Rankings!$E$25:$E$37,MATCH(N10,Rankings!$B$25:$B$37,0)),"TBD")) | R10: =IF($C10="","",IFERROR(IF(INDEX(Rankings!$E$25:$E$37,MATCH(O10,Rankings!$B$25:$B$37,0))=Q10,INDEX(Rankings!$F$25:$F$37,MATCH(O10,Rankings!$B$25:$B$37,0)),INDEX(Rankings!$E$25:$E$37,MATCH(O10,Rankings!$B$25:$B$37,0))),"TBD")) | S10: 24 | T10: 30 | U10: =IF($C10="","",IF(S10=0,0,IF(S10>T10,2,IF(S10=T10,1,0)))) | V10: =IF($C10="","",IF(T10=0,0,IF(U10=2,0,IF(U10=1,1,2)))) | W10: =SUM(U10:V10) | X10: Ryan Wiklund | Y10: Cole Zhang | Z10: Nina Becker | AA10: Kofi Nordin | AB10: =IF($N10="","",_xlfn.LET(_xlpm.pairCal,IFERROR(INDEX('Referees Master'!$U$4:$U$8,MATCH($P10,'Referees Master'!$T$4:$T$8,0)),""),_xlpm.isCalGame,OR(ISNUMBER(SEARCH("HAR",$N10)),ISNUMBER(SEARCH("HAR",$O10))),IF(_xlpm.pairCal="","n/a",IF(AND(_xlpm.pairCal="Yes",_xlpm.isCalGame),"⚠ CONFLICT","OK"))))
B11: =IF($C11="","",(Inputs!$C$22-('Format Engine'!$H$22-3))+IF($C11<='Format Engine'!$H$18,0,IF($C11<='Format Engine'!$H$19,1,IF($C11<='Format Engine'!$H$20,2,3)))) | C11: =IF(ROW()-4<='Format Engine'!$H$13,ROW()-4,"") | D11: {=IF($C11="","",IF(OR($C11=1,$C11='Format Engine'!$H$18+1,$C11='Format Engine'!$H$19+1,$C11='Format Engine'!$H$20+1),INDEX(Inputs!$C$26:$C$29,IF($C11<='Format Engine'!$H$18,1,IF($C11<='Format Engine'!$H$19,2,IF($C11<='Format Engine'!$H$20,3,4)))),H10+TIME(0,$C$38,0)))} | E11: =IF($C11="","",D11+TIME(0,$C$35,0)) | F11: =IF($C11="","",E11+TIME(0,$C$36/2,0)) | G11: =IF($C11="","",F11+TIME(0,$C$37,0)) | H11: =IF($C11="","",G11+TIME(0,$C$36/2,0)+TIME(0,$C$38,0)) | I11: {=IF($C11="","",INDEX(_xlfn.ANCHORARRAY('Format Engine'!$J$23),$C11,2))} | J11: {=IF($C11="","",INDEX(_xlfn.ANCHORARRAY('Format Engine'!$J$23),$C11,3))} | K11: {=IF($C11="","",IF(INDEX(_xlfn.ANCHORARRAY('Format Engine'!$J$23),$C11,6)=0,"",INDEX(_xlfn.ANCHORARRAY('Format Engine'!$J$23),$C11,6)))} | L11: {=IF($C11="","",INDEX(_xlfn.ANCHORARRAY('Format Engine'!$J$23),$C11,4))} | M11: {=IF($C11="","",INDEX(_xlfn.ANCHORARRAY('Format Engine'!$J$23),$C11,5))} | N11: =IF($C11="","",IF($J11="P",IFERROR(INDEX('Standings Engine'!$A$4:$A$16,MATCH($L11,'Standings Engine'!$J$4:$J$16,0)),"TBD"),IFERROR(INDEX('Teams Master'!$C$2:$C$14,MATCH($L11,'Teams Master'!$E$2:$E$14,0)),"TBD"))) | O11: =IF($C11="","",IF($J11="P",IFERROR(INDEX('Standings Engine'!$A$4:$A$16,MATCH($M11,'Standings Engine'!$J$4:$J$16,0)),"TBD"),IFERROR(INDEX('Teams Master'!$C$2:$C$14,MATCH($M11,'Teams Master'!$E$2:$E$14,0)),"TBD"))) | P11: Camila Duarte / Nico Moretti | Q11: =IF($C11="","",IFERROR(INDEX(Rankings!$E$25:$E$37,MATCH(N11,Rankings!$B$25:$B$37,0)),"TBD")) | R11: =IF($C11="","",IFERROR(IF(INDEX(Rankings!$E$25:$E$37,MATCH(O11,Rankings!$B$25:$B$37,0))=Q11,INDEX(Rankings!$F$25:$F$37,MATCH(O11,Rankings!$B$25:$B$37,0)),INDEX(Rankings!$E$25:$E$37,MATCH(O11,Rankings!$B$25:$B$37,0))),"TBD")) | S11: 28 | T11: 21 | U11: =IF($C11="","",IF(S11=0,0,IF(S11>T11,2,IF(S11=T11,1,0)))) | V11: =IF($C11="","",IF(T11=0,0,IF(U11=2,0,IF(U11=1,1,2)))) | W11: =SUM(U11:V11) | X11: Amara Bergstrom | Y11: Magnus Gonzaga | Z11: Bruno Gallo | AA11: Kofi Nordin | AB11: =IF($N11="","",_xlfn.LET(_xlpm.pairCal,IFERROR(INDEX('Referees Master'!$U$4:$U$8,MATCH($P11,'Referees Master'!$T$4:$T$8,0)),""),_xlpm.isCalGame,OR(ISNUMBER(SEARCH("HAR",$N11)),ISNUMBER(SEARCH("HAR",$O11))),IF(_xlpm.pairCal="","n/a",IF(AND(_xlpm.pairCal="Yes",_xlpm.isCalGame),"⚠ CONFLICT","OK"))))
B12: =IF($C12="","",(Inputs!$C$22-('Format Engine'!$H$22-3))+IF($C12<='Format Engine'!$H$18,0,IF($C12<='Format Engine'!$H$19,1,IF($C12<='Format Engine'!$H$20,2,3)))) | C12: =IF(ROW()-4<='Format Engine'!$H$13,ROW()-4,"") | D12: {=IF($C12="","",IF(OR($C12=1,$C12='Format Engine'!$H$18+1,$C12='Format Engine'!$H$19+1,$C12='Format Engine'!$H$20+1),INDEX(Inputs!$C$26:$C$29,IF($C12<='Format Engine'!$H$18,1,IF($C12<='Format Engine'!$H$19,2,IF($C12<='Format Engine'!$H$20,3,4)))),H11+TIME(0,$C$38,0)))} | E12: =IF($C12="","",D12+TIME(0,$C$35,0)) | F12: =IF($C12="","",E12+TIME(0,$C$36/2,0)) | G12: =IF($C12="","",F12+TIME(0,$C$37,0)) | H12: =IF($C12="","",G12+TIME(0,$C$36/2,0)+TIME(0,$C$38,0)) | I12: {=IF($C12="","",INDEX(_xlfn.ANCHORARRAY('Format Engine'!$J$23),$C12,2))} | J12: {=IF($C12="","",INDEX(_xlfn.ANCHORARRAY('Format Engine'!$J$23),$C12,3))} | K12: {=IF($C12="","",IF(INDEX(_xlfn.ANCHORARRAY('Format Engine'!$J$23),$C12,6)=0,"",INDEX(_xlfn.ANCHORARRAY('Format Engine'!$J$23),$C12,6)))} | L12: {=IF($C12="","",INDEX(_xlfn.ANCHORARRAY('Format Engine'!$J$23),$C12,4))} | M12: {=IF($C12="","",INDEX(_xlfn.ANCHORARRAY('Format Engine'!$J$23),$C12,5))} | N12: =IF($C12="","",IF($J12="P",IFERROR(INDEX('Standings Engine'!$A$4:$A$16,MATCH($L12,'Standings Engine'!$J$4:$J$16,0)),"TBD"),IFERROR(INDEX('Teams Master'!$C$2:$C$14,MATCH($L12,'Teams Master'!$E$2:$E$14,0)),"TBD"))) | O12: =IF($C12="","",IF($J12="P",IFERROR(INDEX('Standings Engine'!$A$4:$A$16,MATCH($M12,'Standings Engine'!$J$4:$J$16,0)),"TBD"),IFERROR(INDEX('Teams Master'!$C$2:$C$14,MATCH($M12,'Teams Master'!$E$2:$E$14,0)),"TBD"))) | P12: Kira Engel / Erik Patel | Q12: =IF($C12="","",IFERROR(INDEX(Rankings!$E$25:$E$37,MATCH(N12,Rankings!$B$25:$B$37,0)),"TBD")) | R12: =IF($C12="","",IFERROR(IF(INDEX(Rankings!$E$25:$E$37,MATCH(O12,Rankings!$B$25:$B$37,0))=Q12,INDEX(Rankings!$F$25:$F$37,MATCH(O12,Rankings!$B$25:$B$37,0)),INDEX(Rankings!$E$25:$E$37,MATCH(O12,Rankings!$B$25:$B$37,0))),"TBD")) | S12: 27 | T12: 32 | U12: =IF($C12="","",IF(S12=0,0,IF(S12>T12,2,IF(S12=T12,1,0)))) | V12: =IF($C12="","",IF(T12=0,0,IF(U12=2,0,IF(U12=1,1,2)))) | W12: =SUM(U12:V12) | X12: Erik Marchetti | Y12: Maja Ferreira | Z12: Stefan Obi | AA12: Astrid Nyberg | AB12: =IF($N12="","",_xlfn.LET(_xlpm.pairCal,IFERROR(INDEX('Referees Master'!$U$4:$U$8,MATCH($P12,'Referees Master'!$T$4:$T$8,0)),""),_xlpm.isCalGame,OR(ISNUMBER(SEARCH("HAR",$N12)),ISNUMBER(SEARCH("HAR",$O12))),IF(_xlpm.pairCal="","n/a",IF(AND(_xlpm.pairCal="Yes",_xlpm.isCalGame),"⚠ CONFLICT","OK"))))
B13: =IF($C13="","",(Inputs!$C$22-('Format Engine'!$H$22-3))+IF($C13<='Format Engine'!$H$18,0,IF($C13<='Format Engine'!$H$19,1,IF($C13<='Format Engine'!$H$20,2,3)))) | C13: =IF(ROW()-4<='Format Engine'!$H$13,ROW()-4,"") | D13: {=IF($C13="","",IF(OR($C13=1,$C13='Format Engine'!$H$18+1,$C13='Format Engine'!$H$19+1,$C13='Format Engine'!$H$20+1),INDEX(Inputs!$C$26:$C$29,IF($C13<='Format Engine'!$H$18,1,IF($C13<='Format Engine'!$H$19,2,IF($C13<='Format Engine'!$H$20,3,4)))),H12+TIME(0,$C$38,0)))} | E13: =IF($C13="","",D13+TIME(0,$C$35,0)) | F13: =IF($C13="","",E13+TIME(0,$C$36/2,0)) | G13: =IF($C13="","",F13+TIME(0,$C$37,0)) | H13: =IF($C13="","",G13+TIME(0,$C$36/2,0)+TIME(0,$C$38,0)) | I13: {=IF($C13="","",INDEX(_xlfn.ANCHORARRAY('Format Engine'!$J$23),$C13,2))} | J13: {=IF($C13="","",INDEX(_xlfn.ANCHORARRAY('Format Engine'!$J$23),$C13,3))} | K13: {=IF($C13="","",IF(INDEX(_xlfn.ANCHORARRAY('Format Engine'!$J$23),$C13,6)=0,"",INDEX(_xlfn.ANCHORARRAY('Format Engine'!$J$23),$C13,6)))} | L13: {=IF($C13="","",INDEX(_xlfn.ANCHORARRAY('Format Engine'!$J$23),$C13,4))} | M13: {=IF($C13="","",INDEX(_xlfn.ANCHORARRAY('Format Engine'!$J$23),$C13,5))} | N13: =IF($C13="","",IF($J13="P",IFERROR(INDEX('Standings Engine'!$A$4:$A$16,MATCH($L13,'Standings Engine'!$J$4:$J$16,0)),"TBD"),IFERROR(INDEX('Teams Master'!$C$2:$C$14,MATCH($L13,'Teams Master'!$E$2:$E$14,0)),"TBD"))) | O13: =IF($C13="","",IF($J13="P",IFERROR(INDEX('Standings Engine'!$A$4:$A$16,MATCH($M13,'Standings Engine'!$J$4:$J$16,0)),"TBD"),IFERROR(INDEX('Teams Master'!$C$2:$C$14,MATCH($M13,'Teams Master'!$E$2:$E$14,0)),"TBD"))) | P13: Leo Larsen / Silas Kaplan | Q13: =IF($C13="","",IFERROR(INDEX(Rankings!$E$25:$E$37,MATCH(N13,Rankings!$B$25:$B$37,0)),"TBD")) | R13: =IF($C13="","",IFERROR(IF(INDEX(Rankings!$E$25:$E$37,MATCH(O13,Rankings!$B$25:$B$37,0))=Q13,INDEX(Rankings!$F$25:$F$37,MATCH(O13,Rankings!$B$25:$B$37,0)),INDEX(Rankings!$E$25:$E$37,MATCH(O13,Rankings!$B$25:$B$37,0))),"TBD")) | S13: 22 | T13: 29 | U13: =IF($C13="","",IF(S13=0,0,IF(S13>T13,2,IF(S13=T13,1,0)))) | V13: =IF($C13="","",IF(T13=0,0,IF(U13=2,0,IF(U13=1,1,2)))) | W13: =SUM(U13:V13) | X13: Bram Yilmaz | Y13: Kai Sorensen | Z13: Bram Zapata | AA13: Astrid Nyberg | AB13: =IF($N13="","",_xlfn.LET(_xlpm.pairCal,IFERROR(INDEX('Referees Master'!$U$4:$U$8,MATCH($P13,'Referees Master'!$T$4:$T$8,0)),""),_xlpm.isCalGame,OR(ISNUMBER(SEARCH("HAR",$N13)),ISNUMBER(SEARCH("HAR",$O13))),IF(_xlpm.pairCal="","n/a",IF(AND(_xlpm.pairCal="Yes",_xlpm.isCalGame),"⚠ CONFLICT","OK"))))
B14: =IF($C14="","",(Inputs!$C$22-('Format Engine'!$H$22-3))+IF($C14<='Format Engine'!$H$18,0,IF($C14<='Format Engine'!$H$19,1,IF($C14<='Format Engine'!$H$20,2,3)))) | C14: =IF(ROW()-4<='Format Engine'!$H$13,ROW()-4,"") | D14: {=IF($C14="","",IF(OR($C14=1,$C14='Format Engine'!$H$18+1,$C14='Format Engine'!$H$19+1,$C14='Format Engine'!$H$20+1),INDEX(Inputs!$C$26:$C$29,IF($C14<='Format Engine'!$H$18,1,IF($C14<='Format Engine'!$H$19,2,IF($C14<='Format Engine'!$H$20,3,4)))),H13+TIME(0,$C$38,0)))} | E14: =IF($C14="","",D14+TIME(0,$C$35,0)) | F14: =IF($C14="","",E14+TIME(0,$C$36/2,0)) | G14: =IF($C14="","",F14+TIME(0,$C$37,0)) | H14: =IF($C14="","",G14+TIME(0,$C$36/2,0)+TIME(0,$C$38,0)) | I14: {=IF($C14="","",INDEX(_xlfn.ANCHORARRAY('Format Engine'!$J$23),$C14,2))} | J14: {=IF($C14="","",INDEX(_xlfn.ANCHORARRAY('Format Engine'!$J$23),$C14,3))} | K14: {=IF($C14="","",IF(INDEX(_xlfn.ANCHORARRAY('Format Engine'!$J$23),$C14,6)=0,"",INDEX(_xlfn.ANCHORARRAY('Format Engine'!$J$23),$C14,6)))} | L14: {=IF($C14="","",INDEX(_xlfn.ANCHORARRAY('Format Engine'!$J$23),$C14,4))} | M14: {=IF($C14="","",INDEX(_xlfn.ANCHORARRAY('Format Engine'!$J$23),$C14,5))} | N14: =IF($C14="","",IF($J14="P",IFERROR(INDEX('Standings Engine'!$A$4:$A$16,MATCH($L14,'Standings Engine'!$J$4:$J$16,0)),"TBD"),IFERROR(INDEX('Teams Master'!$C$2:$C$14,MATCH($L14,'Teams Master'!$E$2:$E$14,0)),"TBD"))) | O14: =IF($C14="","",IF($J14="P",IFERROR(INDEX('Standings Engine'!$A$4:$A$16,MATCH($M14,'Standings Engine'!$J$4:$J$16,0)),"TBD"),IFERROR(INDEX('Teams Master'!$C$2:$C$14,MATCH($M14,'Teams Master'!$E$2:$E$14,0)),"TBD"))) | P14: Liam Garza / Emeka Dahl | Q14: =IF($C14="","",IFERROR(INDEX(Rankings!$E$25:$E$37,MATCH(N14,Rankings!$B$25:$B$37,0)),"TBD")) | R14: =IF($C14="","",IFERROR(IF(INDEX(Rankings!$E$25:$E$37,MATCH(O14,Rankings!$B$25:$B$37,0))=Q14,INDEX(Rankings!$F$25:$F$37,MATCH(O14,Rankings!$B$25:$B$37,0)),INDEX(Rankings!$E$25:$E$37,MATCH(O14,Rankings!$B$25:$B$37,0))),"TBD")) | S14: 34 | T14: 25 | U14: =IF($C14="","",IF(S14=0,0,IF(S14>T14,2,IF(S14=T14,1,0)))) | V14: =IF($C14="","",IF(T14=0,0,IF(U14=2,0,IF(U14=1,1,2)))) | W14: =SUM(U14:V14) | X14: Elif Jensen | Y14: Priya Rios | Z14: Ronja Halvorsen | AA14: Astrid Nyberg | AB14: =IF($N14="","",_xlfn.LET(_xlpm.pairCal,IFERROR(INDEX('Referees Master'!$U$4:$U$8,MATCH($P14,'Referees Master'!$T$4:$T$8,0)),""),_xlpm.isCalGame,OR(ISNUMBER(SEARCH("HAR",$N14)),ISNUMBER(SEARCH("HAR",$O14))),IF(_xlpm.pairCal="","n/a",IF(AND(_xlpm.pairCal="Yes",_xlpm.isCalGame),"⚠ CONFLICT","OK"))))
B15: =IF($C15="","",(Inputs!$C$22-('Format Engine'!$H$22-3))+IF($C15<='Format Engine'!$H$18,0,IF($C15<='Format Engine'!$H$19,1,IF($C15<='Format Engine'!$H$20,2,3)))) | C15: =IF(ROW()-4<='Format Engine'!$H$13,ROW()-4,"") | D15: {=IF($C15="","",IF(OR($C15=1,$C15='Format Engine'!$H$18+1,$C15='Format Engine'!$H$19+1,$C15='Format Engine'!$H$20+1),INDEX(Inputs!$C$26:$C$29,IF($C15<='Format Engine'!$H$18,1,IF($C15<='Format Engine'!$H$19,2,IF($C15<='Format Engine'!$H$20,3,4)))),H14+TIME(0,$C$38,0)))} | E15: =IF($C15="","",D15+TIME(0,$C$35,0)) | F15: =IF($C15="","",E15+TIME(0,$C$36/2,0)) | G15: =IF($C15="","",F15+TIME(0,$C$37,0)) | H15: =IF($C15="","",G15+TIME(0,$C$36/2,0)+TIME(0,$C$38,0)) | I15: {=IF($C15="","",INDEX(_xlfn.ANCHORARRAY('Format Engine'!$J$23),$C15,2))} | J15: {=IF($C15="","",INDEX(_xlfn.ANCHORARRAY('Format Engine'!$J$23),$C15,3))} | K15: {=IF($C15="","",IF(INDEX(_xlfn.ANCHORARRAY('Format Engine'!$J$23),$C15,6)=0,"",INDEX(_xlfn.ANCHORARRAY('Format Engine'!$J$23),$C15,6)))} | L15: {=IF($C15="","",INDEX(_xlfn.ANCHORARRAY('Format Engine'!$J$23),$C15,4))} | M15: {=IF($C15="","",INDEX(_xlfn.ANCHORARRAY('Format Engine'!$J$23),$C15,5))} | N15: =IF($C15="","",IF($J15="P",IFERROR(INDEX('Standings Engine'!$A$4:$A$16,MATCH($L15,'Standings Engine'!$J$4:$J$16,0)),"TBD"),IFERROR(INDEX('Teams Master'!$C$2:$C$14,MATCH($L15,'Teams Master'!$E$2:$E$14,0)),"TBD"))) | O15: =IF($C15="","",IF($J15="P",IFERROR(INDEX('Standings Engine'!$A$4:$A$16,MATCH($M15,'Standings Engine'!$J$4:$J$16,0)),"TBD"),IFERROR(INDEX('Teams Master'!$C$2:$C$14,MATCH($M15,'Teams Master'!$E$2:$E$14,0)),"TBD"))) | P15: Selin Ekstrom / Jasper Holm | Q15: =IF($C15="","",IFERROR(INDEX(Rankings!$E$25:$E$37,MATCH(N15,Rankings!$B$25:$B$37,0)),"TBD")) | R15: =IF($C15="","",IFERROR(IF(INDEX(Rankings!$E$25:$E$37,MATCH(O15,Rankings!$B$25:$B$37,0))=Q15,INDEX(Rankings!$F$25:$F$37,MATCH(O15,Rankings!$B$25:$B$37,0)),INDEX(Rankings!$E$25:$E$37,MATCH(O15,Rankings!$B$25:$B$37,0))),"TBD")) | S15: 25 | T15: 27 | U15: =IF($C15="","",IF(S15=0,0,IF(S15>T15,2,IF(S15=T15,1,0)))) | V15: =IF($C15="","",IF(T15=0,0,IF(U15=2,0,IF(U15=1,1,2)))) | W15: =SUM(U15:V15) | X15: Abigail Brennan | Y15: Kevin Gallagher | Z15: Rosa Cruz | AA15: Astrid Nyberg | AB15: =IF($N15="","",_xlfn.LET(_xlpm.pairCal,IFERROR(INDEX('Referees Master'!$U$4:$U$8,MATCH($P15,'Referees Master'!$T$4:$T$8,0)),""),_xlpm.isCalGame,OR(ISNUMBER(SEARCH("HAR",$N15)),ISNUMBER(SEARCH("HAR",$O15))),IF(_xlpm.pairCal="","n/a",IF(AND(_xlpm.pairCal="Yes",_xlpm.isCalGame),"⚠ CONFLICT","OK"))))
B16: =IF($C16="","",(Inputs!$C$22-('Format Engine'!$H$22-3))+IF($C16<='Format Engine'!$H$18,0,IF($C16<='Format Engine'!$H$19,1,IF($C16<='Format Engine'!$H$20,2,3)))) | C16: =IF(ROW()-4<='Format Engine'!$H$13,ROW()-4,"") | D16: {=IF($C16="","",IF(OR($C16=1,$C16='Format Engine'!$H$18+1,$C16='Format Engine'!$H$19+1,$C16='Format Engine'!$H$20+1),INDEX(Inputs!$C$26:$C$29,IF($C16<='Format Engine'!$H$18,1,IF($C16<='Format Engine'!$H$19,2,IF($C16<='Format Engine'!$H$20,3,4)))),H15+TIME(0,$C$38,0)))} | E16: =IF($C16="","",D16+TIME(0,$C$35,0)) | F16: =IF($C16="","",E16+TIME(0,$C$36/2,0)) | G16: =IF($C16="","",F16+TIME(0,$C$37,0)) | H16: =IF($C16="","",G16+TIME(0,$C$36/2,0)+TIME(0,$C$38,0)) | I16: {=IF($C16="","",INDEX(_xlfn.ANCHORARRAY('Format Engine'!$J$23),$C16,2))} | J16: {=IF($C16="","",INDEX(_xlfn.ANCHORARRAY('Format Engine'!$J$23),$C16,3))} | K16: {=IF($C16="","",IF(INDEX(_xlfn.ANCHORARRAY('Format Engine'!$J$23),$C16,6)=0,"",INDEX(_xlfn.ANCHORARRAY('Format Engine'!$J$23),$C16,6)))} | L16: {=IF($C16="","",INDEX(_xlfn.ANCHORARRAY('Format Engine'!$J$23),$C16,4))} | M16: {=IF($C16="","",INDEX(_xlfn.ANCHORARRAY('Format Engine'!$J$23),$C16,5))} | N16: =IF($C16="","",IF($J16="P",IFERROR(INDEX('Standings Engine'!$A$4:$A$16,MATCH($L16,'Standings Engine'!$J$4:$J$16,0)),"TBD"),IFERROR(INDEX('Teams Master'!$C$2:$C$14,MATCH($L16,'Teams Master'!$E$2:$E$14,0)),"TBD"))) | O16: =IF($C16="","",IF($J16="P",IFERROR(INDEX('Standings Engine'!$A$4:$A$16,MATCH($M16,'Standings Engine'!$J$4:$J$16,0)),"TBD"),IFERROR(INDEX('Teams Master'!$C$2:$C$14,MATCH($M16,'Teams Master'!$E$2:$E$14,0)),"TBD"))) | P16: Camila Duarte / Nico Moretti | Q16: =IF($C16="","",IFERROR(INDEX(Rankings!$E$25:$E$37,MATCH(N16,Rankings!$B$25:$B$37,0)),"TBD")) | R16: =IF($C16="","",IFERROR(IF(INDEX(Rankings!$E$25:$E$37,MATCH(O16,Rankings!$B$25:$B$37,0))=Q16,INDEX(Rankings!$F$25:$F$37,MATCH(O16,Rankings!$B$25:$B$37,0)),INDEX(Rankings!$E$25:$E$37,MATCH(O16,Rankings!$B$25:$B$37,0))),"TBD")) | S16: 29 | T16: 29 | U16: =IF($C16="","",IF(S16=0,0,IF(S16>T16,2,IF(S16=T16,1,0)))) | V16: =IF($C16="","",IF(T16=0,0,IF(U16=2,0,IF(U16=1,1,2)))) | W16: =SUM(U16:V16) | X16: Yara Fontaine | Y16: Greta Uribe | Z16: Victor Schmidt | AA16: Kofi Nordin | AB16: =IF($N16="","",_xlfn.LET(_xlpm.pairCal,IFERROR(INDEX('Referees Master'!$U$4:$U$8,MATCH($P16,'Referees Master'!$T$4:$T$8,0)),""),_xlpm.isCalGame,OR(ISNUMBER(SEARCH("HAR",$N16)),ISNUMBER(SEARCH("HAR",$O16))),IF(_xlpm.pairCal="","n/a",IF(AND(_xlpm.pairCal="Yes",_xlpm.isCalGame),"⚠ CONFLICT","OK"))))
B17: =IF($C17="","",(Inputs!$C$22-('Format Engine'!$H$22-3))+IF($C17<='Format Engine'!$H$18,0,IF($C17<='Format Engine'!$H$19,1,IF($C17<='Format Engine'!$H$20,2,3)))) | C17: =IF(ROW()-4<='Format Engine'!$H$13,ROW()-4,"") | D17: {=IF($C17="","",IF(OR($C17=1,$C17='Format Engine'!$H$18+1,$C17='Format Engine'!$H$19+1,$C17='Format Engine'!$H$20+1),INDEX(Inputs!$C$26:$C$29,IF($C17<='Format Engine'!$H$18,1,IF($C17<='Format Engine'!$H$19,2,IF($C17<='Format Engine'!$H$20,3,4)))),H16+TIME(0,$C$38,0)))} | E17: =IF($C17="","",D17+TIME(0,$C$35,0)) | F17: =IF($C17="","",E17+TIME(0,$C$36/2,0)) | G17: =IF($C17="","",F17+TIME(0,$C$37,0)) | H17: =IF($C17="","",G17+TIME(0,$C$36/2,0)+TIME(0,$C$38,0)) | I17: {=IF($C17="","",INDEX(_xlfn.ANCHORARRAY('Format Engine'!$J$23),$C17,2))} | J17: {=IF($C17="","",INDEX(_xlfn.ANCHORARRAY('Format Engine'!$J$23),$C17,3))} | K17: {=IF($C17="","",IF(INDEX(_xlfn.ANCHORARRAY('Format Engine'!$J$23),$C17,6)=0,"",INDEX(_xlfn.ANCHORARRAY('Format Engine'!$J$23),$C17,6)))} | L17: {=IF($C17="","",INDEX(_xlfn.ANCHORARRAY('Format Engine'!$J$23),$C17,4))} | M17: {=IF($C17="","",INDEX(_xlfn.ANCHORARRAY('Format Engine'!$J$23),$C17,5))} | N17: =IF($C17="","",IF($J17="P",IFERROR(INDEX('Standings Engine'!$A$4:$A$16,MATCH($L17,'Standings Engine'!$J$4:$J$16,0)),"TBD"),IFERROR(INDEX('Teams Master'!$C$2:$C$14,MATCH($L17,'Teams Master'!$E$2:$E$14,0)),"TBD"))) | O17: =IF($C17="","",IF($J17="P",IFERROR(INDEX('Standings Engine'!$A$4:$A$16,MATCH($M17,'Standings Engine'!$J$4:$J$16,0)),"TBD"),IFERROR(INDEX('Teams Master'!$C$2:$C$14,MATCH($M17,'Teams Master'!$E$2:$E$14,0)),"TBD"))) | P17: Leo Larsen / Silas Kaplan | Q17: =IF($C17="","",IFERROR(INDEX(Rankings!$E$25:$E$37,MATCH(N17,Rankings!$B$25:$B$37,0)),"TBD")) | R17: =IF($C17="","",IFERROR(IF(INDEX(Rankings!$E$25:$E$37,MATCH(O17,Rankings!$B$25:$B$37,0))=Q17,INDEX(Rankings!$F$25:$F$37,MATCH(O17,Rankings!$B$25:$B$37,0)),INDEX(Rankings!$E$25:$E$37,MATCH(O17,Rankings!$B$25:$B$37,0))),"TBD")) | U17: =IF($C17="","",IF(S17=0,0,IF(S17>T17,2,IF(S17=T17,1,0)))) | V17: =IF($C17="","",IF(T17=0,0,IF(U17=2,0,IF(U17=1,1,2)))) | W17: =SUM(U17:V17) | X17: Zoe Delgado | Y17: Selin Nakamura | Z17: Ronja Doyle | AA17: Kofi Nordin | AB17: =IF($N17="","",_xlfn.LET(_xlpm.pairCal,IFERROR(INDEX('Referees Master'!$U$4:$U$8,MATCH($P17,'Referees Master'!$T$4:$T$8,0)),""),_xlpm.isCalGame,OR(ISNUMBER(SEARCH("HAR",$N17)),ISNUMBER(SEARCH("HAR",$O17))),IF(_xlpm.pairCal="","n/a",IF(AND(_xlpm.pairCal="Yes",_xlpm.isCalGame),"⚠ CONFLICT","OK"))))
B18: =IF($C18="","",(Inputs!$C$22-('Format Engine'!$H$22-3))+IF($C18<='Format Engine'!$H$18,0,IF($C18<='Format Engine'!$H$19,1,IF($C18<='Format Engine'!$H$20,2,3)))) | C18: =IF(ROW()-4<='Format Engine'!$H$13,ROW()-4,"") | D18: {=IF($C18="","",IF(OR($C18=1,$C18='Format Engine'!$H$18+1,$C18='Format Engine'!$H$19+1,$C18='Format Engine'!$H$20+1),INDEX(Inputs!$C$26:$C$29,IF($C18<='Format Engine'!$H$18,1,IF($C18<='Format Engine'!$H$19,2,IF($C18<='Format Engine'!$H$20,3,4)))),H17+TIME(0,$C$38,0)))} | E18: =IF($C18="","",D18+TIME(0,$C$35,0)) | F18: =IF($C18="","",E18+TIME(0,$C$36/2,0)) | G18: =IF($C18="","",F18+TIME(0,$C$37,0)) | H18: =IF($C18="","",G18+TIME(0,$C$36/2,0)+TIME(0,$C$38,0)) | I18: {=IF($C18="","",INDEX(_xlfn.ANCHORARRAY('Format Engine'!$J$23),$C18,2))} | J18: {=IF($C18="","",INDEX(_xlfn.ANCHORARRAY('Format Engine'!$J$23),$C18,3))} | K18: {=IF($C18="","",IF(INDEX(_xlfn.ANCHORARRAY('Format Engine'!$J$23),$C18,6)=0,"",INDEX(_xlfn.ANCHORARRAY('Format Engine'!$J$23),$C18,6)))} | L18: {=IF($C18="","",INDEX(_xlfn.ANCHORARRAY('Format Engine'!$J$23),$C18,4))} | M18: {=IF($C18="","",INDEX(_xlfn.ANCHORARRAY('Format Engine'!$J$23),$C18,5))} | N18: =IF($C18="","",IF($J18="P",IFERROR(INDEX('Standings Engine'!$A$4:$A$16,MATCH($L18,'Standings Engine'!$J$4:$J$16,0)),"TBD"),IFERROR(INDEX('Teams Master'!$C$2:$C$14,MATCH($L18,'Teams Master'!$E$2:$E$14,0)),"TBD"))) | O18: =IF($C18="","",IF($J18="P",IFERROR(INDEX('Standings Engine'!$A$4:$A$16,MATCH($M18,'Standings Engine'!$J$4:$J$16,0)),"TBD"),IFERROR(INDEX('Teams Master'!$C$2:$C$14,MATCH($M18,'Teams Master'!$E$2:$E$14,0)),"TBD"))) | P18: Liam Garza / Emeka Dahl | Q18: =IF($C18="","",IFERROR(INDEX(Rankings!$E$25:$E$37,MATCH(N18,Rankings!$B$25:$B$37,0)),"TBD")) | R18: =IF($C18="","",IFERROR(IF(INDEX(Rankings!$E$25:$E$37,MATCH(O18,Rankings!$B$25:$B$37,0))=Q18,INDEX(Rankings!$F$25:$F$37,MATCH(O18,Rankings!$B$25:$B$37,0)),INDEX(Rankings!$E$25:$E$37,MATCH(O18,Rankings!$B$25:$B$37,0))),"TBD")) | U18: =IF($C18="","",IF(S18=0,0,IF(S18>T18,2,IF(S18=T18,1,0)))) | V18: =IF($C18="","",IF(T18=0,0,IF(U18=2,0,IF(U18=1,1,2)))) | W18: =SUM(U18:V18) | X18: Astrid Lambert | Y18: Gustav Brandt | Z18: Kevin Chen | AA18: Kofi Nordin | AB18: =IF($N18="","",_xlfn.LET(_xlpm.pairCal,IFERROR(INDEX('Referees Master'!$U$4:$U$8,MATCH($P18,'Referees Master'!$T$4:$T$8,0)),""),_xlpm.isCalGame,OR(ISNUMBER(SEARCH("HAR",$N18)),ISNUMBER(SEARCH("HAR",$O18))),IF(_xlpm.pairCal="","n/a",IF(AND(_xlpm.pairCal="Yes",_xlpm.isCalGame),"⚠ CONFLICT","OK"))))
B19: =IF($C19="","",(Inputs!$C$22-('Format Engine'!$H$22-3))+IF($C19<='Format Engine'!$H$18,0,IF($C19<='Format Engine'!$H$19,1,IF($C19<='Format Engine'!$H$20,2,3)))) | C19: =IF(ROW()-4<='Format Engine'!$H$13,ROW()-4,"") | D19: {=IF($C19="","",IF(OR($C19=1,$C19='Format Engine'!$H$18+1,$C19='Format Engine'!$H$19+1,$C19='Format Engine'!$H$20+1),INDEX(Inputs!$C$26:$C$29,IF($C19<='Format Engine'!$H$18,1,IF($C19<='Format Engine'!$H$19,2,IF($C19<='Format Engine'!$H$20,3,4)))),H18+TIME(0,$C$38,0)))} | E19: =IF($C19="","",D19+TIME(0,$C$35,0)) | F19: =IF($C19="","",E19+TIME(0,$C$36/2,0)) | G19: =IF($C19="","",F19+TIME(0,$C$37,0)) | H19: =IF($C19="","",G19+TIME(0,$C$36/2,0)+TIME(0,$C$38,0)) | I19: {=IF($C19="","",INDEX(_xlfn.ANCHORARRAY('Format Engine'!$J$23),$C19,2))} | J19: {=IF($C19="","",INDEX(_xlfn.ANCHORARRAY('Format Engine'!$J$23),$C19,3))} | K19: {=IF($C19="","",IF(INDEX(_xlfn.ANCHORARRAY('Format Engine'!$J$23),$C19,6)=0,"",INDEX(_xlfn.ANCHORARRAY('Format Engine'!$J$23),$C19,6)))} | L19: {=IF($C19="","",INDEX(_xlfn.ANCHORARRAY('Format Engine'!$J$23),$C19,4))} | M19: {=IF($C19="","",INDEX(_xlfn.ANCHORARRAY('Format Engine'!$J$23),$C19,5))} | N19: =IF($C19="","",IF($J19="P",IFERROR(INDEX('Standings Engine'!$A$4:$A$16,MATCH($L19,'Standings Engine'!$J$4:$J$16,0)),"TBD"),IFERROR(INDEX('Teams Master'!$C$2:$C$14,MATCH($L19,'Teams Master'!$E$2:$E$14,0)),"TBD"))) | O19: =IF($C19="","",IF($J19="P",IFERROR(INDEX('Standings Engine'!$A$4:$A$16,MATCH($M19,'Standings Engine'!$J$4:$J$16,0)),"TBD"),IFERROR(INDEX('Teams Master'!$C$2:$C$14,MATCH($M19,'Teams Master'!$E$2:$E$14,0)),"TBD"))) | P19: Kira Engel / Erik Patel | Q19: =IF($C19="","",IFERROR(INDEX(Rankings!$E$25:$E$37,MATCH(N19,Rankings!$B$25:$B$37,0)),"TBD")) | R19: =IF($C19="","",IFERROR(IF(INDEX(Rankings!$E$25:$E$37,MATCH(O19,Rankings!$B$25:$B$37,0))=Q19,INDEX(Rankings!$F$25:$F$37,MATCH(O19,Rankings!$B$25:$B$37,0)),INDEX(Rankings!$E$25:$E$37,MATCH(O19,Rankings!$B$25:$B$37,0))),"TBD")) | U19: =IF($C19="","",IF(S19=0,0,IF(S19>T19,2,IF(S19=T19,1,0)))) | V19: =IF($C19="","",IF(T19=0,0,IF(U19=2,0,IF(U19=1,1,2)))) | W19: =SUM(U19:V19) | X19: Edda Morales | Y19: Bram Cordova | Z19: Tobias Bianchi | AA19: Kofi Nordin | AB19: =IF($N19="","",_xlfn.LET(_xlpm.pairCal,IFERROR(INDEX('Referees Master'!$U$4:$U$8,MATCH($P19,'Referees Master'!$T$4:$T$8,0)),""),_xlpm.isCalGame,OR(ISNUMBER(SEARCH("HAR",$N19)),ISNUMBER(SEARCH("HAR",$O19))),IF(_xlpm.pairCal="","n/a",IF(AND(_xlpm.pairCal="Yes",_xlpm.isCalGame),"⚠ CONFLICT","OK"))))
B20: =IF($C20="","",(Inputs!$C$22-('Format Engine'!$H$22-3))+IF($C20<='Format Engine'!$H$18,0,IF($C20<='Format Engine'!$H$19,1,IF($C20<='Format Engine'!$H$20,2,3)))) | C20: =IF(ROW()-4<='Format Engine'!$H$13,ROW()-4,"") | D20: {=IF($C20="","",IF(OR($C20=1,$C20='Format Engine'!$H$18+1,$C20='Format Engine'!$H$19+1,$C20='Format Engine'!$H$20+1),INDEX(Inputs!$C$26:$C$29,IF($C20<='Format Engine'!$H$18,1,IF($C20<='Format Engine'!$H$19,2,IF($C20<='Format Engine'!$H$20,3,4)))),H19+TIME(0,$C$38,0)))} | E20: =IF($C20="","",D20+TIME(0,$C$35,0)) | F20: =IF($C20="","",E20+TIME(0,$C$36/2,0)) | G20: =IF($C20="","",F20+TIME(0,$C$37,0)) | H20: =IF($C20="","",G20+TIME(0,$C$36/2,0)+TIME(0,$C$38,0)) | I20: {=IF($C20="","",INDEX(_xlfn.ANCHORARRAY('Format Engine'!$J$23),$C20,2))} | J20: {=IF($C20="","",INDEX(_xlfn.ANCHORARRAY('Format Engine'!$J$23),$C20,3))} | K20: {=IF($C20="","",IF(INDEX(_xlfn.ANCHORARRAY('Format Engine'!$J$23),$C20,6)=0,"",INDEX(_xlfn.ANCHORARRAY('Format Engine'!$J$23),$C20,6)))} | L20: {=IF($C20="","",INDEX(_xlfn.ANCHORARRAY('Format Engine'!$J$23),$C20,4))} | M20: {=IF($C20="","",INDEX(_xlfn.ANCHORARRAY('Format Engine'!$J$23),$C20,5))} | N20: =IF($C20="","",IF($J20="P",IFERROR(INDEX('Standings Engine'!$A$4:$A$16,MATCH($L20,'Standings Engine'!$J$4:$J$16,0)),"TBD"),IFERROR(INDEX('Teams Master'!$C$2:$C$14,MATCH($L20,'Teams Master'!$E$2:$E$14,0)),"TBD"))) | O20: =IF($C20="","",IF($J20="P",IFERROR(INDEX('Standings Engine'!$A$4:$A$16,MATCH($M20,'Standings Engine'!$J$4:$J$16,0)),"TBD"),IFERROR(INDEX('Teams Master'!$C$2:$C$14,MATCH($M20,'Teams Master'!$E$2:$E$14,0)),"TBD"))) | P20: Selin Ekstrom / Jasper Holm | Q20: =IF($C20="","",IFERROR(INDEX(Rankings!$E$25:$E$37,MATCH(N20,Rankings!$B$25:$B$37,0)),"TBD")) | R20: =IF($C20="","",IFERROR(IF(INDEX(Rankings!$E$25:$E$37,MATCH(O20,Rankings!$B$25:$B$37,0))=Q20,INDEX(Rankings!$F$25:$F$37,MATCH(O20,Rankings!$B$25:$B$37,0)),INDEX(Rankings!$E$25:$E$37,MATCH(O20,Rankings!$B$25:$B$37,0))),"TBD")) | U20: =IF($C20="","",IF(S20=0,0,IF(S20>T20,2,IF(S20=T20,1,0)))) | V20: =IF($C20="","",IF(T20=0,0,IF(U20=2,0,IF(U20=1,1,2)))) | W20: =SUM(U20:V20) | X20: Nestor Flynn | Y20: Nadia Castillo | Z20: Hugo Lowe | AA20: Kira Kim | AB20: =IF($N20="","",_xlfn.LET(_xlpm.pairCal,IFERROR(INDEX('Referees Master'!$U$4:$U$8,MATCH($P20,'Referees Master'!$T$4:$T$8,0)),""),_xlpm.isCalGame,OR(ISNUMBER(SEARCH("HAR",$N20)),ISNUMBER(SEARCH("HAR",$O20))),IF(_xlpm.pairCal="","n/a",IF(AND(_xlpm.pairCal="Yes",_xlpm.isCalGame),"⚠ CONFLICT","OK"))))
B21: =IF($C21="","",(Inputs!$C$22-('Format Engine'!$H$22-3))+IF($C21<='Format Engine'!$H$18,0,IF($C21<='Format Engine'!$H$19,1,IF($C21<='Format Engine'!$H$20,2,3)))) | C21: =IF(ROW()-4<='Format Engine'!$H$13,ROW()-4,"") | D21: {=IF($C21="","",IF(OR($C21=1,$C21='Format Engine'!$H$18+1,$C21='Format Engine'!$H$19+1,$C21='Format Engine'!$H$20+1),INDEX(Inputs!$C$26:$C$29,IF($C21<='Format Engine'!$H$18,1,IF($C21<='Format Engine'!$H$19,2,IF($C21<='Format Engine'!$H$20,3,4)))),H20+TIME(0,$C$38,0)))} | E21: =IF($C21="","",D21+TIME(0,$C$35,0)) | F21: =IF($C21="","",E21+TIME(0,$C$36/2,0)) | G21: =IF($C21="","",F21+TIME(0,$C$37,0)) | H21: =IF($C21="","",G21+TIME(0,$C$36/2,0)+TIME(0,$C$38,0)) | I21: {=IF($C21="","",INDEX(_xlfn.ANCHORARRAY('Format Engine'!$J$23),$C21,2))} | J21: {=IF($C21="","",INDEX(_xlfn.ANCHORARRAY('Format Engine'!$J$23),$C21,3))} | K21: {=IF($C21="","",IF(INDEX(_xlfn.ANCHORARRAY('Format Engine'!$J$23),$C21,6)=0,"",INDEX(_xlfn.ANCHORARRAY('Format Engine'!$J$23),$C21,6)))} | L21: {=IF($C21="","",INDEX(_xlfn.ANCHORARRAY('Format Engine'!$J$23),$C21,4))} | M21: {=IF($C21="","",INDEX(_xlfn.ANCHORARRAY('Format Engine'!$J$23),$C21,5))} | N21: =IF($C21="","",IF($J21="P",IFERROR(INDEX('Standings Engine'!$A$4:$A$16,MATCH($L21,'Standings Engine'!$J$4:$J$16,0)),"TBD"),IFERROR(INDEX('Teams Master'!$C$2:$C$14,MATCH($L21,'Teams Master'!$E$2:$E$14,0)),"TBD"))) | O21: =IF($C21="","",IF($J21="P",IFERROR(INDEX('Standings Engine'!$A$4:$A$16,MATCH($M21,'Standings Engine'!$J$4:$J$16,0)),"TBD"),IFERROR(INDEX('Teams Master'!$C$2:$C$14,MATCH($M21,'Teams Master'!$E$2:$E$14,0)),"TBD"))) | P21: Camila Duarte / Nico Moretti | Q21: =IF($C21="","",IFERROR(INDEX(Rankings!$E$25:$E$37,MATCH(N21,Rankings!$B$25:$B$37,0)),"TBD")) | R21: =IF($C21="","",IFERROR(IF(INDEX(Rankings!$E$25:$E$37,MATCH(O21,Rankings!$B$25:$B$37,0))=Q21,INDEX(Rankings!$F$25:$F$37,MATCH(O21,Rankings!$B$25:$B$37,0)),INDEX(Rankings!$E$25:$E$37,MATCH(O21,Rankings!$B$25:$B$37,0))),"TBD")) | U21: =IF($C21="","",IF(S21=0,0,IF(S21>T21,2,IF(S21=T21,1,0)))) | V21: =IF($C21="","",IF(T21=0,0,IF(U21=2,0,IF(U21=1,1,2)))) | W21: =SUM(U21:V21) | X21: Jasper Singh | Y21: Amir Rautio | Z21: Kai Varga | AA21: Kira Kim | AB21: =IF($N21="","",_xlfn.LET(_xlpm.pairCal,IFERROR(INDEX('Referees Master'!$U$4:$U$8,MATCH($P21,'Referees Master'!$T$4:$T$8,0)),""),_xlpm.isCalGame,OR(ISNUMBER(SEARCH("HAR",$N21)),ISNUMBER(SEARCH("HAR",$O21))),IF(_xlpm.pairCal="","n/a",IF(AND(_xlpm.pairCal="Yes",_xlpm.isCalGame),"⚠ CONFLICT","OK"))))
B22: =IF($C22="","",(Inputs!$C$22-('Format Engine'!$H$22-3))+IF($C22<='Format Engine'!$H$18,0,IF($C22<='Format Engine'!$H$19,1,IF($C22<='Format Engine'!$H$20,2,3)))) | C22: =IF(ROW()-4<='Format Engine'!$H$13,ROW()-4,"") | D22: {=IF($C22="","",IF(OR($C22=1,$C22='Format Engine'!$H$18+1,$C22='Format Engine'!$H$19+1,$C22='Format Engine'!$H$20+1),INDEX(Inputs!$C$26:$C$29,IF($C22<='Format Engine'!$H$18,1,IF($C22<='Format Engine'!$H$19,2,IF($C22<='Format Engine'!$H$20,3,4)))),H21+TIME(0,$C$38,0)))} | E22: =IF($C22="","",D22+TIME(0,$C$35,0)) | F22: =IF($C22="","",E22+TIME(0,$C$36/2,0)) | G22: =IF($C22="","",F22+TIME(0,$C$37,0)) | H22: =IF($C22="","",G22+TIME(0,$C$36/2,0)+TIME(0,$C$38,0)) | I22: {=IF($C22="","",INDEX(_xlfn.ANCHORARRAY('Format Engine'!$J$23),$C22,2))} | J22: {=IF($C22="","",INDEX(_xlfn.ANCHORARRAY('Format Engine'!$J$23),$C22,3))} | K22: {=IF($C22="","",IF(INDEX(_xlfn.ANCHORARRAY('Format Engine'!$J$23),$C22,6)=0,"",INDEX(_xlfn.ANCHORARRAY('Format Engine'!$J$23),$C22,6)))} | L22: {=IF($C22="","",INDEX(_xlfn.ANCHORARRAY('Format Engine'!$J$23),$C22,4))} | M22: {=IF($C22="","",INDEX(_xlfn.ANCHORARRAY('Format Engine'!$J$23),$C22,5))} | N22: =IF($C22="","",IF($J22="P",IFERROR(INDEX('Standings Engine'!$A$4:$A$16,MATCH($L22,'Standings Engine'!$J$4:$J$16,0)),"TBD"),IFERROR(INDEX('Teams Master'!$C$2:$C$14,MATCH($L22,'Teams Master'!$E$2:$E$14,0)),"TBD"))) | O22: =IF($C22="","",IF($J22="P",IFERROR(INDEX('Standings Engine'!$A$4:$A$16,MATCH($M22,'Standings Engine'!$J$4:$J$16,0)),"TBD"),IFERROR(INDEX('Teams Master'!$C$2:$C$14,MATCH($M22,'Teams Master'!$E$2:$E$14,0)),"TBD"))) | P22: Leo Larsen / Silas Kaplan | Q22: =IF($C22="","",IFERROR(INDEX(Rankings!$E$25:$E$37,MATCH(N22,Rankings!$B$25:$B$37,0)),"TBD")) | R22: =IF($C22="","",IFERROR(IF(INDEX(Rankings!$E$25:$E$37,MATCH(O22,Rankings!$B$25:$B$37,0))=Q22,INDEX(Rankings!$F$25:$F$37,MATCH(O22,Rankings!$B$25:$B$37,0)),INDEX(Rankings!$E$25:$E$37,MATCH(O22,Rankings!$B$25:$B$37,0))),"TBD")) | U22: =IF($C22="","",IF(S22=0,0,IF(S22>T22,2,IF(S22=T22,1,0)))) | V22: =IF($C22="","",IF(T22=0,0,IF(U22=2,0,IF(U22=1,1,2)))) | W22: =SUM(U22:V22) | X22: Tobias Calloway | Y22: Ivan Almeida | Z22: Saskia Costa | AA22: Kira Kim | AB22: =IF($N22="","",_xlfn.LET(_xlpm.pairCal,IFERROR(INDEX('Referees Master'!$U$4:$U$8,MATCH($P22,'Referees Master'!$T$4:$T$8,0)),""),_xlpm.isCalGame,OR(ISNUMBER(SEARCH("HAR",$N22)),ISNUMBER(SEARCH("HAR",$O22))),IF(_xlpm.pairCal="","n/a",IF(AND(_xlpm.pairCal="Yes",_xlpm.isCalGame),"⚠ CONFLICT","OK"))))
B23: =IF($C23="","",(Inputs!$C$22-('Format Engine'!$H$22-3))+IF($C23<='Format Engine'!$H$18,0,IF($C23<='Format Engine'!$H$19,1,IF($C23<='Format Engine'!$H$20,2,3)))) | C23: =IF(ROW()-4<='Format Engine'!$H$13,ROW()-4,"") | D23: {=IF($C23="","",IF(OR($C23=1,$C23='Format Engine'!$H$18+1,$C23='Format Engine'!$H$19+1,$C23='Format Engine'!$H$20+1),INDEX(Inputs!$C$26:$C$29,IF($C23<='Format Engine'!$H$18,1,IF($C23<='Format Engine'!$H$19,2,IF($C23<='Format Engine'!$H$20,3,4)))),H22+TIME(0,$C$38,0)))} | E23: =IF($C23="","",D23+TIME(0,$C$35,0)) | F23: =IF($C23="","",E23+TIME(0,$C$36/2,0)) | G23: =IF($C23="","",F23+TIME(0,$C$37,0)) | H23: =IF($C23="","",G23+TIME(0,$C$36/2,0)+TIME(0,$C$38,0)) | I23: {=IF($C23="","",INDEX(_xlfn.ANCHORARRAY('Format Engine'!$J$23),$C23,2))} | J23: {=IF($C23="","",INDEX(_xlfn.ANCHORARRAY('Format Engine'!$J$23),$C23,3))} | K23: {=IF($C23="","",IF(INDEX(_xlfn.ANCHORARRAY('Format Engine'!$J$23),$C23,6)=0,"",INDEX(_xlfn.ANCHORARRAY('Format Engine'!$J$23),$C23,6)))} | L23: {=IF($C23="","",INDEX(_xlfn.ANCHORARRAY('Format Engine'!$J$23),$C23,4))} | M23: {=IF($C23="","",INDEX(_xlfn.ANCHORARRAY('Format Engine'!$J$23),$C23,5))} | N23: =IF($C23="","",IF($J23="P",IFERROR(INDEX('Standings Engine'!$A$4:$A$16,MATCH($L23,'Standings Engine'!$J$4:$J$16,0)),"TBD"),IFERROR(INDEX('Teams Master'!$C$2:$C$14,MATCH($L23,'Teams Master'!$E$2:$E$14,0)),"TBD"))) | O23: =IF($C23="","",IF($J23="P",IFERROR(INDEX('Standings Engine'!$A$4:$A$16,MATCH($M23,'Standings Engine'!$J$4:$J$16,0)),"TBD"),IFERROR(INDEX('Teams Master'!$C$2:$C$14,MATCH($M23,'Teams Master'!$E$2:$E$14,0)),"TBD"))) | P23: Kira Engel / Erik Patel | Q23: =IF($C23="","",IFERROR(INDEX(Rankings!$E$25:$E$37,MATCH(N23,Rankings!$B$25:$B$37,0)),"TBD")) | R23: =IF($C23="","",IFERROR(IF(INDEX(Rankings!$E$25:$E$37,MATCH(O23,Rankings!$B$25:$B$37,0))=Q23,INDEX(Rankings!$F$25:$F$37,MATCH(O23,Rankings!$B$25:$B$37,0)),INDEX(Rankings!$E$25:$E$37,MATCH(O23,Rankings!$B$25:$B$37,0))),"TBD")) | U23: =IF($C23="","",IF(S23=0,0,IF(S23>T23,2,IF(S23=T23,1,0)))) | V23: =IF($C23="","",IF(T23=0,0,IF(U23=2,0,IF(U23=1,1,2)))) | W23: =SUM(U23:V23) | X23: Daria Coleman | Y23: Bastian Falk | Z23: Adaeze Ueda | AA23: Kira Kim | AB23: =IF($N23="","",_xlfn.LET(_xlpm.pairCal,IFERROR(INDEX('Referees Master'!$U$4:$U$8,MATCH($P23,'Referees Master'!$T$4:$T$8,0)),""),_xlpm.isCalGame,OR(ISNUMBER(SEARCH("HAR",$N23)),ISNUMBER(SEARCH("HAR",$O23))),IF(_xlpm.pairCal="","n/a",IF(AND(_xlpm.pairCal="Yes",_xlpm.isCalGame),"⚠ CONFLICT","OK"))))
B24: =IF($C24="","",(Inputs!$C$22-('Format Engine'!$H$22-3))+IF($C24<='Format Engine'!$H$18,0,IF($C24<='Format Engine'!$H$19,1,IF($C24<='Format Engine'!$H$20,2,3)))) | C24: =IF(ROW()-4<='Format Engine'!$H$13,ROW()-4,"") | D24: {=IF($C24="","",IF(OR($C24=1,$C24='Format Engine'!$H$18+1,$C24='Format Engine'!$H$19+1,$C24='Format Engine'!$H$20+1),INDEX(Inputs!$C$26:$C$29,IF($C24<='Format Engine'!$H$18,1,IF($C24<='Format Engine'!$H$19,2,IF($C24<='Format Engine'!$H$20,3,4)))),H23+TIME(0,$C$38,0)))} | E24: =IF($C24="","",D24+TIME(0,$C$35,0)) | F24: =IF($C24="","",E24+TIME(0,$C$36/2,0)) | G24: =IF($C24="","",F24+TIME(0,$C$37,0)) | H24: =IF($C24="","",G24+TIME(0,$C$36/2,0)+TIME(0,$C$38,0)) | I24: {=IF($C24="","",INDEX(_xlfn.ANCHORARRAY('Format Engine'!$J$23),$C24,2))} | J24: {=IF($C24="","",INDEX(_xlfn.ANCHORARRAY('Format Engine'!$J$23),$C24,3))} | K24: {=IF($C24="","",IF(INDEX(_xlfn.ANCHORARRAY('Format Engine'!$J$23),$C24,6)=0,"",INDEX(_xlfn.ANCHORARRAY('Format Engine'!$J$23),$C24,6)))} | L24: {=IF($C24="","",INDEX(_xlfn.ANCHORARRAY('Format Engine'!$J$23),$C24,4))} | M24: {=IF($C24="","",INDEX(_xlfn.ANCHORARRAY('Format Engine'!$J$23),$C24,5))} | N24: =IF($C24="","",IF($J24="P",IFERROR(INDEX('Standings Engine'!$A$4:$A$16,MATCH($L24,'Standings Engine'!$J$4:$J$16,0)),"TBD"),IFERROR(INDEX('Teams Master'!$C$2:$C$14,MATCH($L24,'Teams Master'!$E$2:$E$14,0)),"TBD"))) | O24: =IF($C24="","",IF($J24="P",IFERROR(INDEX('Standings Engine'!$A$4:$A$16,MATCH($M24,'Standings Engine'!$J$4:$J$16,0)),"TBD"),IFERROR(INDEX('Teams Master'!$C$2:$C$14,MATCH($M24,'Teams Master'!$E$2:$E$14,0)),"TBD"))) | P24: Selin Ekstrom / Jasper Holm | Q24: =IF($C24="","",IFERROR(INDEX(Rankings!$E$25:$E$37,MATCH(N24,Rankings!$B$25:$B$37,0)),"TBD")) | R24: =IF($C24="","",IFERROR(IF(INDEX(Rankings!$E$25:$E$37,MATCH(O24,Rankings!$B$25:$B$37,0))=Q24,INDEX(Rankings!$F$25:$F$37,MATCH(O24,Rankings!$B$25:$B$37,0)),INDEX(Rankings!$E$25:$E$37,MATCH(O24,Rankings!$B$25:$B$37,0))),"TBD")) | U24: =IF($C24="","",IF(S24=0,0,IF(S24>T24,2,IF(S24=T24,1,0)))) | V24: =IF($C24="","",IF(T24=0,0,IF(U24=2,0,IF(U24=1,1,2)))) | W24: =SUM(U24:V24) | X24: Nora Bakker | Y24: Emil Madsen | Z24: Nina Becker | AA24: Astrid Nyberg | AB24: =IF($N24="","",_xlfn.LET(_xlpm.pairCal,IFERROR(INDEX('Referees Master'!$U$4:$U$8,MATCH($P24,'Referees Master'!$T$4:$T$8,0)),""),_xlpm.isCalGame,OR(ISNUMBER(SEARCH("HAR",$N24)),ISNUMBER(SEARCH("HAR",$O24))),IF(_xlpm.pairCal="","n/a",IF(AND(_xlpm.pairCal="Yes",_xlpm.isCalGame),"⚠ CONFLICT","OK"))))
B25: =IF($C25="","",(Inputs!$C$22-('Format Engine'!$H$22-3))+IF($C25<='Format Engine'!$H$18,0,IF($C25<='Format Engine'!$H$19,1,IF($C25<='Format Engine'!$H$20,2,3)))) | C25: =IF(ROW()-4<='Format Engine'!$H$13,ROW()-4,"") | D25: {=IF($C25="","",IF(OR($C25=1,$C25='Format Engine'!$H$18+1,$C25='Format Engine'!$H$19+1,$C25='Format Engine'!$H$20+1),INDEX(Inputs!$C$26:$C$29,IF($C25<='Format Engine'!$H$18,1,IF($C25<='Format Engine'!$H$19,2,IF($C25<='Format Engine'!$H$20,3,4)))),H24+TIME(0,$C$38,0)))} | E25: =IF($C25="","",D25+TIME(0,$C$35,0)) | F25: =IF($C25="","",E25+TIME(0,$C$36/2,0)) | G25: =IF($C25="","",F25+TIME(0,$C$37,0)) | H25: =IF($C25="","",G25+TIME(0,$C$36/2,0)+TIME(0,$C$38,0)) | I25: {=IF($C25="","",INDEX(_xlfn.ANCHORARRAY('Format Engine'!$J$23),$C25,2))} | J25: {=IF($C25="","",INDEX(_xlfn.ANCHORARRAY('Format Engine'!$J$23),$C25,3))} | K25: {=IF($C25="","",IF(INDEX(_xlfn.ANCHORARRAY('Format Engine'!$J$23),$C25,6)=0,"",INDEX(_xlfn.ANCHORARRAY('Format Engine'!$J$23),$C25,6)))} | L25: {=IF($C25="","",INDEX(_xlfn.ANCHORARRAY('Format Engine'!$J$23),$C25,4))} | M25: {=IF($C25="","",INDEX(_xlfn.ANCHORARRAY('Format Engine'!$J$23),$C25,5))} | N25: =IF($C25="","",IF($J25="P",IFERROR(INDEX('Standings Engine'!$A$4:$A$16,MATCH($L25,'Standings Engine'!$J$4:$J$16,0)),"TBD"),IFERROR(INDEX('Teams Master'!$C$2:$C$14,MATCH($L25,'Teams Master'!$E$2:$E$14,0)),"TBD"))) | O25: =IF($C25="","",IF($J25="P",IFERROR(INDEX('Standings Engine'!$A$4:$A$16,MATCH($M25,'Standings Engine'!$J$4:$J$16,0)),"TBD"),IFERROR(INDEX('Teams Master'!$C$2:$C$14,MATCH($M25,'Teams Master'!$E$2:$E$14,0)),"TBD"))) | P25: Camila Duarte / Nico Moretti | Q25: =IF($C25="","",IFERROR(INDEX(Rankings!$E$25:$E$37,MATCH(N25,Rankings!$B$25:$B$37,0)),"TBD")) | R25: =IF($C25="","",IFERROR(IF(INDEX(Rankings!$E$25:$E$37,MATCH(O25,Rankings!$B$25:$B$37,0))=Q25,INDEX(Rankings!$F$25:$F$37,MATCH(O25,Rankings!$B$25:$B$37,0)),INDEX(Rankings!$E$25:$E$37,MATCH(O25,Rankings!$B$25:$B$37,0))),"TBD")) | U25: =IF($C25="","",IF(S25=0,0,IF(S25>T25,2,IF(S25=T25,1,0)))) | V25: =IF($C25="","",IF(T25=0,0,IF(U25=2,0,IF(U25=1,1,2)))) | W25: =SUM(U25:V25) | X25: Ryan Wiklund | Y25: Cole Zhang | Z25: Bruno Gallo | AA25: Astrid Nyberg | AB25: =IF($N25="","",_xlfn.LET(_xlpm.pairCal,IFERROR(INDEX('Referees Master'!$U$4:$U$8,MATCH($P25,'Referees Master'!$T$4:$T$8,0)),""),_xlpm.isCalGame,OR(ISNUMBER(SEARCH("HAR",$N25)),ISNUMBER(SEARCH("HAR",$O25))),IF(_xlpm.pairCal="","n/a",IF(AND(_xlpm.pairCal="Yes",_xlpm.isCalGame),"⚠ CONFLICT","OK"))))
B26: =IF($C26="","",(Inputs!$C$22-('Format Engine'!$H$22-3))+IF($C26<='Format Engine'!$H$18,0,IF($C26<='Format Engine'!$H$19,1,IF($C26<='Format Engine'!$H$20,2,3)))) | C26: =IF(ROW()-4<='Format Engine'!$H$13,ROW()-4,"") | D26: {=IF($C26="","",IF(OR($C26=1,$C26='Format Engine'!$H$18+1,$C26='Format Engine'!$H$19+1,$C26='Format Engine'!$H$20+1),INDEX(Inputs!$C$26:$C$29,IF($C26<='Format Engine'!$H$18,1,IF($C26<='Format Engine'!$H$19,2,IF($C26<='Format Engine'!$H$20,3,4)))),H25+TIME(0,$C$38,0)))} | E26: =IF($C26="","",D26+TIME(0,$C$35,0)) | F26: =IF($C26="","",E26+TIME(0,$C$36/2,0)) | G26: =IF($C26="","",F26+TIME(0,$C$37,0)) | H26: =IF($C26="","",G26+TIME(0,$C$36/2,0)+TIME(0,$C$38,0)) | I26: {=IF($C26="","",INDEX(_xlfn.ANCHORARRAY('Format Engine'!$J$23),$C26,2))} | J26: {=IF($C26="","",INDEX(_xlfn.ANCHORARRAY('Format Engine'!$J$23),$C26,3))} | K26: {=IF($C26="","",IF(INDEX(_xlfn.ANCHORARRAY('Format Engine'!$J$23),$C26,6)=0,"",INDEX(_xlfn.ANCHORARRAY('Format Engine'!$J$23),$C26,6)))} | L26: {=IF($C26="","",INDEX(_xlfn.ANCHORARRAY('Format Engine'!$J$23),$C26,4))} | M26: {=IF($C26="","",INDEX(_xlfn.ANCHORARRAY('Format Engine'!$J$23),$C26,5))} | N26: =IF($C26="","",IF($J26="P",IFERROR(INDEX('Standings Engine'!$A$4:$A$16,MATCH($L26,'Standings Engine'!$J$4:$J$16,0)),"TBD"),IFERROR(INDEX('Teams Master'!$C$2:$C$14,MATCH($L26,'Teams Master'!$E$2:$E$14,0)),"TBD"))) | O26: =IF($C26="","",IF($J26="P",IFERROR(INDEX('Standings Engine'!$A$4:$A$16,MATCH($M26,'Standings Engine'!$J$4:$J$16,0)),"TBD"),IFERROR(INDEX('Teams Master'!$C$2:$C$14,MATCH($M26,'Teams Master'!$E$2:$E$14,0)),"TBD"))) | P26: Kira Engel / Erik Patel | Q26: =IF($C26="","",IFERROR(INDEX(Rankings!$E$25:$E$37,MATCH(N26,Rankings!$B$25:$B$37,0)),"TBD")) | R26: =IF($C26="","",IFERROR(IF(INDEX(Rankings!$E$25:$E$37,MATCH(O26,Rankings!$B$25:$B$37,0))=Q26,INDEX(Rankings!$F$25:$F$37,MATCH(O26,Rankings!$B$25:$B$37,0)),INDEX(Rankings!$E$25:$E$37,MATCH(O26,Rankings!$B$25:$B$37,0))),"TBD")) | U26: =IF($C26="","",IF(S26=0,0,IF(S26>T26,2,IF(S26=T26,1,0)))) | V26: =IF($C26="","",IF(T26=0,0,IF(U26=2,0,IF(U26=1,1,2)))) | W26: =SUM(U26:V26) | X26: Amara Bergstrom | Y26: Magnus Gonzaga | Z26: Stefan Obi | AA26: Astrid Nyberg | AB26: =IF($N26="","",_xlfn.LET(_xlpm.pairCal,IFERROR(INDEX('Referees Master'!$U$4:$U$8,MATCH($P26,'Referees Master'!$T$4:$T$8,0)),""),_xlpm.isCalGame,OR(ISNUMBER(SEARCH("HAR",$N26)),ISNUMBER(SEARCH("HAR",$O26))),IF(_xlpm.pairCal="","n/a",IF(AND(_xlpm.pairCal="Yes",_xlpm.isCalGame),"⚠ CONFLICT","OK"))))
B27: =IF($C27="","",(Inputs!$C$22-('Format Engine'!$H$22-3))+IF($C27<='Format Engine'!$H$18,0,IF($C27<='Format Engine'!$H$19,1,IF($C27<='Format Engine'!$H$20,2,3)))) | C27: =IF(ROW()-4<='Format Engine'!$H$13,ROW()-4,"") | D27: {=IF($C27="","",IF(OR($C27=1,$C27='Format Engine'!$H$18+1,$C27='Format Engine'!$H$19+1,$C27='Format Engine'!$H$20+1),INDEX(Inputs!$C$26:$C$29,IF($C27<='Format Engine'!$H$18,1,IF($C27<='Format Engine'!$H$19,2,IF($C27<='Format Engine'!$H$20,3,4)))),H26+TIME(0,$C$38,0)))} | E27: =IF($C27="","",D27+TIME(0,$C$35,0)) | F27: =IF($C27="","",E27+TIME(0,$C$36/2,0)) | G27: =IF($C27="","",F27+TIME(0,$C$37,0)) | H27: =IF($C27="","",G27+TIME(0,$C$36/2,0)+TIME(0,$C$38,0)) | I27: {=IF($C27="","",INDEX(_xlfn.ANCHORARRAY('Format Engine'!$J$23),$C27,2))} | J27: {=IF($C27="","",INDEX(_xlfn.ANCHORARRAY('Format Engine'!$J$23),$C27,3))} | K27: {=IF($C27="","",IF(INDEX(_xlfn.ANCHORARRAY('Format Engine'!$J$23),$C27,6)=0,"",INDEX(_xlfn.ANCHORARRAY('Format Engine'!$J$23),$C27,6)))} | L27: {=IF($C27="","",INDEX(_xlfn.ANCHORARRAY('Format Engine'!$J$23),$C27,4))} | M27: {=IF($C27="","",INDEX(_xlfn.ANCHORARRAY('Format Engine'!$J$23),$C27,5))} | N27: =IF($C27="","",IF($J27="P",IFERROR(INDEX('Standings Engine'!$A$4:$A$16,MATCH($L27,'Standings Engine'!$J$4:$J$16,0)),"TBD"),IFERROR(INDEX('Teams Master'!$C$2:$C$14,MATCH($L27,'Teams Master'!$E$2:$E$14,0)),"TBD"))) | O27: =IF($C27="","",IF($J27="P",IFERROR(INDEX('Standings Engine'!$A$4:$A$16,MATCH($M27,'Standings Engine'!$J$4:$J$16,0)),"TBD"),IFERROR(INDEX('Teams Master'!$C$2:$C$14,MATCH($M27,'Teams Master'!$E$2:$E$14,0)),"TBD"))) | P27: Selin Ekstrom / Jasper Holm | Q27: =IF($C27="","",IFERROR(INDEX(Rankings!$E$25:$E$37,MATCH(N27,Rankings!$B$25:$B$37,0)),"TBD")) | R27: =IF($C27="","",IFERROR(IF(INDEX(Rankings!$E$25:$E$37,MATCH(O27,Rankings!$B$25:$B$37,0))=Q27,INDEX(Rankings!$F$25:$F$37,MATCH(O27,Rankings!$B$25:$B$37,0)),INDEX(Rankings!$E$25:$E$37,MATCH(O27,Rankings!$B$25:$B$37,0))),"TBD")) | U27: =IF($C27="","",IF(S27=0,0,IF(S27>T27,2,IF(S27=T27,1,0)))) | V27: =IF($C27="","",IF(T27=0,0,IF(U27=2,0,IF(U27=1,1,2)))) | W27: =SUM(U27:V27) | X27: Erik Marchetti | Y27: Maja Ferreira | Z27: Bram Zapata | AA27: Astrid Nyberg | AB27: =IF($N27="","",_xlfn.LET(_xlpm.pairCal,IFERROR(INDEX('Referees Master'!$U$4:$U$8,MATCH($P27,'Referees Master'!$T$4:$T$8,0)),""),_xlpm.isCalGame,OR(ISNUMBER(SEARCH("HAR",$N27)),ISNUMBER(SEARCH("HAR",$O27))),IF(_xlpm.pairCal="","n/a",IF(AND(_xlpm.pairCal="Yes",_xlpm.isCalGame),"⚠ CONFLICT","OK"))))
B28: =IF($C28="","",(Inputs!$C$22-('Format Engine'!$H$22-3))+IF($C28<='Format Engine'!$H$18,0,IF($C28<='Format Engine'!$H$19,1,IF($C28<='Format Engine'!$H$20,2,3)))) | C28: =IF(ROW()-4<='Format Engine'!$H$13,ROW()-4,"") | D28: {=IF($C28="","",IF(OR($C28=1,$C28='Format Engine'!$H$18+1,$C28='Format Engine'!$H$19+1,$C28='Format Engine'!$H$20+1),INDEX(Inputs!$C$26:$C$29,IF($C28<='Format Engine'!$H$18,1,IF($C28<='Format Engine'!$H$19,2,IF($C28<='Format Engine'!$H$20,3,4)))),H27+TIME(0,$C$38,0)))} | E28: =IF($C28="","",D28+TIME(0,$C$35,0)) | F28: =IF($C28="","",E28+TIME(0,$C$36/2,0)) | G28: =IF($C28="","",F28+TIME(0,$C$37,0)) | H28: =IF($C28="","",G28+TIME(0,$C$36/2,0)+TIME(0,$C$38,0)) | I28: {=IF($C28="","",INDEX(_xlfn.ANCHORARRAY('Format Engine'!$J$23),$C28,2))} | J28: {=IF($C28="","",INDEX(_xlfn.ANCHORARRAY('Format Engine'!$J$23),$C28,3))} | K28: {=IF($C28="","",IF(INDEX(_xlfn.ANCHORARRAY('Format Engine'!$J$23),$C28,6)=0,"",INDEX(_xlfn.ANCHORARRAY('Format Engine'!$J$23),$C28,6)))} | L28: {=IF($C28="","",INDEX(_xlfn.ANCHORARRAY('Format Engine'!$J$23),$C28,4))} | M28: {=IF($C28="","",INDEX(_xlfn.ANCHORARRAY('Format Engine'!$J$23),$C28,5))} | N28: =IF($C28="","",IF($J28="P",IFERROR(INDEX('Standings Engine'!$A$4:$A$16,MATCH($L28,'Standings Engine'!$J$4:$J$16,0)),"TBD"),IFERROR(INDEX('Teams Master'!$C$2:$C$14,MATCH($L28,'Teams Master'!$E$2:$E$14,0)),"TBD"))) | O28: =IF($C28="","",IF($J28="P",IFERROR(INDEX('Standings Engine'!$A$4:$A$16,MATCH($M28,'Standings Engine'!$J$4:$J$16,0)),"TBD"),IFERROR(INDEX('Teams Master'!$C$2:$C$14,MATCH($M28,'Teams Master'!$E$2:$E$14,0)),"TBD"))) | P28: Camila Duarte / Nico Moretti | Q28: =IF($C28="","",IFERROR(INDEX(Rankings!$E$25:$E$37,MATCH(N28,Rankings!$B$25:$B$37,0)),"TBD")) | R28: =IF($C28="","",IFERROR(IF(INDEX(Rankings!$E$25:$E$37,MATCH(O28,Rankings!$B$25:$B$37,0))=Q28,INDEX(Rankings!$F$25:$F$37,MATCH(O28,Rankings!$B$25:$B$37,0)),INDEX(Rankings!$E$25:$E$37,MATCH(O28,Rankings!$B$25:$B$37,0))),"TBD")) | U28: =IF($C28="","",IF(S28=0,0,IF(S28>T28,2,IF(S28=T28,1,0)))) | V28: =IF($C28="","",IF(T28=0,0,IF(U28=2,0,IF(U28=1,1,2)))) | W28: =SUM(U28:V28) | X28: Bram Yilmaz | Y28: Kai Sorensen | Z28: Ronja Halvorsen | AA28: Kira Kim | AB28: =IF($N28="","",_xlfn.LET(_xlpm.pairCal,IFERROR(INDEX('Referees Master'!$U$4:$U$8,MATCH($P28,'Referees Master'!$T$4:$T$8,0)),""),_xlpm.isCalGame,OR(ISNUMBER(SEARCH("HAR",$N28)),ISNUMBER(SEARCH("HAR",$O28))),IF(_xlpm.pairCal="","n/a",IF(AND(_xlpm.pairCal="Yes",_xlpm.isCalGame),"⚠ CONFLICT","OK"))))
... B31: =IF($C31="","",(Inputs!$C$22-('Format Engine'!$H$22-3))+IF($C31<='Format Engine'!$H$18,0,IF($C31<='Format Engine'!$H$19,1,IF($C31<='Format Engine'!$H$20,2,3)))) | C31: =IF(ROW()-4<='Format Engine'!$H$13,ROW()-4,"") | D31: {=IF($C31="","",IF(OR($C31=1,$C31='Format Engine'!$H$18+1,$C31='Format Engine'!$H$19+1,$C31='Format Engine'!$H$20+1),INDEX(Inputs!$C$26:$C$29,IF($C31<='Format Engine'!$H$18,1,IF($C31<='Format Engine'!$H$19,2,IF($C31<='Format Engine'!$H$20,3,4)))),H30+TIME(0,$C$38,0)))} | E31: =IF($C31="","",D31+TIME(0,$C$35,0)) | F31: =IF($C31="","",E31+TIME(0,$C$36/2,0)) | G31: =IF($C31="","",F31+TIME(0,$C$37,0)) | H31: =IF($C31="","",G31+TIME(0,$C$36/2,0)+TIME(0,$C$38,0)) | I31: {=IF($C31="","",INDEX(_xlfn.ANCHORARRAY('Format Engine'!$J$23),$C31,2))} | J31: {=IF($C31="","",INDEX(_xlfn.ANCHORARRAY('Format Engine'!$J$23),$C31,3))} | K31: {=IF($C31="","",IF(INDEX(_xlfn.ANCHORARRAY('Format Engine'!$J$23),$C31,6)=0,"",INDEX(_xlfn.ANCHORARRAY('Format Engine'!$J$23),$C31,6)))} | L31: {=IF($C31="","",INDEX(_xlfn.ANCHORARRAY('Format Engine'!$J$23),$C31,4))} | M31: {=IF($C31="","",INDEX(_xlfn.ANCHORARRAY('Format Engine'!$J$23),$C31,5))} | N31: =IF($C31="","",IF($J31="P",IFERROR(INDEX('Standings Engine'!$A$4:$A$16,MATCH($L31,'Standings Engine'!$J$4:$J$16,0)),"TBD"),IFERROR(INDEX('Teams Master'!$C$2:$C$14,MATCH($L31,'Teams Master'!$E$2:$E$14,0)),"TBD"))) | O31: =IF($C31="","",IF($J31="P",IFERROR(INDEX('Standings Engine'!$A$4:$A$16,MATCH($M31,'Standings Engine'!$J$4:$J$16,0)),"TBD"),IFERROR(INDEX('Teams Master'!$C$2:$C$14,MATCH($M31,'Teams Master'!$E$2:$E$14,0)),"TBD"))) | P31: (assign manually) | Q31: =IF($C31="","",IFERROR(INDEX(Rankings!$E$25:$E$37,MATCH(N31,Rankings!$B$25:$B$37,0)),"TBD")) | R31: =IF($C31="","",IFERROR(IF(INDEX(Rankings!$E$25:$E$37,MATCH(O31,Rankings!$B$25:$B$37,0))=Q31,INDEX(Rankings!$F$25:$F$37,MATCH(O31,Rankings!$B$25:$B$37,0)),INDEX(Rankings!$E$25:$E$37,MATCH(O31,Rankings!$B$25:$B$37,0))),"TBD")) | U31: =IF($C31="","",IF(S31=0,0,IF(S31>T31,2,IF(S31=T31,1,0)))) | V31: =IF($C31="","",IF(T31=0,0,IF(U31=2,0,IF(U31=1,1,2)))) | W31: =SUM(U31:V31) | X31: Yara Fontaine | Y31: Greta Uribe | Z31: Ronja Doyle | AA31: Kira Kim | AB31: =IF($N31="","",_xlfn.LET(_xlpm.pairCal,IFERROR(INDEX('Referees Master'!$U$4:$U$8,MATCH($P31,'Referees Master'!$T$4:$T$8,0)),""),_xlpm.isCalGame,OR(ISNUMBER(SEARCH("HAR",$N31)),ISNUMBER(SEARCH("HAR",$O31))),IF(_xlpm.pairCal="","n/a",IF(AND(_xlpm.pairCal="Yes",_xlpm.isCalGame),"⚠ CONFLICT","OK"))))
B34: Game parameters | P34: Referee Pairs | Q34: # of games per pair
B35: Warm up | C35: =Inputs!C6 | P35: ='Referees Master'!T4 | Q35: =COUNTIF($P$5:$P$31,$P35)
B36: Actual play | C36: =Inputs!C7 | P36: ='Referees Master'!T5 | Q36: =COUNTIF($P$5:$P$31,$P36)
B37: Halftime | C37: =Inputs!C8 | P37: ='Referees Master'!T6 | Q37: =COUNTIF($P$5:$P$31,$P37)
B38: Incidents | C38: =Inputs!C9 | P38: ='Referees Master'!T7 | Q38: =COUNTIF($P$5:$P$31,$P38)
B39: Total | C39: =SUM(C35:C38) | P39: ='Referees Master'!T8 | Q39: =COUNTIF($P$5:$P$31,$P39)
Q40: =SUM(Q35:Q39)-SUM(C53:C54)
N42: URLs to share (Schedule / Live Streaming / Live updates): | P42: HOST CLUB REF CONFLICT CHECK
N43: https://example.org/schedule | P43: =IF(COUNTIF($AB$5:$AB$31,"*CONFLICT*")=0,"✓ Clear: no host club pair reffing a host club game","⚠ "&COUNTIF($AB$5:$AB$31,"*CONFLICT*")&" conflict(s): see Host Ref Check column")
N44: https://example.org/live
N45: https://example.org/social
N46: https://example.org/photos
B47: Goals Total
B48: A | C48: =SUMIF($J$5:$J$26,$B48,$S$5:$S$31)+SUMIF($J$5:$J$26,$B48,$T$5:$T$31)
B49: B | C49: =SUMIF($J$5:$J$26,$B49,$S$5:$S$31)+SUMIF($J$5:$J$26,$B49,$T$5:$T$31)
B50: W | C50: =SUMIF($J$5:$J$31,$B50,$S$5:$S$31)+SUMIF($J$5:$J$31,$B50,$T$5:$T$31)
B52: Total Games
B53: W | C53: =COUNTIF(I5:I31,B53)
B54: M | C54: =COUNTIF(I5:I31,B54)

Sheet Group Draw
A1: GROUP DRAW: Random Assignment of Registered Teams
A2: Pure random draw. Constraint: two teams from the same club cannot be in the same group (the formula flags the host club's men's teams, short names HAR and HAR2). Re-roll until satisfied, then lock (see instructions at right). The Group Codes feed Games Schedule automatically. | K2: ⚠ Before drawing: set the Tournament Format on the Control Panel AND make sure Teams Master holds exactly that format's teams (e.g. 6 men + 6 women for 6M+6W).
A4: MEN'S DRAW (8 teams → Group A & Group B) | H4: DRAW RESULT (live preview) | K4: HOW TO RUN THE DRAW
A5: Team (Short Name) | B5: Random Key | C5: Is host club? | D5: Draw Order | E5: Assigned Group | F5: Group Code | H5: Team | I5: Drawn Code | K5: 1. Press F9 to re-roll. Each press is a fresh random draw.
A6: {=IFERROR(INDEX(_xlfn._xlws.FILTER('Teams Master'!$C$2:$C$14,'Teams Master'!$D$2:$D$14="Men"),ROW()-5),"")} | B6: =IF($A6="","",RAND()) | C6: =IF($A6="","",IF(OR($A6="HAR",$A6="HAR2"),1,0)) | D6: {=IF($A6="","",SUMPRODUCT(($C$6:$C$13=$C6)*($B$6:$B$13>$B6)*($A$6:$A$13<>""))+1)} | E6: =IF($A6="","",IF($C6=1,IF($D6=1,"A","B"),IF($D6<=('Format Engine'!$H$9/2-1),"A","B"))) | F6: {=IF($A6="","",$E6&(SUMPRODUCT(($E$6:$E$13=$E6)*($B$6:$B$13>$B6)*($A$6:$A$13<>""))+1))} | H6: ='Teams Master'!C2 | I6: =IFERROR(INDEX($F$6:$F$22,MATCH($H6,$A$6:$A$22,0)),"") | K6: 2. When you're happy with the result, do it publicly/once so it's fair.
A7: {=IFERROR(INDEX(_xlfn._xlws.FILTER('Teams Master'!$C$2:$C$14,'Teams Master'!$D$2:$D$14="Men"),ROW()-5),"")} | B7: =IF($A7="","",RAND()) | C7: =IF($A7="","",IF(OR($A7="HAR",$A7="HAR2"),1,0)) | D7: {=IF($A7="","",SUMPRODUCT(($C$6:$C$13=$C7)*($B$6:$B$13>$B7)*($A$6:$A$13<>""))+1)} | E7: =IF($A7="","",IF($C7=1,IF($D7=1,"A","B"),IF($D7<=('Format Engine'!$H$9/2-1),"A","B"))) | F7: {=IF($A7="","",$E7&(SUMPRODUCT(($E$6:$E$13=$E7)*($B$6:$B$13>$B7)*($A$6:$A$13<>""))+1))} | H7: ='Teams Master'!C3 | I7: =IFERROR(INDEX($F$6:$F$22,MATCH($H7,$A$6:$A$22,0)),"") | K7: 3. Select the 'Drawn Code' column (I6:I18), Copy, then Paste-Special > Values into Teams Master column E (Group Code), matching by team.
A8: {=IFERROR(INDEX(_xlfn._xlws.FILTER('Teams Master'!$C$2:$C$14,'Teams Master'!$D$2:$D$14="Men"),ROW()-5),"")} | B8: =IF($A8="","",RAND()) | C8: =IF($A8="","",IF(OR($A8="HAR",$A8="HAR2"),1,0)) | D8: {=IF($A8="","",SUMPRODUCT(($C$6:$C$13=$C8)*($B$6:$B$13>$B8)*($A$6:$A$13<>""))+1)} | E8: =IF($A8="","",IF($C8=1,IF($D8=1,"A","B"),IF($D8<=('Format Engine'!$H$9/2-1),"A","B"))) | F8: {=IF($A8="","",$E8&(SUMPRODUCT(($E$6:$E$13=$E8)*($B$6:$B$13>$B8)*($A$6:$A$13<>""))+1))} | H8: ='Teams Master'!C4 | I8: =IFERROR(INDEX($F$6:$F$22,MATCH($H8,$A$6:$A$22,0)),"") | K8: 4. Once pasted as values into Teams Master, the codes are LOCKED and stop changing. Games Schedule then resolves team names from these codes.
A9: {=IFERROR(INDEX(_xlfn._xlws.FILTER('Teams Master'!$C$2:$C$14,'Teams Master'!$D$2:$D$14="Men"),ROW()-5),"")} | B9: =IF($A9="","",RAND()) | C9: =IF($A9="","",IF(OR($A9="HAR",$A9="HAR2"),1,0)) | D9: {=IF($A9="","",SUMPRODUCT(($C$6:$C$13=$C9)*($B$6:$B$13>$B9)*($A$6:$A$13<>""))+1)} | E9: =IF($A9="","",IF($C9=1,IF($D9=1,"A","B"),IF($D9<=('Format Engine'!$H$9/2-1),"A","B"))) | F9: {=IF($A9="","",$E9&(SUMPRODUCT(($E$6:$E$13=$E9)*($B$6:$B$13>$B9)*($A$6:$A$13<>""))+1))} | H9: ='Teams Master'!C5 | I9: =IFERROR(INDEX($F$6:$F$22,MATCH($H9,$A$6:$A$22,0)),"")
A10: {=IFERROR(INDEX(_xlfn._xlws.FILTER('Teams Master'!$C$2:$C$14,'Teams Master'!$D$2:$D$14="Men"),ROW()-5),"")} | B10: =IF($A10="","",RAND()) | C10: =IF($A10="","",IF(OR($A10="HAR",$A10="HAR2"),1,0)) | D10: {=IF($A10="","",SUMPRODUCT(($C$6:$C$13=$C10)*($B$6:$B$13>$B10)*($A$6:$A$13<>""))+1)} | E10: =IF($A10="","",IF($C10=1,IF($D10=1,"A","B"),IF($D10<=('Format Engine'!$H$9/2-1),"A","B"))) | F10: {=IF($A10="","",$E10&(SUMPRODUCT(($E$6:$E$13=$E10)*($B$6:$B$13>$B10)*($A$6:$A$13<>""))+1))} | H10: ='Teams Master'!C6 | I10: =IFERROR(INDEX($F$6:$F$22,MATCH($H10,$A$6:$A$22,0)),"") | K10: VALIDATION CHECK
A11: {=IFERROR(INDEX(_xlfn._xlws.FILTER('Teams Master'!$C$2:$C$14,'Teams Master'!$D$2:$D$14="Men"),ROW()-5),"")} | B11: =IF($A11="","",RAND()) | C11: =IF($A11="","",IF(OR($A11="HAR",$A11="HAR2"),1,0)) | D11: {=IF($A11="","",SUMPRODUCT(($C$6:$C$13=$C11)*($B$6:$B$13>$B11)*($A$6:$A$13<>""))+1)} | E11: =IF($A11="","",IF($C11=1,IF($D11=1,"A","B"),IF($D11<=('Format Engine'!$H$9/2-1),"A","B"))) | F11: {=IF($A11="","",$E11&(SUMPRODUCT(($E$6:$E$13=$E11)*($B$6:$B$13>$B11)*($A$6:$A$13<>""))+1))} | H11: ='Teams Master'!C7 | I11: =IFERROR(INDEX($F$6:$F$22,MATCH($H11,$A$6:$A$22,0)),"") | K11: Group A count: | L11: =COUNTIF($E$6:$E$13,"A") | M11: =IF(L11='Format Engine'!$H$9/2,"OK","CHECK")
A12: {=IFERROR(INDEX(_xlfn._xlws.FILTER('Teams Master'!$C$2:$C$14,'Teams Master'!$D$2:$D$14="Men"),ROW()-5),"")} | B12: =IF($A12="","",RAND()) | C12: =IF($A12="","",IF(OR($A12="HAR",$A12="HAR2"),1,0)) | D12: {=IF($A12="","",SUMPRODUCT(($C$6:$C$13=$C12)*($B$6:$B$13>$B12)*($A$6:$A$13<>""))+1)} | E12: =IF($A12="","",IF($C12=1,IF($D12=1,"A","B"),IF($D12<=('Format Engine'!$H$9/2-1),"A","B"))) | F12: {=IF($A12="","",$E12&(SUMPRODUCT(($E$6:$E$13=$E12)*($B$6:$B$13>$B12)*($A$6:$A$13<>""))+1))} | H12: ='Teams Master'!C8 | I12: =IFERROR(INDEX($F$6:$F$22,MATCH($H12,$A$6:$A$22,0)),"") | K12: Group B count: | L12: =COUNTIF($E$6:$E$13,"B") | M12: =IF(L12='Format Engine'!$H$9/2,"OK","CHECK")
A13: {=IFERROR(INDEX(_xlfn._xlws.FILTER('Teams Master'!$C$2:$C$14,'Teams Master'!$D$2:$D$14="Men"),ROW()-5),"")} | B13: =IF($A13="","",RAND()) | C13: =IF($A13="","",IF(OR($A13="HAR",$A13="HAR2"),1,0)) | D13: {=IF($A13="","",SUMPRODUCT(($C$6:$C$13=$C13)*($B$6:$B$13>$B13)*($A$6:$A$13<>""))+1)} | E13: =IF($A13="","",IF($C13=1,IF($D13=1,"A","B"),IF($D13<=('Format Engine'!$H$9/2-1),"A","B"))) | F13: {=IF($A13="","",$E13&(SUMPRODUCT(($E$6:$E$13=$E13)*($B$6:$B$13>$B13)*($A$6:$A$13<>""))+1))} | H13: ='Teams Master'!C9 | I13: =IFERROR(INDEX($F$6:$F$22,MATCH($H13,$A$6:$A$22,0)),"") | K13: Host club split OK: | L13: =IF(COUNTIFS($C$6:$C$13,1,$E$6:$E$13,"A")=1,"YES","NO: reroll") | M13: =IF(L13="YES","OK","CHECK")
H14: ='Teams Master'!C10 | I14: =IFERROR(INDEX($F$6:$F$22,MATCH($H14,$A$6:$A$22,0)),"") | K14: Unique codes: | L14: {=SUMPRODUCT(1/COUNTIF(I6:I18,I6:I18))} | M14: =IF(L14='Format Engine'!$H$8,"OK","CHECK")
A15: WOMEN'S DRAW (5 teams → Group W) | H15: ='Teams Master'!C11 | I15: =IFERROR(INDEX($F$6:$F$22,MATCH($H15,$A$6:$A$22,0)),"") | K15: Women pools OK: | L15: =IF('Format Engine'!$H$12=1,IF(COUNTIF($E$17:$E$22,"W")='Format Engine'!$H$10,"YES","NO"),IF(AND(COUNTIF($E$17:$E$22,"WA")='Format Engine'!$H$10/2,COUNTIF($E$17:$E$22,"WB")='Format Engine'!$H$10/2),"YES","NO")) | M15: =IF(L15="YES","OK","CHECK")
A16: Team (Short Name) | B16: Random Key | F16: Group Code | H16: ='Teams Master'!C12 | I16: =IFERROR(INDEX($F$6:$F$22,MATCH($H16,$A$6:$A$22,0)),"") | K16: VALID CODES (vary by format)
A17: {=IFERROR(INDEX(_xlfn._xlws.FILTER('Teams Master'!$C$2:$C$14,'Teams Master'!$D$2:$D$14="Women"),ROW()-16),"")} | B17: =IF($A17="","",RAND()) | D17: {=IF($A17="","",SUMPRODUCT(($B$17:$B$22>$B17)*($A$17:$A$22<>""))+1)} | E17: =IF($A17="","",IF('Format Engine'!$H$12=1,"W",IF($D17<=('Format Engine'!$H$10/2),"WA","WB"))) | F17: {=IF($A17="","",IF($E17="W","W"&$D17,$E17&(SUMPRODUCT(($E$17:$E$22=$E17)*($B$17:$B$22>$B17)*($A$17:$A$22<>""))+1)))} | H17: ='Teams Master'!C13 | I17: =IFERROR(INDEX($F$6:$F$22,MATCH($H17,$A$6:$A$22,0)),"") | K17: A1
A18: {=IFERROR(INDEX(_xlfn._xlws.FILTER('Teams Master'!$C$2:$C$14,'Teams Master'!$D$2:$D$14="Women"),ROW()-16),"")} | B18: =IF($A18="","",RAND()) | D18: {=IF($A18="","",SUMPRODUCT(($B$17:$B$22>$B18)*($A$17:$A$22<>""))+1)} | E18: =IF($A18="","",IF('Format Engine'!$H$12=1,"W",IF($D18<=('Format Engine'!$H$10/2),"WA","WB"))) | F18: {=IF($A18="","",IF($E18="W","W"&$D18,$E18&(SUMPRODUCT(($E$17:$E$22=$E18)*($B$17:$B$22>$B18)*($A$17:$A$22<>""))+1)))} | H18: ='Teams Master'!C14 | I18: =IFERROR(INDEX($F$6:$F$22,MATCH($H18,$A$6:$A$22,0)),"") | K18: A2
A19: {=IFERROR(INDEX(_xlfn._xlws.FILTER('Teams Master'!$C$2:$C$14,'Teams Master'!$D$2:$D$14="Women"),ROW()-16),"")} | B19: =IF($A19="","",RAND()) | D19: {=IF($A19="","",SUMPRODUCT(($B$17:$B$22>$B19)*($A$17:$A$22<>""))+1)} | E19: =IF($A19="","",IF('Format Engine'!$H$12=1,"W",IF($D19<=('Format Engine'!$H$10/2),"WA","WB"))) | F19: {=IF($A19="","",IF($E19="W","W"&$D19,$E19&(SUMPRODUCT(($E$17:$E$22=$E19)*($B$17:$B$22>$B19)*($A$17:$A$22<>""))+1)))} | K19: A3
A20: {=IFERROR(INDEX(_xlfn._xlws.FILTER('Teams Master'!$C$2:$C$14,'Teams Master'!$D$2:$D$14="Women"),ROW()-16),"")} | B20: =IF($A20="","",RAND()) | D20: {=IF($A20="","",SUMPRODUCT(($B$17:$B$22>$B20)*($A$17:$A$22<>""))+1)} | E20: =IF($A20="","",IF('Format Engine'!$H$12=1,"W",IF($D20<=('Format Engine'!$H$10/2),"WA","WB"))) | F20: {=IF($A20="","",IF($E20="W","W"&$D20,$E20&(SUMPRODUCT(($E$17:$E$22=$E20)*($B$17:$B$22>$B20)*($A$17:$A$22<>""))+1)))} | K20: A4
A21: {=IFERROR(INDEX(_xlfn._xlws.FILTER('Teams Master'!$C$2:$C$14,'Teams Master'!$D$2:$D$14="Women"),ROW()-16),"")} | B21: =IF($A21="","",RAND()) | D21: {=IF($A21="","",SUMPRODUCT(($B$17:$B$22>$B21)*($A$17:$A$22<>""))+1)} | E21: =IF($A21="","",IF('Format Engine'!$H$12=1,"W",IF($D21<=('Format Engine'!$H$10/2),"WA","WB"))) | F21: {=IF($A21="","",IF($E21="W","W"&$D21,$E21&(SUMPRODUCT(($E$17:$E$22=$E21)*($B$17:$B$22>$B21)*($A$17:$A$22<>""))+1)))} | K21: B1
A22: {=IFERROR(INDEX(_xlfn._xlws.FILTER('Teams Master'!$C$2:$C$14,'Teams Master'!$D$2:$D$14="Women"),ROW()-16),"")} | B22: =IF($A22="","",RAND()) | D22: {=IF($A22="","",SUMPRODUCT(($B$17:$B$22>$B22)*($A$17:$A$22<>""))+1)} | E22: =IF($A22="","",IF('Format Engine'!$H$12=1,"W",IF($D22<=('Format Engine'!$H$10/2),"WA","WB"))) | F22: {=IF($A22="","",IF($E22="W","W"&$D22,$E22&(SUMPRODUCT(($E$17:$E$22=$E22)*($B$17:$B$22>$B22)*($A$17:$A$22<>""))+1)))} | K22: B2
K23: B3
K24: B4
K25: W1
K26: W2
K27: W3
K28: W4
K29: W5

Sheet Printable Schedule
A1: 🏐 Bay Classic 2027: GAME SCHEDULE
A3: Date | B3: Game # | C3: Court Time | D3: Game Time | E3: Div | F3: Group | G3: Team A | H3: Team B | I3: Score | J3: Time Keeper | K3: Score Keeper
A4: ='Games Schedule'!B5 | B4: ='Games Schedule'!C5 | C4: ='Games Schedule'!D5 | D4: ='Games Schedule'!E5 | E4: ='Games Schedule'!I5 | F4: ='Games Schedule'!J5 | G4: ='Games Schedule'!N5 | H4: ='Games Schedule'!O5 | I4: =IF(OR('Games Schedule'!S5="",'Games Schedule'!T5=""),"",TEXT('Games Schedule'!S5,"0")&":"&TEXT('Games Schedule'!T5,"0")) | J4: ='Games Schedule'!X5 | K4: ='Games Schedule'!Y5
A5: ='Games Schedule'!B6 | B5: ='Games Schedule'!C6 | C5: ='Games Schedule'!D6 | D5: ='Games Schedule'!E6 | E5: ='Games Schedule'!I6 | F5: ='Games Schedule'!J6 | G5: ='Games Schedule'!N6 | H5: ='Games Schedule'!O6 | I5: =IF(OR('Games Schedule'!S6="",'Games Schedule'!T6=""),"",TEXT('Games Schedule'!S6,"0")&":"&TEXT('Games Schedule'!T6,"0")) | J5: ='Games Schedule'!X6 | K5: ='Games Schedule'!Y6
A6: ='Games Schedule'!B7 | B6: ='Games Schedule'!C7 | C6: ='Games Schedule'!D7 | D6: ='Games Schedule'!E7 | E6: ='Games Schedule'!I7 | F6: ='Games Schedule'!J7 | G6: ='Games Schedule'!N7 | H6: ='Games Schedule'!O7 | I6: =IF(OR('Games Schedule'!S7="",'Games Schedule'!T7=""),"",TEXT('Games Schedule'!S7,"0")&":"&TEXT('Games Schedule'!T7,"0")) | J6: ='Games Schedule'!X7 | K6: ='Games Schedule'!Y7
A7: ='Games Schedule'!B8 | B7: ='Games Schedule'!C8 | C7: ='Games Schedule'!D8 | D7: ='Games Schedule'!E8 | E7: ='Games Schedule'!I8 | F7: ='Games Schedule'!J8 | G7: ='Games Schedule'!N8 | H7: ='Games Schedule'!O8 | I7: =IF(OR('Games Schedule'!S8="",'Games Schedule'!T8=""),"",TEXT('Games Schedule'!S8,"0")&":"&TEXT('Games Schedule'!T8,"0")) | J7: ='Games Schedule'!X8 | K7: ='Games Schedule'!Y8
A8: ='Games Schedule'!B9 | B8: ='Games Schedule'!C9 | C8: ='Games Schedule'!D9 | D8: ='Games Schedule'!E9 | E8: ='Games Schedule'!I9 | F8: ='Games Schedule'!J9 | G8: ='Games Schedule'!N9 | H8: ='Games Schedule'!O9 | I8: =IF(OR('Games Schedule'!S9="",'Games Schedule'!T9=""),"",TEXT('Games Schedule'!S9,"0")&":"&TEXT('Games Schedule'!T9,"0")) | J8: ='Games Schedule'!X9 | K8: ='Games Schedule'!Y9
A9: ='Games Schedule'!B10 | B9: ='Games Schedule'!C10 | C9: ='Games Schedule'!D10 | D9: ='Games Schedule'!E10 | E9: ='Games Schedule'!I10 | F9: ='Games Schedule'!J10 | G9: ='Games Schedule'!N10 | H9: ='Games Schedule'!O10 | I9: =IF(OR('Games Schedule'!S10="",'Games Schedule'!T10=""),"",TEXT('Games Schedule'!S10,"0")&":"&TEXT('Games Schedule'!T10,"0")) | J9: ='Games Schedule'!X10 | K9: ='Games Schedule'!Y10
A10: ='Games Schedule'!B11 | B10: ='Games Schedule'!C11 | C10: ='Games Schedule'!D11 | D10: ='Games Schedule'!E11 | E10: ='Games Schedule'!I11 | F10: ='Games Schedule'!J11 | G10: ='Games Schedule'!N11 | H10: ='Games Schedule'!O11 | I10: =IF(OR('Games Schedule'!S11="",'Games Schedule'!T11=""),"",TEXT('Games Schedule'!S11,"0")&":"&TEXT('Games Schedule'!T11,"0")) | J10: ='Games Schedule'!X11 | K10: ='Games Schedule'!Y11
A11: ='Games Schedule'!B12 | B11: ='Games Schedule'!C12 | C11: ='Games Schedule'!D12 | D11: ='Games Schedule'!E12 | E11: ='Games Schedule'!I12 | F11: ='Games Schedule'!J12 | G11: ='Games Schedule'!N12 | H11: ='Games Schedule'!O12 | I11: =IF(OR('Games Schedule'!S12="",'Games Schedule'!T12=""),"",TEXT('Games Schedule'!S12,"0")&":"&TEXT('Games Schedule'!T12,"0")) | J11: ='Games Schedule'!X12 | K11: ='Games Schedule'!Y12
A12: ='Games Schedule'!B13 | B12: ='Games Schedule'!C13 | C12: ='Games Schedule'!D13 | D12: ='Games Schedule'!E13 | E12: ='Games Schedule'!I13 | F12: ='Games Schedule'!J13 | G12: ='Games Schedule'!N13 | H12: ='Games Schedule'!O13 | I12: =IF(OR('Games Schedule'!S13="",'Games Schedule'!T13=""),"",TEXT('Games Schedule'!S13,"0")&":"&TEXT('Games Schedule'!T13,"0")) | J12: ='Games Schedule'!X13 | K12: ='Games Schedule'!Y13
A13: ='Games Schedule'!B14 | B13: ='Games Schedule'!C14 | C13: ='Games Schedule'!D14 | D13: ='Games Schedule'!E14 | E13: ='Games Schedule'!I14 | F13: ='Games Schedule'!J14 | G13: ='Games Schedule'!N14 | H13: ='Games Schedule'!O14 | I13: =IF(OR('Games Schedule'!S14="",'Games Schedule'!T14=""),"",TEXT('Games Schedule'!S14,"0")&":"&TEXT('Games Schedule'!T14,"0")) | J13: ='Games Schedule'!X14 | K13: ='Games Schedule'!Y14
A14: ='Games Schedule'!B15 | B14: ='Games Schedule'!C15 | C14: ='Games Schedule'!D15 | D14: ='Games Schedule'!E15 | E14: ='Games Schedule'!I15 | F14: ='Games Schedule'!J15 | G14: ='Games Schedule'!N15 | H14: ='Games Schedule'!O15 | I14: =IF(OR('Games Schedule'!S15="",'Games Schedule'!T15=""),"",TEXT('Games Schedule'!S15,"0")&":"&TEXT('Games Schedule'!T15,"0")) | J14: ='Games Schedule'!X15 | K14: ='Games Schedule'!Y15
A15: ='Games Schedule'!B16 | B15: ='Games Schedule'!C16 | C15: ='Games Schedule'!D16 | D15: ='Games Schedule'!E16 | E15: ='Games Schedule'!I16 | F15: ='Games Schedule'!J16 | G15: ='Games Schedule'!N16 | H15: ='Games Schedule'!O16 | I15: =IF(OR('Games Schedule'!S16="",'Games Schedule'!T16=""),"",TEXT('Games Schedule'!S16,"0")&":"&TEXT('Games Schedule'!T16,"0")) | J15: ='Games Schedule'!X16 | K15: ='Games Schedule'!Y16
... A30: ='Games Schedule'!B31 | B30: ='Games Schedule'!C31 | C30: ='Games Schedule'!D31 | D30: ='Games Schedule'!E31 | E30: ='Games Schedule'!I31 | F30: ='Games Schedule'!J31 | G30: ='Games Schedule'!N31 | H30: ='Games Schedule'!O31 | I30: =IF(OR('Games Schedule'!S31="",'Games Schedule'!T31=""),"",TEXT('Games Schedule'!S31,"0")&":"&TEXT('Games Schedule'!T31,"0")) | J30: ='Games Schedule'!X31 | K30: ='Games Schedule'!Y31
A32: 📌 This schedule auto-updates from 'Games Schedule' sheet. Print this for the latest version.

Sheet Rankings
A1: RANKINGS: all automatic from Games Schedule scores (sorted via Standings Engine; playoff games excluded). The box at B24:F37 is the jersey/division lookup Games Schedule uses; no typing on this tab. | H1: 📊 AUTO-SORTED RANKINGS (Excel only)
B2: Group A | C2: Points | D2: Goal For | E2: Goal Against | F2: Total Goal Difference | G2: Rank Score | I2: Code | J2: Team | K2: Pts | L2: GF | M2: GA | N2: GD
A3: A1 | B3: =IFERROR(INDEX('Standings Engine'!$A$4:$A$16,MATCH($A3,'Standings Engine'!$J$4:$J$16,0)),"") | C3: =IFERROR(INDEX('Standings Engine'!$D$4:$D$16,MATCH($A3,'Standings Engine'!$J$4:$J$16,0)),"") | D3: =IFERROR(INDEX('Standings Engine'!$E$4:$E$16,MATCH($A3,'Standings Engine'!$J$4:$J$16,0)),"") | E3: =IFERROR(INDEX('Standings Engine'!$F$4:$F$16,MATCH($A3,'Standings Engine'!$J$4:$J$16,0)),"") | F3: =IFERROR(INDEX('Standings Engine'!$G$4:$G$16,MATCH($A3,'Standings Engine'!$J$4:$J$16,0)),"") | G3: =IFERROR(INDEX('Standings Engine'!$H$4:$H$16,MATCH($A3,'Standings Engine'!$J$4:$J$16,0)),"") | H3: A1 | I3: {=IFERROR(_xlfn._xlws.SORT(_xlfn._xlws.FILTER(A3:F6,B3:B6<>""),{3,6},{-1,-1}),"")}
A4: A2 | B4: =IFERROR(INDEX('Standings Engine'!$A$4:$A$16,MATCH($A4,'Standings Engine'!$J$4:$J$16,0)),"") | C4: =IFERROR(INDEX('Standings Engine'!$D$4:$D$16,MATCH($A4,'Standings Engine'!$J$4:$J$16,0)),"") | D4: =IFERROR(INDEX('Standings Engine'!$E$4:$E$16,MATCH($A4,'Standings Engine'!$J$4:$J$16,0)),"") | E4: =IFERROR(INDEX('Standings Engine'!$F$4:$F$16,MATCH($A4,'Standings Engine'!$J$4:$J$16,0)),"") | F4: =IFERROR(INDEX('Standings Engine'!$G$4:$G$16,MATCH($A4,'Standings Engine'!$J$4:$J$16,0)),"") | G4: =IFERROR(INDEX('Standings Engine'!$H$4:$H$16,MATCH($A4,'Standings Engine'!$J$4:$J$16,0)),"") | H4: A2
A5: A3 | B5: =IFERROR(INDEX('Standings Engine'!$A$4:$A$16,MATCH($A5,'Standings Engine'!$J$4:$J$16,0)),"") | C5: =IFERROR(INDEX('Standings Engine'!$D$4:$D$16,MATCH($A5,'Standings Engine'!$J$4:$J$16,0)),"") | D5: =IFERROR(INDEX('Standings Engine'!$E$4:$E$16,MATCH($A5,'Standings Engine'!$J$4:$J$16,0)),"") | E5: =IFERROR(INDEX('Standings Engine'!$F$4:$F$16,MATCH($A5,'Standings Engine'!$J$4:$J$16,0)),"") | F5: =IFERROR(INDEX('Standings Engine'!$G$4:$G$16,MATCH($A5,'Standings Engine'!$J$4:$J$16,0)),"") | G5: =IFERROR(INDEX('Standings Engine'!$H$4:$H$16,MATCH($A5,'Standings Engine'!$J$4:$J$16,0)),"") | H5: A3
A6: A4 | B6: =IFERROR(INDEX('Standings Engine'!$A$4:$A$16,MATCH($A6,'Standings Engine'!$J$4:$J$16,0)),"") | C6: =IFERROR(INDEX('Standings Engine'!$D$4:$D$16,MATCH($A6,'Standings Engine'!$J$4:$J$16,0)),"") | D6: =IFERROR(INDEX('Standings Engine'!$E$4:$E$16,MATCH($A6,'Standings Engine'!$J$4:$J$16,0)),"") | E6: =IFERROR(INDEX('Standings Engine'!$F$4:$F$16,MATCH($A6,'Standings Engine'!$J$4:$J$16,0)),"") | F6: =IFERROR(INDEX('Standings Engine'!$G$4:$G$16,MATCH($A6,'Standings Engine'!$J$4:$J$16,0)),"") | G6: =IFERROR(INDEX('Standings Engine'!$H$4:$H$16,MATCH($A6,'Standings Engine'!$J$4:$J$16,0)),"") | H6: A4
B7: Check | C7: =SUM(C3:C6)
B9: Group B | C9: =C2 | D9: =D2 | E9: =E2 | F9: =F2 | I9: Code | J9: Team | K9: Pts | L9: GF | M9: GA | N9: GD
A10: B1 | B10: =IFERROR(INDEX('Standings Engine'!$A$4:$A$16,MATCH($A10,'Standings Engine'!$J$4:$J$16,0)),"") | C10: =IFERROR(INDEX('Standings Engine'!$D$4:$D$16,MATCH($A10,'Standings Engine'!$J$4:$J$16,0)),"") | D10: =IFERROR(INDEX('Standings Engine'!$E$4:$E$16,MATCH($A10,'Standings Engine'!$J$4:$J$16,0)),"") | E10: =IFERROR(INDEX('Standings Engine'!$F$4:$F$16,MATCH($A10,'Standings Engine'!$J$4:$J$16,0)),"") | F10: =IFERROR(INDEX('Standings Engine'!$G$4:$G$16,MATCH($A10,'Standings Engine'!$J$4:$J$16,0)),"") | G10: =IFERROR(INDEX('Standings Engine'!$H$4:$H$16,MATCH($A10,'Standings Engine'!$J$4:$J$16,0)),"") | H10: B1 | I10: {=IFERROR(_xlfn._xlws.SORT(_xlfn._xlws.FILTER(A10:F13,B10:B13<>""),{3,6},{-1,-1}),"")}
A11: B2 | B11: =IFERROR(INDEX('Standings Engine'!$A$4:$A$16,MATCH($A11,'Standings Engine'!$J$4:$J$16,0)),"") | C11: =IFERROR(INDEX('Standings Engine'!$D$4:$D$16,MATCH($A11,'Standings Engine'!$J$4:$J$16,0)),"") | D11: =IFERROR(INDEX('Standings Engine'!$E$4:$E$16,MATCH($A11,'Standings Engine'!$J$4:$J$16,0)),"") | E11: =IFERROR(INDEX('Standings Engine'!$F$4:$F$16,MATCH($A11,'Standings Engine'!$J$4:$J$16,0)),"") | F11: =IFERROR(INDEX('Standings Engine'!$G$4:$G$16,MATCH($A11,'Standings Engine'!$J$4:$J$16,0)),"") | G11: =IFERROR(INDEX('Standings Engine'!$H$4:$H$16,MATCH($A11,'Standings Engine'!$J$4:$J$16,0)),"") | H11: B2
A12: B3 | B12: =IFERROR(INDEX('Standings Engine'!$A$4:$A$16,MATCH($A12,'Standings Engine'!$J$4:$J$16,0)),"") | C12: =IFERROR(INDEX('Standings Engine'!$D$4:$D$16,MATCH($A12,'Standings Engine'!$J$4:$J$16,0)),"") | D12: =IFERROR(INDEX('Standings Engine'!$E$4:$E$16,MATCH($A12,'Standings Engine'!$J$4:$J$16,0)),"") | E12: =IFERROR(INDEX('Standings Engine'!$F$4:$F$16,MATCH($A12,'Standings Engine'!$J$4:$J$16,0)),"") | F12: =IFERROR(INDEX('Standings Engine'!$G$4:$G$16,MATCH($A12,'Standings Engine'!$J$4:$J$16,0)),"") | G12: =IFERROR(INDEX('Standings Engine'!$H$4:$H$16,MATCH($A12,'Standings Engine'!$J$4:$J$16,0)),"") | H12: B3
A13: B4 | B13: =IFERROR(INDEX('Standings Engine'!$A$4:$A$16,MATCH($A13,'Standings Engine'!$J$4:$J$16,0)),"") | C13: =IFERROR(INDEX('Standings Engine'!$D$4:$D$16,MATCH($A13,'Standings Engine'!$J$4:$J$16,0)),"") | D13: =IFERROR(INDEX('Standings Engine'!$E$4:$E$16,MATCH($A13,'Standings Engine'!$J$4:$J$16,0)),"") | E13: =IFERROR(INDEX('Standings Engine'!$F$4:$F$16,MATCH($A13,'Standings Engine'!$J$4:$J$16,0)),"") | F13: =IFERROR(INDEX('Standings Engine'!$G$4:$G$16,MATCH($A13,'Standings Engine'!$J$4:$J$16,0)),"") | G13: =IFERROR(INDEX('Standings Engine'!$H$4:$H$16,MATCH($A13,'Standings Engine'!$J$4:$J$16,0)),"") | H13: B4
B14: Check | C14: =SUM(C10:C13)
B16: Women | C16: =C9 | D16: =D9 | E16: =E9 | F16: =F9 | I16: Code | J16: Team | K16: Pts | L16: GF | M16: GA | N16: GD
A17: =IF('Format Engine'!$H$12=1,"W1","WA1") | B17: =IFERROR(INDEX('Standings Engine'!$A$4:$A$16,MATCH($A17,'Standings Engine'!$J$4:$J$16,0)),"") | C17: =IFERROR(INDEX('Standings Engine'!$D$4:$D$16,MATCH($A17,'Standings Engine'!$J$4:$J$16,0)),"") | D17: =IFERROR(INDEX('Standings Engine'!$E$4:$E$16,MATCH($A17,'Standings Engine'!$J$4:$J$16,0)),"") | E17: =IFERROR(INDEX('Standings Engine'!$F$4:$F$16,MATCH($A17,'Standings Engine'!$J$4:$J$16,0)),"") | F17: =IFERROR(INDEX('Standings Engine'!$G$4:$G$16,MATCH($A17,'Standings Engine'!$J$4:$J$16,0)),"") | G17: =IFERROR(INDEX('Standings Engine'!$H$4:$H$16,MATCH($A17,'Standings Engine'!$J$4:$J$16,0)),"") | H17: W1 | I17: {=IFERROR(_xlfn._xlws.SORT(_xlfn._xlws.FILTER(A17:F22,B17:B22<>""),{3,6},{-1,-1}),"")}
A18: =IF('Format Engine'!$H$12=1,"W2","WA2") | B18: =IFERROR(INDEX('Standings Engine'!$A$4:$A$16,MATCH($A18,'Standings Engine'!$J$4:$J$16,0)),"") | C18: =IFERROR(INDEX('Standings Engine'!$D$4:$D$16,MATCH($A18,'Standings Engine'!$J$4:$J$16,0)),"") | D18: =IFERROR(INDEX('Standings Engine'!$E$4:$E$16,MATCH($A18,'Standings Engine'!$J$4:$J$16,0)),"") | E18: =IFERROR(INDEX('Standings Engine'!$F$4:$F$16,MATCH($A18,'Standings Engine'!$J$4:$J$16,0)),"") | F18: =IFERROR(INDEX('Standings Engine'!$G$4:$G$16,MATCH($A18,'Standings Engine'!$J$4:$J$16,0)),"") | G18: =IFERROR(INDEX('Standings Engine'!$H$4:$H$16,MATCH($A18,'Standings Engine'!$J$4:$J$16,0)),"") | H18: W2
A19: =IF('Format Engine'!$H$12=1,"W3","WA3") | B19: =IFERROR(INDEX('Standings Engine'!$A$4:$A$16,MATCH($A19,'Standings Engine'!$J$4:$J$16,0)),"") | C19: =IFERROR(INDEX('Standings Engine'!$D$4:$D$16,MATCH($A19,'Standings Engine'!$J$4:$J$16,0)),"") | D19: =IFERROR(INDEX('Standings Engine'!$E$4:$E$16,MATCH($A19,'Standings Engine'!$J$4:$J$16,0)),"") | E19: =IFERROR(INDEX('Standings Engine'!$F$4:$F$16,MATCH($A19,'Standings Engine'!$J$4:$J$16,0)),"") | F19: =IFERROR(INDEX('Standings Engine'!$G$4:$G$16,MATCH($A19,'Standings Engine'!$J$4:$J$16,0)),"") | G19: =IFERROR(INDEX('Standings Engine'!$H$4:$H$16,MATCH($A19,'Standings Engine'!$J$4:$J$16,0)),"") | H19: W3
A20: =IF('Format Engine'!$H$12=1,"W4","WB1") | B20: =IFERROR(INDEX('Standings Engine'!$A$4:$A$16,MATCH($A20,'Standings Engine'!$J$4:$J$16,0)),"") | C20: =IFERROR(INDEX('Standings Engine'!$D$4:$D$16,MATCH($A20,'Standings Engine'!$J$4:$J$16,0)),"") | D20: =IFERROR(INDEX('Standings Engine'!$E$4:$E$16,MATCH($A20,'Standings Engine'!$J$4:$J$16,0)),"") | E20: =IFERROR(INDEX('Standings Engine'!$F$4:$F$16,MATCH($A20,'Standings Engine'!$J$4:$J$16,0)),"") | F20: =IFERROR(INDEX('Standings Engine'!$G$4:$G$16,MATCH($A20,'Standings Engine'!$J$4:$J$16,0)),"") | G20: =IFERROR(INDEX('Standings Engine'!$H$4:$H$16,MATCH($A20,'Standings Engine'!$J$4:$J$16,0)),"") | H20: W4
A21: =IF('Format Engine'!$H$12=1,"W5","WB2") | B21: =IFERROR(INDEX('Standings Engine'!$A$4:$A$16,MATCH($A21,'Standings Engine'!$J$4:$J$16,0)),"") | C21: =IFERROR(INDEX('Standings Engine'!$D$4:$D$16,MATCH($A21,'Standings Engine'!$J$4:$J$16,0)),"") | D21: =IFERROR(INDEX('Standings Engine'!$E$4:$E$16,MATCH($A21,'Standings Engine'!$J$4:$J$16,0)),"") | E21: =IFERROR(INDEX('Standings Engine'!$F$4:$F$16,MATCH($A21,'Standings Engine'!$J$4:$J$16,0)),"") | F21: =IFERROR(INDEX('Standings Engine'!$G$4:$G$16,MATCH($A21,'Standings Engine'!$J$4:$J$16,0)),"") | G21: =IFERROR(INDEX('Standings Engine'!$H$4:$H$16,MATCH($A21,'Standings Engine'!$J$4:$J$16,0)),"") | H21: W5
A22: =IF('Format Engine'!$H$12=1,"","WB3") | B22: =IF($A22="","",IFERROR(INDEX('Standings Engine'!$A$4:$A$16,MATCH($A22,'Standings Engine'!$J$4:$J$16,0)),"")) | C22: =IF($A22="","",IFERROR(INDEX('Standings Engine'!$D$4:$D$16,MATCH($A22,'Standings Engine'!$J$4:$J$16,0)),"")) | D22: =IF($A22="","",IFERROR(INDEX('Standings Engine'!$E$4:$E$16,MATCH($A22,'Standings Engine'!$J$4:$J$16,0)),"")) | E22: =IF($A22="","",IFERROR(INDEX('Standings Engine'!$F$4:$F$16,MATCH($A22,'Standings Engine'!$J$4:$J$16,0)),"")) | F22: =IF($A22="","",IFERROR(INDEX('Standings Engine'!$G$4:$G$16,MATCH($A22,'Standings Engine'!$J$4:$J$16,0)),"")) | G22: =IF($A22="","",IFERROR(INDEX('Standings Engine'!$H$4:$H$16,MATCH($A22,'Standings Engine'!$J$4:$J$16,0)),""))
I23: Games/Day tracking
B24: Team Name | C24: Division | D24: Group | E24: Jersey Color 1 | F24: Jersey Color 2 | I24: Team | J24: Thursday | K24: Friday | L24: Saturday | M24: Sunday | N24: Total
B25: ='Teams Master'!C2 | C25: =IFERROR(INDEX('Teams Master'!$D$2:$D$14,MATCH($B25,'Teams Master'!$C$2:$C$14,0)),"") | D25: =IFERROR(LEFT(INDEX('Teams Master'!$E$2:$E$14,MATCH($B25,'Teams Master'!$C$2:$C$14,0)),1),"") | E25: =IFERROR(INDEX('Teams Master'!$F$2:$F$14,MATCH($B25,'Teams Master'!$C$2:$C$14,0)),"") | F25: =IFERROR(INDEX('Teams Master'!$G$2:$G$14,MATCH($B25,'Teams Master'!$C$2:$C$14,0)),"") | I25: =B25 | J25: =COUNTIF('Games Schedule'!$N$5:$O$5,Rankings!$I25) | K25: =COUNTIF('Games Schedule'!$N$6:$O$11,Rankings!$I25) | L25: =COUNTIF('Games Schedule'!$N$12:$O$24,Rankings!$I25) | M25: =COUNTIF('Games Schedule'!$N$25:$O$26,Rankings!$I25) | N25: =SUM(J25:M25)
B26: ='Teams Master'!C3 | C26: =IFERROR(INDEX('Teams Master'!$D$2:$D$14,MATCH($B26,'Teams Master'!$C$2:$C$14,0)),"") | D26: =IFERROR(LEFT(INDEX('Teams Master'!$E$2:$E$14,MATCH($B26,'Teams Master'!$C$2:$C$14,0)),1),"") | E26: =IFERROR(INDEX('Teams Master'!$F$2:$F$14,MATCH($B26,'Teams Master'!$C$2:$C$14,0)),"") | F26: =IFERROR(INDEX('Teams Master'!$G$2:$G$14,MATCH($B26,'Teams Master'!$C$2:$C$14,0)),"") | I26: =B26 | J26: =COUNTIF('Games Schedule'!$N$5:$O$5,Rankings!$I26) | K26: =COUNTIF('Games Schedule'!$N$6:$O$11,Rankings!$I26) | L26: =COUNTIF('Games Schedule'!$N$12:$O$24,Rankings!$I26) | M26: =COUNTIF('Games Schedule'!$N$25:$O$26,Rankings!$I26) | N26: =SUM(J26:M26)
B27: ='Teams Master'!C4 | C27: =IFERROR(INDEX('Teams Master'!$D$2:$D$14,MATCH($B27,'Teams Master'!$C$2:$C$14,0)),"") | D27: =IFERROR(LEFT(INDEX('Teams Master'!$E$2:$E$14,MATCH($B27,'Teams Master'!$C$2:$C$14,0)),1),"") | E27: =IFERROR(INDEX('Teams Master'!$F$2:$F$14,MATCH($B27,'Teams Master'!$C$2:$C$14,0)),"") | F27: =IFERROR(INDEX('Teams Master'!$G$2:$G$14,MATCH($B27,'Teams Master'!$C$2:$C$14,0)),"") | I27: =B27 | J27: =COUNTIF('Games Schedule'!$N$5:$O$5,Rankings!$I27) | K27: =COUNTIF('Games Schedule'!$N$6:$O$11,Rankings!$I27) | L27: =COUNTIF('Games Schedule'!$N$12:$O$24,Rankings!$I27) | M27: =COUNTIF('Games Schedule'!$N$25:$O$26,Rankings!$I27) | N27: =SUM(J27:M27)
B28: ='Teams Master'!C5 | C28: =IFERROR(INDEX('Teams Master'!$D$2:$D$14,MATCH($B28,'Teams Master'!$C$2:$C$14,0)),"") | D28: =IFERROR(LEFT(INDEX('Teams Master'!$E$2:$E$14,MATCH($B28,'Teams Master'!$C$2:$C$14,0)),1),"") | E28: =IFERROR(INDEX('Teams Master'!$F$2:$F$14,MATCH($B28,'Teams Master'!$C$2:$C$14,0)),"") | F28: =IFERROR(INDEX('Teams Master'!$G$2:$G$14,MATCH($B28,'Teams Master'!$C$2:$C$14,0)),"") | I28: =B28 | J28: =COUNTIF('Games Schedule'!$N$5:$O$5,Rankings!$I28) | K28: =COUNTIF('Games Schedule'!$N$6:$O$11,Rankings!$I28) | L28: =COUNTIF('Games Schedule'!$N$12:$O$24,Rankings!$I28) | M28: =COUNTIF('Games Schedule'!$N$25:$O$26,Rankings!$I28) | N28: =SUM(J28:M28)
B29: ='Teams Master'!C6 | C29: =IFERROR(INDEX('Teams Master'!$D$2:$D$14,MATCH($B29,'Teams Master'!$C$2:$C$14,0)),"") | D29: =IFERROR(LEFT(INDEX('Teams Master'!$E$2:$E$14,MATCH($B29,'Teams Master'!$C$2:$C$14,0)),1),"") | E29: =IFERROR(INDEX('Teams Master'!$F$2:$F$14,MATCH($B29,'Teams Master'!$C$2:$C$14,0)),"") | F29: =IFERROR(INDEX('Teams Master'!$G$2:$G$14,MATCH($B29,'Teams Master'!$C$2:$C$14,0)),"") | I29: =B29 | J29: =COUNTIF('Games Schedule'!$N$5:$O$5,Rankings!$I29) | K29: =COUNTIF('Games Schedule'!$N$6:$O$11,Rankings!$I29) | L29: =COUNTIF('Games Schedule'!$N$12:$O$24,Rankings!$I29) | M29: =COUNTIF('Games Schedule'!$N$25:$O$26,Rankings!$I29) | N29: =SUM(J29:M29)
B30: ='Teams Master'!C7 | C30: =IFERROR(INDEX('Teams Master'!$D$2:$D$14,MATCH($B30,'Teams Master'!$C$2:$C$14,0)),"") | D30: =IFERROR(LEFT(INDEX('Teams Master'!$E$2:$E$14,MATCH($B30,'Teams Master'!$C$2:$C$14,0)),1),"") | E30: =IFERROR(INDEX('Teams Master'!$F$2:$F$14,MATCH($B30,'Teams Master'!$C$2:$C$14,0)),"") | F30: =IFERROR(INDEX('Teams Master'!$G$2:$G$14,MATCH($B30,'Teams Master'!$C$2:$C$14,0)),"") | I30: =B30 | J30: =COUNTIF('Games Schedule'!$N$5:$O$5,Rankings!$I30) | K30: =COUNTIF('Games Schedule'!$N$6:$O$11,Rankings!$I30) | L30: =COUNTIF('Games Schedule'!$N$12:$O$24,Rankings!$I30) | M30: =COUNTIF('Games Schedule'!$N$25:$O$26,Rankings!$I30) | N30: =SUM(J30:M30)
B31: ='Teams Master'!C8 | C31: =IFERROR(INDEX('Teams Master'!$D$2:$D$14,MATCH($B31,'Teams Master'!$C$2:$C$14,0)),"") | D31: =IFERROR(LEFT(INDEX('Teams Master'!$E$2:$E$14,MATCH($B31,'Teams Master'!$C$2:$C$14,0)),1),"") | E31: =IFERROR(INDEX('Teams Master'!$F$2:$F$14,MATCH($B31,'Teams Master'!$C$2:$C$14,0)),"") | F31: =IFERROR(INDEX('Teams Master'!$G$2:$G$14,MATCH($B31,'Teams Master'!$C$2:$C$14,0)),"") | I31: =B31 | J31: =COUNTIF('Games Schedule'!$N$5:$O$5,Rankings!$I31) | K31: =COUNTIF('Games Schedule'!$N$6:$O$11,Rankings!$I31) | L31: =COUNTIF('Games Schedule'!$N$12:$O$24,Rankings!$I31) | M31: =COUNTIF('Games Schedule'!$N$25:$O$26,Rankings!$I31) | N31: =SUM(J31:M31)
B32: ='Teams Master'!C9 | C32: =IFERROR(INDEX('Teams Master'!$D$2:$D$14,MATCH($B32,'Teams Master'!$C$2:$C$14,0)),"") | D32: =IFERROR(LEFT(INDEX('Teams Master'!$E$2:$E$14,MATCH($B32,'Teams Master'!$C$2:$C$14,0)),1),"") | E32: =IFERROR(INDEX('Teams Master'!$F$2:$F$14,MATCH($B32,'Teams Master'!$C$2:$C$14,0)),"") | F32: =IFERROR(INDEX('Teams Master'!$G$2:$G$14,MATCH($B32,'Teams Master'!$C$2:$C$14,0)),"") | I32: =B32 | J32: =COUNTIF('Games Schedule'!$N$5:$O$5,Rankings!$I32) | K32: =COUNTIF('Games Schedule'!$N$6:$O$11,Rankings!$I32) | L32: =COUNTIF('Games Schedule'!$N$12:$O$24,Rankings!$I32) | M32: =COUNTIF('Games Schedule'!$N$25:$O$26,Rankings!$I32) | N32: =SUM(J32:M32)
B33: ='Teams Master'!C10 | C33: =IFERROR(INDEX('Teams Master'!$D$2:$D$14,MATCH($B33,'Teams Master'!$C$2:$C$14,0)),"") | D33: =IFERROR(LEFT(INDEX('Teams Master'!$E$2:$E$14,MATCH($B33,'Teams Master'!$C$2:$C$14,0)),1),"") | E33: =IFERROR(INDEX('Teams Master'!$F$2:$F$14,MATCH($B33,'Teams Master'!$C$2:$C$14,0)),"") | F33: =IFERROR(INDEX('Teams Master'!$G$2:$G$14,MATCH($B33,'Teams Master'!$C$2:$C$14,0)),"") | I33: =B33 | J33: =COUNTIF('Games Schedule'!$N$5:$O$5,Rankings!$I33) | K33: =COUNTIF('Games Schedule'!$N$6:$O$11,Rankings!$I33) | L33: =COUNTIF('Games Schedule'!$N$12:$O$24,Rankings!$I33) | M33: =COUNTIF('Games Schedule'!$N$25:$O$26,Rankings!$I33) | N33: =SUM(J33:M33)
B34: ='Teams Master'!C11 | C34: =IFERROR(INDEX('Teams Master'!$D$2:$D$14,MATCH($B34,'Teams Master'!$C$2:$C$14,0)),"") | D34: =IFERROR(LEFT(INDEX('Teams Master'!$E$2:$E$14,MATCH($B34,'Teams Master'!$C$2:$C$14,0)),1),"") | E34: =IFERROR(INDEX('Teams Master'!$F$2:$F$14,MATCH($B34,'Teams Master'!$C$2:$C$14,0)),"") | F34: =IFERROR(INDEX('Teams Master'!$G$2:$G$14,MATCH($B34,'Teams Master'!$C$2:$C$14,0)),"") | I34: =B34 | J34: =COUNTIF('Games Schedule'!$N$5:$O$5,Rankings!$I34) | K34: =COUNTIF('Games Schedule'!$N$6:$O$11,Rankings!$I34) | L34: =COUNTIF('Games Schedule'!$N$12:$O$24,Rankings!$I34) | M34: =COUNTIF('Games Schedule'!$N$25:$O$26,Rankings!$I34) | N34: =SUM(J34:M34)
B35: ='Teams Master'!C12 | C35: =IFERROR(INDEX('Teams Master'!$D$2:$D$14,MATCH($B35,'Teams Master'!$C$2:$C$14,0)),"") | D35: =IFERROR(LEFT(INDEX('Teams Master'!$E$2:$E$14,MATCH($B35,'Teams Master'!$C$2:$C$14,0)),1),"") | E35: =IFERROR(INDEX('Teams Master'!$F$2:$F$14,MATCH($B35,'Teams Master'!$C$2:$C$14,0)),"") | F35: =IFERROR(INDEX('Teams Master'!$G$2:$G$14,MATCH($B35,'Teams Master'!$C$2:$C$14,0)),"") | I35: =B35 | J35: =COUNTIF('Games Schedule'!$N$5:$O$5,Rankings!$I35) | K35: =COUNTIF('Games Schedule'!$N$6:$O$11,Rankings!$I35) | L35: =COUNTIF('Games Schedule'!$N$12:$O$24,Rankings!$I35) | M35: =COUNTIF('Games Schedule'!$N$25:$O$26,Rankings!$I35) | N35: =SUM(J35:M35)
B36: ='Teams Master'!C13 | C36: =IFERROR(INDEX('Teams Master'!$D$2:$D$14,MATCH($B36,'Teams Master'!$C$2:$C$14,0)),"") | D36: =IFERROR(LEFT(INDEX('Teams Master'!$E$2:$E$14,MATCH($B36,'Teams Master'!$C$2:$C$14,0)),1),"") | E36: =IFERROR(INDEX('Teams Master'!$F$2:$F$14,MATCH($B36,'Teams Master'!$C$2:$C$14,0)),"") | F36: =IFERROR(INDEX('Teams Master'!$G$2:$G$14,MATCH($B36,'Teams Master'!$C$2:$C$14,0)),"") | I36: =B36 | J36: =COUNTIF('Games Schedule'!$N$5:$O$5,Rankings!$I36) | K36: =COUNTIF('Games Schedule'!$N$6:$O$11,Rankings!$I36) | L36: =COUNTIF('Games Schedule'!$N$12:$O$24,Rankings!$I36) | M36: =COUNTIF('Games Schedule'!$N$25:$O$26,Rankings!$I36) | N36: =SUM(J36:M36)
B37: ='Teams Master'!C14 | C37: =IFERROR(INDEX('Teams Master'!$D$2:$D$14,MATCH($B37,'Teams Master'!$C$2:$C$14,0)),"") | D37: =IFERROR(LEFT(INDEX('Teams Master'!$E$2:$E$14,MATCH($B37,'Teams Master'!$C$2:$C$14,0)),1),"") | E37: =IFERROR(INDEX('Teams Master'!$F$2:$F$14,MATCH($B37,'Teams Master'!$C$2:$C$14,0)),"") | F37: =IFERROR(INDEX('Teams Master'!$G$2:$G$14,MATCH($B37,'Teams Master'!$C$2:$C$14,0)),"") | I37: =B37 | J37: =COUNTIF('Games Schedule'!$N$5:$O$5,Rankings!$I37) | K37: =COUNTIF('Games Schedule'!$N$6:$O$11,Rankings!$I37) | L37: =COUNTIF('Games Schedule'!$N$12:$O$24,Rankings!$I37) | M37: =COUNTIF('Games Schedule'!$N$25:$O$26,Rankings!$I37) | N37: =SUM(J37:M37)
B40: Check Total Goals
B41: Group A | C41: =SUM(D3:D6)-'Games Schedule'!C48
B42: Group B | C42: =SUM(D10:D13)-'Games Schedule'!C49
B43: Women | C43: =SUM(D17:D21)-'Games Schedule'!C50

Sheet Final Rankings
B2: FINAL TOURNAMENT RANKINGS | E2: TOURNAMENT AWARDS
B3: Everything on this tab auto-fills from game results, standings and votes: nothing to type here.
B4: MEN'S DIVISION | E4: MEN'S AWARDS
B5: 🥇 Gold | C5: =I20 | E5: MVP | F5: =IFERROR(IF('MVP Voting'!B102<>"",'MVP Voting'!B102&" ("&'MVP Voting'!C102&")","No votes yet"),"No votes yet")
B6: 🥈 Silver | C6: =I21 | E6: MVG | F6: =IFERROR(IF('MVP Voting'!B104<>"",'MVP Voting'!B104&" ("&'MVP Voting'!C104&")","No votes yet"),"No votes yet")
B7: 🥉 Bronze | C7: =I22 | E7: Top Scorer | F7: =IFERROR('Stats & MVP'!B6&" ("&'Stats & MVP'!C6&")","")
B8: 4th | C8: =I23 | E8: Top Scorer Goals | F8: =IFERROR('Stats & MVP'!D6&" Goals","")
B9: 5th | C9: =I24
B10: 6th | C10: =I25
B11: 7th | C11: =I26
B12: 8th | C12: =I27
B14: WOMEN'S DIVISION | E14: WOMEN'S AWARDS
B15: 🥇 Gold | C15: =I30 | E15: MVP | F15: =IFERROR(IF('MVP Voting'!B103<>"",'MVP Voting'!B103&" ("&'MVP Voting'!C103&")","No votes yet"),"No votes yet")
B16: 🥈 Silver | C16: =I31 | E16: MVG | F16: =IFERROR(IF('MVP Voting'!B105<>"",'MVP Voting'!B105&" ("&'MVP Voting'!C105&")","No votes yet"),"No votes yet") | H16: FINAL PLACEMENTS (auto-computed from game results)
B17: 🥉 Bronze | C17: =I32 | E17: Top Scorer | F17: =IFERROR('Stats & MVP'!B15&" ("&'Stats & MVP'!C15&")","") | H17: Men: medal/placement games (G23-G27). Women: final (G26) + group ranking.
B18: 4th | C18: =I33 | E18: Top Scorer Goals | F18: =IFERROR('Stats & MVP'!D15&" Goals","")
B19: 5th | C19: =I34 | H19: MEN'S PLACEMENTS
B20: 6th | C20: =I35 | H20: 1st (Gold): | I20: {=IF(COUNTIFS('Games Schedule'!$I$5:$I$31,"M",'Games Schedule'!$J$5:$J$31,"P",'Games Schedule'!$K$5:$K$31,1,'Games Schedule'!$S$5:$S$31,"<>",'Games Schedule'!$T$5:$T$31,"<>")=0,"",IFERROR(INDEX(IF('Games Schedule'!$S$5:$S$31>'Games Schedule'!$T$5:$T$31,'Games Schedule'!$N$5:$N$31,'Games Schedule'!$O$5:$O$31),MATCH(1,('Games Schedule'!$I$5:$I$31="M")*('Games Schedule'!$J$5:$J$31="P")*('Games Schedule'!$K$5:$K$31=1),0)),""))}
B21: GROUP STAGE STANDINGS (Auto-calculated) | H21: 2nd (Silver): | I21: {=IF(COUNTIFS('Games Schedule'!$I$5:$I$31,"M",'Games Schedule'!$J$5:$J$31,"P",'Games Schedule'!$K$5:$K$31,1,'Games Schedule'!$S$5:$S$31,"<>",'Games Schedule'!$T$5:$T$31,"<>")=0,"",IFERROR(INDEX(IF('Games Schedule'!$S$5:$S$31>'Games Schedule'!$T$5:$T$31,'Games Schedule'!$O$5:$O$31,'Games Schedule'!$N$5:$N$31),MATCH(1,('Games Schedule'!$I$5:$I$31="M")*('Games Schedule'!$J$5:$J$31="P")*('Games Schedule'!$K$5:$K$31=1),0)),""))}
H22: 3rd (Bronze): | I22: {=IF(COUNTIFS('Games Schedule'!$I$5:$I$31,"M",'Games Schedule'!$J$5:$J$31,"P",'Games Schedule'!$K$5:$K$31,3,'Games Schedule'!$S$5:$S$31,"<>",'Games Schedule'!$T$5:$T$31,"<>")=0,"",IFERROR(INDEX(IF('Games Schedule'!$S$5:$S$31>'Games Schedule'!$T$5:$T$31,'Games Schedule'!$N$5:$N$31,'Games Schedule'!$O$5:$O$31),MATCH(1,('Games Schedule'!$I$5:$I$31="M")*('Games Schedule'!$J$5:$J$31="P")*('Games Schedule'!$K$5:$K$31=3),0)),""))}
B23: Group A | D23: Group B | H23: 4th: | I23: {=IF(COUNTIFS('Games Schedule'!$I$5:$I$31,"M",'Games Schedule'!$J$5:$J$31,"P",'Games Schedule'!$K$5:$K$31,3,'Games Schedule'!$S$5:$S$31,"<>",'Games Schedule'!$T$5:$T$31,"<>")=0,"",IFERROR(INDEX(IF('Games Schedule'!$S$5:$S$31>'Games Schedule'!$T$5:$T$31,'Games Schedule'!$O$5:$O$31,'Games Schedule'!$N$5:$N$31),MATCH(1,('Games Schedule'!$I$5:$I$31="M")*('Games Schedule'!$J$5:$J$31="P")*('Games Schedule'!$K$5:$K$31=3),0)),""))}
B24: Team | C24: Points | D24: Team | E24: Points | H24: 5th: | I24: {=IF(COUNTIFS('Games Schedule'!$I$5:$I$31,"M",'Games Schedule'!$J$5:$J$31,"P",'Games Schedule'!$K$5:$K$31,5,'Games Schedule'!$S$5:$S$31,"<>",'Games Schedule'!$T$5:$T$31,"<>")=0,"",IFERROR(INDEX(IF('Games Schedule'!$S$5:$S$31>'Games Schedule'!$T$5:$T$31,'Games Schedule'!$N$5:$N$31,'Games Schedule'!$O$5:$O$31),MATCH(1,('Games Schedule'!$I$5:$I$31="M")*('Games Schedule'!$J$5:$J$31="P")*('Games Schedule'!$K$5:$K$31=5),0)),""))}
